Workbook
Name IQ_CH: 110000
Name IQ_CQ: 5000
Name IQ_CY: 10000
Name IQ_DAILY: 500000
Name IQ_FH: 100000
Name IQ_FQ: 500
Name IQ_FY: 1000
Name IQ_LTM: 2000
Name IQ_MONTH: 15000
Name IQ_NTM: 6000
Name IQ_WEEK: 50000
Name IQ_YTD: 3000

Sheet Staffing_2026
D1: Forecast | E1: Forecast | F1: Forecast | G1: Forecast | H1: Forecast | I1: Forecast | J1: Forecast | K1: Forecast | L1: Forecast | M1: Forecast | N1: Forecast | O1: Forecast
A2: Name | B2: POC | C2: Service | D2: Jan | E2: Feb | F2: Mar | G2: Apr | H2: May | I2: Jun | J2: Jul | K2: Aug | L2: Sep | M2: Oct | N2: Nov | O2: Dec | P2: Total | Q2: Comments | R2: Renewal Confidence | S2: Group | T2: Sub-Group
C3: Staffing | T3: Secured
C4: Staffing | T4: Secured
C5: Staffing | T5: Secured
C6: Staffing | T6: Secured
C7: Staffing | T7: Secured
C8: Staffing | T8: Secured
C9: Staffing | T9: Secured
C10: Staffing | T10: Secured
C11: Staffing | T11: Secured
C12: Staffing | T12: Secured
A13: Subtotal- Secured | D13: =SUM(D3:D12) -> 0 | E13: =SUM(E3:E12) -> 0 | F13: =SUM(F3:F12) -> 0 | G13: =SUM(G3:G12) -> 0 | H13: =SUM(H3:H12) -> 0 | I13: =SUM(I3:I12) -> 0 | J13: =SUM(J3:J12) -> 0 | K13: =SUM(K3:K12) -> 0 | ... P13: =SUM(P3:P12) -> 0
C15: Staffing
C16: Staffing | T16: Projected
C17: Staffing | T17: Projected
C18: Staffing | T18: Projected
C19: Staffing | T19: Projected
C20: Staffing | T20: Projected
C21: Staffing | T21: Projected
C22: Staffing | T22: Projected
C23: Staffing | T23: Projected
C24: Staffing | T24: Projected
C25: Staffing | T25: Projected
C26: Staffing | T26: Projected
A27: Subtotal- Projected | D27: =SUM(D15:D26) -> 0 | E27: =SUM(E15:E26) -> 0 | F27: =SUM(F15:F26) -> 0 | G27: =SUM(G15:G26) -> 0 | H27: =SUM(H15:H26) -> 0 | I27: =SUM(I15:I26) -> 0 | J27: =SUM(J15:J26) -> 0 | K27: =SUM(K15:K26) -> 0 | ... P27: =SUM(P15:P26) -> 0
A29: Grand Total | D29: =+D13+D27 -> 0 | E29: =+E13+E27 -> 0 | F29: =+F13+F27 -> 0 | G29: =+G13+G27 -> 0 | H29: =+H13+H27 -> 0 | I29: =+I13+I27 -> 0 | J29: =+J13+J27 -> 0 | K29: =+K13+K27 -> 0 | ... P29: =+P13+P27 -> 0

Sheet Staffing_Backup_260218
D1: Forecast | E1: Forecast | F1: Forecast | G1: Forecast | H1: Forecast | I1: Forecast | J1: Forecast | K1: Forecast | L1: Forecast | M1: Forecast | N1: Forecast | O1: Forecast
A2: Name | B2: POC | C2: Service | D2: 46023 | E2: 46054 | F2: 46082 | G2: 46113 | H2: 46143 | I2: 46174 | J2: 46204 | K2: 46235 | L2: 46266 | M2: 46296 | N2: 46327 | O2: 46357 | P2: Total Revenue | Q2: Comments | R2: Renewal Confidence | S2: Group | T2: Sub-Group
A3: Staffing
A4: HPE Ami Noss | B4: Manmeet | C4: Staffing | D4: 20276 | E4: 19180 | F4: 23290 | G4: 20139 | H4: 22194 | I4: 22194 | J4: 20276 | K4: 23290 | L4: 20139 | M4: 22194 | N4: 20139 | O4: 19180 | P4: {=SUMPRODUCT((D$1:O$1<>"Margin")*(D$1:O$1<>"Salary_$600")*D4:O4)} -> 252491 | Q4: SOW for renewal has been submitted | R4: 100% | S4: HPE | T4: ds_StaffingT01
A5: HPE Rebecca Wissinger | B5: Manmeet | C5: Staffing | D5: 11100 | E5: 10500 | F5: 12750 | G5: 11025 | H5: 12150 | I5: 12150 | J5: 11100 | K5: 12750 | L5: 11025 | M5: 12150 | N5: 11025 | O5: 10500 | P5: {=SUMPRODUCT((D$1:O$1<>"Margin")*(D$1:O$1<>"Salary_$600")*D5:O5)} -> 138225 | Q5: SOW valid until Oct 31, 2026 | R5: 100% | S5: HPE | T5: ds_StaffingT01
A6: HPE Budget Mgmt | B6: Manmeet | C6: Staffing | D6: 10656 | E6: 10080 | F6: 12240 | G6: 10584 | H6: 11664 | I6: 11664 | J6: 10656 | K6: 12240 | L6: 10584 | M6: 11664 | N6: 10584 | O6: 10080 | P6: {=SUMPRODUCT((D$1:O$1<>"Margin")*(D$1:O$1<>"Salary_$600")*D6:O6)} -> 132696 | Q6: SOW valid until Apr 30, 2026 | R6: 100% | S6: HPE | T6: ds_StaffingT01
A7: HPE Tech Compliance | B7: Manmeet | C7: Staffing | D7: 18216 | E7: 17231 | F7: 20924 | G7: 18093 | H7: 19939 | I7: 19939 | J7: 18216 | K7: 20924 | L7: 18093 | M7: 19939 | N7: 18093 | O7: 17231 | P7: {=SUMPRODUCT((D$1:O$1<>"Margin")*(D$1:O$1<>"Salary_$600")*D7:O7)} -> 226838 | Q7: SOW valid until Jan 31, 2026 | R7: 100% | S7: HPE | T7: ds_StaffingT01
A8: HPE Data Foundation | B8: Manmeet | C8: Staffing | D8: 30932 | E8: 29260 | F8: 35530 | G8: 30723 | H8: 33858 | I8: 33858 | J8: 30932 | K8: 35530 | L8: 30723 | M8: 33858 | N8: 30723 | O8: 29260 | P8: {=SUMPRODUCT((D$1:O$1<>"Margin")*(D$1:O$1<>"Salary_$600")*D8:O8)} -> 385187 | Q8: SOW for renewal has been submitted | R8: 100% | S8: HPE | T8: ds_StaffingT01
A9: HPE Marketing Automation | B9: Manmeet | C9: Staffing | D9: 14060 | E9: 13300 | F9: 16150 | G9: 13965 | H9: 15390 | I9: 15390 | J9: 14060 | K9: 16150 | L9: 13965 | M9: 15390 | N9: 13965 | O9: 13300 | P9: {=SUMPRODUCT((D$1:O$1<>"Margin")*(D$1:O$1<>"Salary_$600")*D9:O9)} -> 175085 | Q9: SOW valid until Jan 31, 2026 | R9: 100% | S9: HPE | T9: ds_StaffingT01
A10: Marvell India Staffing | B10: Sunil/Neeraj | C10: Staffing | D10: 15453 | E10: 14617 | F10: 17750 | G10: 15348 | H10: 16914 | I10: 16914 | J10: 15453 | K10: 17750 | L10: 15348 | M10: 16914 | N10: 15348 | O10: 14617 | P10: {=SUMPRODUCT((D$1:O$1<>"Margin")*(D$1:O$1<>"Salary_$600")*D10:O10)} -> 192426 | Q10: Contract renewed valid till Jan 31, 2026 | R10: 100% | S10: Marvell India | T10: ds_StaffingT01
A11: Azu Solutions | B11: Pankaj/Neeraj | C11: Staffing | P11: {=SUMPRODUCT((D$1:O$1<>"Margin")*(D$1:O$1<>"Salary_$600")*D11:O11)} -> 0 | Q11: SOW valid until Mar 31, 2026 | R11: 100% | S11: AZU Solutions | T11: ds_StaffingT01
A12: Databricks SEO Content Strategist | B12: Manmeet | C12: Staffing | D12: 14208 | E12: 13440 | F12: 16320 | G12: 14112 | H12: 15552 | I12: 15552 | J12: 14208 | K12: 16320 | L12: 1536 | M12: 0 | N12: 0 | O12: 0 | P12: {=SUMPRODUCT((D$1:O$1<>"Margin")*(D$1:O$1<>"Salary_$600")*D12:O12)} -> 121248 | Q12: SOW valid until Feb 28, 2026 | R12: 100% | S12: Databricks | T12: ds_StaffingT01
A13: JSG | B13: Wendy | C13: Staffing | D13: 4588 | E13: 4340 | F13: 5270 | G13: 4557 | H13: 5022 | I13: 5022 | J13: 4588 | K13: 5270 | L13: 4557 | M13: 5022 | N13: 4557 | O13: 4340 | P13: {=SUMPRODUCT((D$1:O$1<>"Margin")*(D$1:O$1<>"Salary_$600")*D13:O13)} -> 57133 | R13: 100% | S13: JSG | T13: ds_StaffingT02
A14: Mastek | B14: Wendy | C14: Staffing | D14: 10804 | E14: 10220 | F14: 12410 | G14: 10731 | H14: 11826 | I14: 11826 | J14: 13432 | K14: 0 | L14: 0 | M14: 0 | N14: 0 | O14: 0 | P14: {=SUMPRODUCT((D$1:O$1<>"Margin")*(D$1:O$1<>"Salary_$600")*D14:O14)} -> 81249 | R14: 100% | S14: Mastek | T14: ds_StaffingT02
A15: Matchpoint Solutions | B15: Wendy | C15: Staffing | D15: 6480 | E15: 12600 | F15: 15300 | G15: 13230 | H15: 14580 | I15: 14580 | J15: 5760 | K15: 0 | L15: 0 | M15: 0 | N15: 0 | O15: 0 | P15: {=SUMPRODUCT((D$1:O$1<>"Margin")*(D$1:O$1<>"Salary_$600")*D15:O15)} -> 82530 | R15: 100% | S15: MatchPoint Solutions | T15: ds_StaffingT02
A16: Maxonic | B16: Wendy | C16: Staffing | D16: 75611 | E16: 69485 | F16: 69376 | G16: 27481 | H16: 22062 | I16: 12312 | J16: 11248 | K16: 1216 | L16: 0 | M16: 0 | N16: 0 | O16: 0 | P16: {=SUMPRODUCT((D$1:O$1<>"Margin")*(D$1:O$1<>"Salary_$600")*D16:O16)} -> 288791 | R16: 100% | S16: Maxonic | T16: ds_StaffingT02
A17: Technology Partners | B17: Wendy | C17: Staffing | D17: 740 | E17: 700 | F17: 850 | G17: 735 | H17: 810 | I17: 810 | J17: 740 | K17: 850 | L17: 735 | M17: 810 | N17: 735 | O17: 700 | P17: {=SUMPRODUCT((D$1:O$1<>"Margin")*(D$1:O$1<>"Salary_$600")*D17:O17)} -> 9215 | R17: 100% | S17: Technology Partners | T17: ds_StaffingT02
A18: Vdart | B18: Wendy | C18: Staffing | D18: 8880 | E18: 8400 | F18: 10200 | G18: 8820 | H18: 9720 | I18: 10560 | J18: 0 | K18: 0 | L18: 0 | M18: 0 | N18: 0 | O18: 0 | P18: {=SUMPRODUCT((D$1:O$1<>"Margin")*(D$1:O$1<>"Salary_$600")*D18:O18)} -> 56580 | S18: Vdart | T18: ds_StaffingT02
A19: Sub-Total : Secured | D19: =SUM(D4:D18) -> 242004 | E19: =SUM(E4:E18) -> 233353 | F19: =SUM(F4:F18) -> 268360 | G19: =SUM(G4:G18) -> 199543 | H19: =SUM(H4:H18) -> 211681 | I19: =SUM(I4:I18) -> 202771 | J19: =SUM(J4:J18) -> 170669 | K19: =SUM(K4:K18) -> 162290 | ... P19: =SUM(P4:P18) -> 2199694
A20: Maxonic | B20: Pankaj/Wendy | C20: Staffing | D20: 12303 | E20: 11638 | F20: 14132 | G20: 24440 | H20: 13467 | I20: 26934 | J20: 12303 | K20: 28264 | L20: 12220 | M20: 13467 | N20: 12220 | O20: 0 | P20: {=SUMPRODUCT((D$1:O$1<>"Margin")*(D$1:O$1<>"Salary_$600")*D20:O20)} -> 181388 | S20: Maxonic | T20: ds_StaffingT03
A21: AZU Solutions | B21: Pankaj/Neeraj | C21: Staffing | D21: 0 | E21: 11200 | F21: 13600 | G21: 11760 | H21: 12960 | I21: 25920 | J21: 11840 | K21: 0 | L21: 11760 | M21: 12960 | N21: 0 | O21: 0 | P21: {=SUMPRODUCT((D$1:O$1<>"Margin")*(D$1:O$1<>"Salary_$600")*D21:O21)} -> 112000 | S21: AZU Solutions | T21: ds_StaffingT03
A22: MatchPoint Solutions | B22: Pankaj/Wendy | C22: Staffing | D22: 0 | E22: 10500 | F22: 12750 | G22: 11025 | H22: 12150 | I22: 12150 | J22: 11100 | K22: 12750 | L22: 11025 | M22: 12150 | N22: 0 | O22: 0 | P22: {=SUMPRODUCT((D$1:O$1<>"Margin")*(D$1:O$1<>"Salary_$600")*D22:O22)} -> 105600 | S22: MatchPoint Solutions | T22: ds_StaffingT03
A23: The Mice Group | B23: Pankaj/Wendy | C23: Staffing | D23: 0 | E23: 0 | F23: 0 | G23: 11760 | H23: 12960 | I23: 12960 | J23: 11840 | K23: 13600 | L23: 11760 | M23: 0 | N23: 0 | O23: 0 | P23: {=SUMPRODUCT((D$1:O$1<>"Margin")*(D$1:O$1<>"Salary_$600")*D23:O23)} -> 74880 | S23: The Mice Group | T23: ds_StaffingT03
A24: Technology Partners | B24: Shashank/Wendy | C24: Staffing | D24: 3088 | E24: 0 | F24: 850 | G24: 1470 | H24: 3240 | I24: 3240 | J24: 2960 | K24: 4250 | L24: 3675 | M24: 4860 | N24: 4410 | O24: 4900 | P24: {=SUMPRODUCT((D$1:O$1<>"Margin")*(D$1:O$1<>"Salary_$600")*D24:O24)} -> 36943 | S24: Technology Partners | T24: ds_StaffingT03
A25: VanderHouwen | B25: Shashank/Wendy | C25: Staffing | D25: 45297 | E25: 0 | F25: 13600 | G25: 23520 | H25: 51840 | I25: 51840 | J25: 47360 | K25: 68000 | L25: 58800 | M25: 77760 | N25: 70560 | O25: 78400 | P25: {=SUMPRODUCT((D$1:O$1<>"Margin")*(D$1:O$1<>"Salary_$600")*D25:O25)} -> 586977 | S25: VanderHouwen | T25: ds_StaffingT03
A26: JSG | B26: Shashank/Wendy | C26: Staffing | D26: 10710 | E26: 868 | F26: 2108 | G26: 1823 | H26: 3013 | I26: 3013 | J26: 2753 | K26: 3162 | L26: 2734 | M26: 3013 | N26: 2734 | O26: 2604 | P26: {=SUMPRODUCT((D$1:O$1<>"Margin")*(D$1:O$1<>"Salary_$600")*D26:O26)} -> 38535 | S26: JSG | T26: ds_StaffingT03
A27: Red Oak | B27: Shashank/Wendy | C27: Staffing | D27: 4257 | E27: 700 | F27: 1700 | G27: 2940 | H27: 3240 | I27: 4860 | J27: 5180 | K27: 6800 | L27: 5880 | M27: 7290 | N27: 6615 | O27: 2100 | P27: {=SUMPRODUCT((D$1:O$1<>"Margin")*(D$1:O$1<>"Salary_$600")*D27:O27)} -> 51562 | S27: Red Oak | T27: ds_StaffingT03
A28: Manpower Group | B28: Shashank/Wendy | C28: Staffing | D28: 22278 | E28: 0 | F28: 12750 | G28: 22050 | H28: 24300 | I28: 24300 | J28: 22200 | K28: 25500 | L28: 33075 | M28: 36450 | N28: 33075 | O28: 31500 | P28: {=SUMPRODUCT((D$1:O$1<>"Margin")*(D$1:O$1<>"Salary_$600")*D28:O28)} -> 287478 | S28: Manpower Group | T28: ds_StaffingT03
A29: Trans American (Mastek) | B29: Shashank/Wendy | C29: Staffing | D29: 0 | E29: 0 | F29: 0 | G29: 0 | H29: 0 | I29: 0 | J29: 0 | K29: 0 | L29: 0 | M29: 0 | N29: 0 | O29: 0 | P29: {=SUMPRODUCT((D$1:O$1<>"Margin")*(D$1:O$1<>"Salary_$600")*D29:O29)} -> 0 | S29: Mastek | T29: ds_StaffingT03
A30: Vdart | B30: Shashank/Wendy | C30: Staffing | D30: 0 | E30: 0 | F30: 0 | G30: 0 | H30: 0 | I30: 0 | J30: 0 | K30: 0 | L30: 0 | M30: 0 | N30: 0 | O30: 0 | P30: {=SUMPRODUCT((D$1:O$1<>"Margin")*(D$1:O$1<>"Salary_$600")*D30:O30)} -> 0 | S30: Vdart | T30: ds_StaffingT03
A31: New Logos | B31: Shashank/Wendy | C31: Staffing | D31: 16060 | E31: 0 | F31: 0 | G31: 0 | H31: 25272 | I31: 25272 | J31: 23088 | K31: 26520 | L31: 22932 | M31: 25272 | N31: 22932 | O31: 21840 | P31: {=SUMPRODUCT((D$1:O$1<>"Margin")*(D$1:O$1<>"Salary_$600")*D31:O31)} -> 209188 | S31: New Logos | T31: ds_StaffingT03
A32: Sub-Total : Projection (Wendy) | D32: =SUM(D20:D31) -> 113993 | E32: =SUM(E20:E31) -> 34906 | F32: =SUM(F20:F31) -> 71490 | G32: =SUM(G20:G31) -> 110788 | H32: =SUM(H20:H31) -> 162442 | I32: =SUM(I20:I31) -> 190489 | J32: =SUM(J20:J31) -> 150624 | K32: =SUM(K20:K31) -> 188846 | ... P32: =SUM(P20:P31) -> 1684551
A33: Total Staffing (Secured + Projection) | D33: =+D19+D32 -> 355997 | E33: =+E19+E32 -> 268259 | F33: =+F19+F32 -> 339850 | G33: =+G19+G32 -> 310331 | H33: =+H19+H32 -> 374123 | I33: =+I19+I32 -> 393260 | J33: =+J19+J32 -> 321293 | K33: =+K19+K32 -> 351136 | ... P33: =+P19+P32 -> 3884245

Sheet Sales by Customer- 2026
D1: Actual | E1: Salary_$600 | F1: Margin | G1: Actual | H1: Salary_$600 | I1: Margin | J1: Actual | K1: Salary_$600 | L1: Margin | M1: Actual | N1: Salary_$600 | O1: Margin | P1: Actual | Q1: Salary_$600 | R1: Margin | S1: Forecast | T1: Salary_$600 | U1: Margin | V1: Forecast | W1: Salary_$600 | X1: Margin | Y1: Forecast | Z1: Salary_$600 | AA1: Margin | AB1: Forecast | AC1: Salary_$600 | AD1: Margin | AE1: Forecast | AF1: Salary_$600 | AG1: Margin | AH1: Forecast | AI1: Salary_$600 | AJ1: Margin | AK1: Forecast | AL1: Salary_$600 | AM1: Margin
A2: Name | B2: POC | C2: Service | D2: 46023 | E2: 46023 | F2: 46023 | G2: 46054 | H2: 46054 | I2: 46054 | J2: 46082 | K2: 46082 | L2: 46082 | M2: 46113 | N2: 46113 | O2: 46113 | P2: 46143 | Q2: 46143 | R2: 46143 | S2: 46174 | T2: 46174 | U2: 46174 | V2: 46204 | W2: 46204 | X2: 46204 | Y2: 46235 | Z2: 46235 | AA2: 46235 | AB2: 46266 | AC2: 46266 | AD2: 46266 | AE2: 46296 | AF2: 46296 | AG2: 46296 | AH2: 46327 | AI2: 46327 | AJ2: 46327 | AK2: 46357 | AL2: 46357 | AM2: 46357 | AN2: Total Revenue | AO2: Total Margin | AP2: Comments | AQ2: Renewal Confidence | AR2: Group | AS2: Sub-Group | AU2: 2024 | AV2: 2025_Total | AW2: 2025_Q4
A3: Solutions and Staff Augmentation (Projects) - Track 1 | AR3: Track 1-Secured
A4: AI Forward | B4: Vijay | C4: Non Billable | D4: 0 | F4: =D4-E4 -> 0 | G4: 0 | I4: =G4-H4 -> 0 | J4: 0 | L4: =J4-K4 -> 0 | M4: 0 | N4: 3169 | O4: =M4-N4 -> -3169 | P4: 0 | Q4: 5610 | R4: =P4-Q4 -> -5610 | S4: 0 | T4: 12879 | U4: =S4-T4 -> -12879 | V4: 0 | W4: 12879 | X4: =V4-W4 -> -12879 | Y4: 0 | Z4: 12879 | AA4: =Y4-Z4 -> -12879 | AB4: 0 | AC4: 12879 | AD4: =AB4-AC4 -> -12879 | AE4: 0 | AF4: 12879 | AG4: =AE4-AF4 -> -12879 | AH4: 0 | AI4: 12879 | AJ4: =AH4-AI4 -> -12879 | AK4: 0 | AL4: 12879 | AM4: =AK4-AL4 -> -12879 | AN4: {=SUMPRODUCT((D$1:AK$1<>"Margin")*(D$1:AK$1<>"Salary_$600")*D4:AK4)} -> 0 | AO4: {=SUMPRODUCT((D$1:AM$1="Margin")*D4:AM4)} -> -98932 | AR4: AI Forward | AS4: DS10_Secured
A5: Bench | B5: Vijay | C5: Non Billable | E5: 25952 | F5: =D5-E5 -> -25952 | H5: 26606 | I5: =G5-H5 -> -26606 | K5: 22428 | L5: =J5-K5 -> -22428 | N5: 27663 | O5: =M5-N5 -> -27663 | Q5: 17634 | R5: =P5-Q5 -> -17634 | T5: 8174 | U5: =S5-T5 -> -8174 | W5: 8174 | X5: =V5-W5 -> -8174 | Z5: =6501+8174 -> 14675 | AA5: =Y5-Z5 -> -14675 | AC5: =6501+8174 -> 14675 | AD5: =AB5-AC5 -> -14675 | AF5: =6501+8174 -> 14675 | AG5: =AE5-AF5 -> -14675 | AI5: =6501+8174 -> 14675 | AJ5: =AH5-AI5 -> -14675 | AL5: =6501+8174 -> 14675 | AM5: =AK5-AL5 -> -14675 | AN5: {=SUMPRODUCT((D$1:AK$1<>"Margin")*(D$1:AK$1<>"Salary_$600")*D5:AK5)} -> 0 | AO5: {=SUMPRODUCT((D$1:AM$1="Margin")*D5:AM5)} -> -210006 | AR5: Bench | AS5: DS10_Secured
A6: Bench Deployed | B6: Vijay | C6: Non Billable | F6: =D6-E6 -> 0 | I6: =G6-H6 -> 0 | L6: =J6-K6 -> 0 | O6: =M6-N6 -> 0 | Q6: 2572 | R6: =P6-Q6 -> -2572 | T6: 2572 | U6: =S6-T6 -> -2572 | W6: 2572 | X6: =V6-W6 -> -2572 | Z6: 2572 | AA6: =Y6-Z6 -> -2572 | AC6: 2572 | AD6: =AB6-AC6 -> -2572 | AF6: 2572 | AG6: =AE6-AF6 -> -2572 | AI6: 2572 | AJ6: =AH6-AI6 -> -2572 | AL6: 2572 | AM6: =AK6-AL6 -> -2572 | AN6: {=SUMPRODUCT((D$1:AK$1<>"Margin")*(D$1:AK$1<>"Salary_$600")*D6:AK6)} -> 0 | AO6: {=SUMPRODUCT((D$1:AM$1="Margin")*D6:AM6)} -> -20576 | AR6: Bench Deployed | AS6: DS10_Secured
A7: MetaSys Payroll Portal-Truist | B7: Vijay | C7: Non Billable | F7: =D7-E7 -> 0 | I7: =G7-H7 -> 0 | K7: 4718 | L7: =J7-K7 -> -4718 | N7: 2544 | O7: =M7-N7 -> -2544 | Q7: 2544 | R7: =P7-Q7 -> -2544 | U7: =S7-T7 -> 0 | X7: =V7-W7 -> 0 | AA7: =Y7-Z7 -> 0 | AD7: =AB7-AC7 -> 0 | AG7: =AE7-AF7 -> 0 | AJ7: =AH7-AI7 -> 0 | AM7: =AK7-AL7 -> 0 | AN7: {=SUMPRODUCT((D$1:AK$1<>"Margin")*(D$1:AK$1<>"Salary_$600")*D7:AK7)} -> 0 | AO7: {=SUMPRODUCT((D$1:AM$1="Margin")*D7:AM7)} -> -9806 | AR7: MetaSys Payroll Portal-Truist | AS7: DS10_Secured
A8: MetaSys Staffing Reports Wendy | B8: Vijay | C8: Non Billable | D8: 0 | E8: 3169 | F8: =D8-E8 -> -3169 | G8: 0 | H8: 3169 | I8: =G8-H8 -> -3169 | J8: 0 | L8: =J8-K8 -> 0 | M8: 0 | O8: =M8-N8 -> 0 | P8: 0 | R8: =P8-Q8 -> 0 | S8: 0 | U8: =S8-T8 -> 0 | V8: 0 | X8: =V8-W8 -> 0 | Y8: 0 | AA8: =Y8-Z8 -> 0 | AB8: 0 | AD8: =AB8-AC8 -> 0 | AE8: 0 | AG8: =AE8-AF8 -> 0 | AH8: 0 | AJ8: =AH8-AI8 -> 0 | AK8: 0 | AM8: =AK8-AL8 -> 0 | AN8: {=SUMPRODUCT((D$1:AK$1<>"Margin")*(D$1:AK$1<>"Salary_$600")*D8:AK8)} -> 0 | AO8: {=SUMPRODUCT((D$1:AM$1="Margin")*D8:AM8)} -> -6338 | AR8: MetaSys Staffing Reports Wendy | AS8: DS10_Secured
A9: MetaSys, Marlow Content and Design | B9: Vijay | C9: Non Billable | D9: 0 | F9: =D9-E9 -> 0 | G9: 0 | I9: =G9-H9 -> 0 | J9: 0 | L9: =J9-K9 -> 0 | M9: 0 | O9: =M9-N9 -> 0 | P9: 0 | R9: =P9-Q9 -> 0 | S9: 0 | T9: 6501 | U9: =S9-T9 -> -6501 | V9: 0 | W9: 6501 | X9: =V9-W9 -> -6501 | Y9: 0 | AA9: =Y9-Z9 -> 0 | AB9: 0 | AD9: =AB9-AC9 -> 0 | AE9: 0 | AG9: =AE9-AF9 -> 0 | AH9: 0 | AJ9: =AH9-AI9 -> 0 | AK9: 0 | AM9: =AK9-AL9 -> 0 | AN9: {=SUMPRODUCT((D$1:AK$1<>"Margin")*(D$1:AK$1<>"Salary_$600")*D9:AK9)} -> 0 | AO9: {=SUMPRODUCT((D$1:AM$1="Margin")*D9:AM9)} -> -13002 | AR9: MetaSys, Marlow Content and Design | AS9: DS10_Secured
A10: Ovis Programming + MetaSys Websites | B10: Vijay | C10: Non Billable | D10: 0 | F10: =D10-E10 -> 0 | G10: 0 | I10: =G10-H10 -> 0 | J10: 0 | L10: =J10-K10 -> 0 | M10: 0 | O10: =M10-N10 -> 0 | P10: 0 | Q10: 7445 | R10: =P10-Q10 -> -7445 | S10: 0 | T10: 8786 | U10: =S10-T10 -> -8786 | V10: 0 | W10: 8786 | X10: =V10-W10 -> -8786 | Y10: 0 | Z10: 8786 | AA10: =Y10-Z10 -> -8786 | AB10: 0 | AC10: 8786 | AD10: =AB10-AC10 -> -8786 | AE10: 0 | AF10: 8786 | AG10: =AE10-AF10 -> -8786 | AH10: 0 | AI10: 8786 | AJ10: =AH10-AI10 -> -8786 | AK10: 0 | AL10: 8786 | AM10: =AK10-AL10 -> -8786 | AN10: {=SUMPRODUCT((D$1:AK$1<>"Margin")*(D$1:AK$1<>"Salary_$600")*D10:AK10)} -> 0 | AO10: {=SUMPRODUCT((D$1:AM$1="Margin")*D10:AM10)} -> -68947 | AR10: Ovis Programming + MetaSys Websites | AS10: DS10_Secured
A11: Ovis- Creative Support | B11: Vijay | C11: Non Billable | N11: 1619 | O11: =M11-N11 -> -1619 | AN11: {=SUMPRODUCT((D$1:AK$1<>"Margin")*(D$1:AK$1<>"Salary_$600")*D11:AK11)} -> 0 | AO11: {=SUMPRODUCT((D$1:AM$1="Margin")*D11:AM11)} -> -1619 | AR11: Ovis- Creative Support | AS11: DS10_Secured
A12: Sales & Marketing (Nvish & MetaSys) | B12: Vijay | C12: Non Billable | D12: 0 | E12: 11387 | F12: =D12-E12 -> -11387 | G12: 0 | H12: 10945 | I12: =G12-H12 -> -10945 | J12: 0 | K12: 10945 | L12: =J12-K12 -> -10945 | M12: 0 | N12: 9115 | O12: =M12-N12 -> -9115 | P12: 0 | Q12: 9115 | R12: =P12-Q12 -> -9115 | S12: 0 | T12: 9115 | U12: =S12-T12 -> -9115 | V12: 0 | W12: 9115 | X12: =V12-W12 -> -9115 | Y12: 0 | Z12: 9115 | AA12: =Y12-Z12 -> -9115 | AB12: 0 | AC12: 9115 | AD12: =AB12-AC12 -> -9115 | AE12: 0 | AF12: 9115 | AG12: =AE12-AF12 -> -9115 | AH12: 0 | AI12: 9115 | AJ12: =AH12-AI12 -> -9115 | AK12: 0 | AL12: 9115 | AM12: =AK12-AL12 -> -9115 | AN12: {=SUMPRODUCT((D$1:AK$1<>"Margin")*(D$1:AK$1<>"Salary_$600")*D12:AK12)} -> 0 | AO12: {=SUMPRODUCT((D$1:AM$1="Margin")*D12:AM12)} -> -115312 | AR12: Sales & Marketing (Nvish & MetaSys) | AS12: DS10_Secured
A13: Automation Anywhere Web Dev | B13: Neeraj | C13: Staff Aug | D13: 30000 | E13: 30276 | F13: =D13-E13 -> -276 | G13: 30000 | H13: ='Salary Projections 2026'!$B$2 -> 26522 | I13: =G13-H13 -> 3478 | J13: 30000 | K13: ='Salary Projections 2026'!$B$2 -> 26522 | L13: =J13-K13 -> 3478 | M13: 30000 | N13: =VLOOKUP($A13,'Salary Projections 2026'!$A:$D,3,FALSE) -> 26522 | O13: =M13-N13 -> 3478 | P13: 30000 | Q13: =VLOOKUP($A13,'Salary Projections 2026'!$A:$D,3,FALSE) -> 26522 | R13: =P13-Q13 -> 3478 | S13: 30000 | T13: =VLOOKUP($A13,'Salary Projections 2026'!$A:$D,3,FALSE) -> 26522 | U13: =S13-T13 -> 3478 | V13: 30000 | W13: =VLOOKUP($A13,'Salary Projections 2026'!$A:$D,3,FALSE) -> 26522 | X13: =V13-W13 -> 3478 | Y13: 33350 | Z13: =VLOOKUP($A13,'Salary Projections 2026'!$A:$D,3,FALSE) -> 26522 | AA13: =Y13-Z13 -> 6828 | AB13: 33350 | AC13: =VLOOKUP($A13,'Salary Projections 2026'!$A:$D,3,FALSE) -> 26522 | AD13: =AB13-AC13 -> 6828 | AE13: 33350 | AF13: =VLOOKUP($A13,'Salary Projections 2026'!$A:$D,4,FALSE) -> 26522 | AG13: =AE13-AF13 -> 6828 | AH13: 33350 | AI13: =VLOOKUP($A13,'Salary Projections 2026'!$A:$D,4,FALSE) -> 26522 | AJ13: =AH13-AI13 -> 6828 | AK13: 33350 | AL13: =VLOOKUP($A13,'Salary Projections 2026'!$A:$D,4,FALSE) -> 26522 | AM13: =AK13-AL13 -> 6828 | AN13: {=SUMPRODUCT((D$1:AK$1<>"Margin")*(D$1:AK$1<>"Salary_$600")*D13:AK13)} -> 376750 | AO13: {=SUMPRODUCT((D$1:AM$1="Margin")*D13:AM13)} -> 54732 | AP13: SOW valid until Jan 2026. On SOW renewal, the client has reduced the monthly billing. Feb - July 2026 - $30K per month | AQ13: 100% | AR13: Automation Anywhere | AS13: DS10_Secured | AU13: 546884 | AV13: 411812 | AW13: 98766
A14: AIS Solutions | B14: Vijay | C14: Staff Aug | D14: 0 | E14: 0 | F14: 0 | G14: 0 | H14: 1341 | I14: =G14-H14 -> -1341 | J14: 5000 | K14: 1341 | L14: =J14-K14 -> 3659 | M14: 5000 | N14: 1341 | O14: =M14-N14 -> 3659 | P14: 5000 | Q14: =1341/2 -> 670.5 | R14: =P14-Q14 -> 4329.5 | S14: 0 | T14: 0 | U14: 0 | V14: 0 | W14: 0 | X14: 0 | Y14: 0 | Z14: 0 | AA14: 0 | AB14: 0 | AC14: 0 | AD14: 0 | AE14: 0 | AF14: 0 | AG14: 0 | AH14: 0 | AI14: 0 | AJ14: 0 | AK14: 0 | AL14: 0 | AM14: 0 | AN14: {=SUMPRODUCT((D$1:AK$1<>"Margin")*(D$1:AK$1<>"Salary_$600")*D14:AK14)} -> 15000 | AO14: {=SUMPRODUCT((D$1:AM$1="Margin")*D14:AM14)} -> 10306.5 | AQ14: 0% | AR14: AIS Solutions | AS14: DS10_Secured | AU14: 0 | AV14: 0 | AW14: 0
A15: Aldevron - Address Cookie Compliance Issue | B15: Neeraj | C15: Project | D15: 1200 | E15: 600 | F15: =D15-E15 -> 600 | G15: 0 | J15: 0 | M15: 0 | P15: 0 | S15: 0 | V15: 0 | Y15: 0 | AB15: 0 | AE15: 0 | AH15: 0 | AK15: 0 | AN15: {=SUMPRODUCT((D$1:AK$1<>"Margin")*(D$1:AK$1<>"Salary_$600")*D15:AK15)} -> 1200 | AO15: {=SUMPRODUCT((D$1:AM$1="Margin")*D15:AM15)} -> 600 | AQ15: 100% | AR15: Aldevron | AS15: DS10_Secured
A16: Aldevron - Website Support & Maintenance | B16: Neeraj | C16: Staff Aug | D16: 0 | G16: 8150 | H16: 3940 | I16: =G16-H16 -> 4210 | J16: 8150 | K16: 3940 | L16: =J16-K16 -> 4210 | M16: 8150 | N16: 3940 | O16: =M16-N16 -> 4210 | P16: 8150 | Q16: 3940 | R16: =P16-Q16 -> 4210 | S16: 8150 | T16: 3940 | U16: =S16-T16 -> 4210 | V16: 8150 | W16: 3940 | X16: =V16-W16 -> 4210 | Y16: 8150 | Z16: 3940 | AA16: =Y16-Z16 -> 4210 | AB16: 8150 | AC16: 3940 | AD16: =AB16-AC16 -> 4210 | AE16: 8150 | AF16: 3940 | AG16: =AE16-AF16 -> 4210 | AH16: 8150 | AI16: 3940 | AJ16: =AH16-AI16 -> 4210 | AK16: 8150 | AL16: 3940 | AM16: =AK16-AL16 -> 4210 | AN16: {=SUMPRODUCT((D$1:AK$1<>"Margin")*(D$1:AK$1<>"Salary_$600")*D16:AK16)} -> 89650 | AO16: {=SUMPRODUCT((D$1:AM$1="Margin")*D16:AM16)} -> 46310 | AQ16: 100% | AR16: Aldevron | AS16: DS10_Secured
A17: Aldevron - SEO Strategy & Optimization | B17: Neeraj | C17: Staff Aug | D17: 0 | E17: 0 | F17: 0 | G17: 0 | H17: 0 | I17: 0 | J17: 0 | K17: 0 | L17: 0 | M17: 0 | N17: 0 | O17: 0 | P17: 0 | Q17: 0 | R17: 0 | S17: 2500 | T17: 1500 | U17: =S17-T17 -> 1000 | V17: 2500 | W17: 1500 | X17: =V17-W17 -> 1000 | Y17: 2500 | Z17: 1500 | AA17: =Y17-Z17 -> 1000 | AB17: 2500 | AC17: 1500 | AD17: =AB17-AC17 -> 1000 | AE17: 2500 | AF17: 1500 | AG17: =AE17-AF17 -> 1000 | AH17: 2500 | AI17: 1500 | AJ17: =AH17-AI17 -> 1000 | AK17: 2500 | AL17: 1500 | AM17: =AK17-AL17 -> 1000 | AN17: {=SUMPRODUCT((D$1:AK$1<>"Margin")*(D$1:AK$1<>"Salary_$600")*D17:AK17)} -> 17500 | AO17: {=SUMPRODUCT((D$1:AM$1="Margin")*D17:AM17)} -> 7000 | AR17: Aldevron | AS17: DS10_Secured
A18: CheckPoint Desktop publishing of translated assets | B18: Neeraj | C18: Staff Aug | D18: 5000 | E18: =VLOOKUP($A18,'Salary Projections 2026'!$A:$D,2,FALSE) -> 849 | F18: =D18-E18 -> 4151 | G18: 0 | H18: =VLOOKUP($A18,'Salary Projections 2026'!$A:$D,2,FALSE) -> 849 | I18: =G18-H18 -> -849 | J18: 702 | K18: =VLOOKUP($A18,'Salary Projections 2026'!$A:$D,2,FALSE) -> 849 | L18: =J18-K18 -> -147 | M18: 0 | N18: 0 | O18: 0 | P18: 0 | Q18: 0 | R18: 0 | S18: 0 | T18: 0 | U18: 0 | V18: 0 | W18: 0 | X18: 0 | Y18: 0 | Z18: 0 | AA18: 0 | AB18: 0 | AC18: 0 | AD18: 0 | AE18: 0 | AF18: 0 | AG18: 0 | AH18: 0 | AI18: 0 | AJ18: 0 | AK18: 0 | AL18: 0 | AM18: 0 | AN18: {=SUMPRODUCT((D$1:AK$1<>"Margin")*(D$1:AK$1<>"Salary_$600")*D18:AK18)} -> 5702 | AO18: {=SUMPRODUCT((D$1:AM$1="Margin")*D18:AM18)} -> 3155 | AP18: SOW valid Feb 2026. For the last 2 years client is continuously renewing for 5 months. | AQ18: 0% | AR18: CheckPoint | AS18: DS10_Secured | AU18: 30190 | AV18: 24990 | AW18: 5000
A19: Church's Chicken & IT Support | B19: Neeraj | C19: Project | D19: 0 | E19: =VLOOKUP($A19,'Salary Projections 2026'!$A:$D,2,FALSE) -> 201 | F19: =D19-E19 -> -201 | G19: 0 | H19: =VLOOKUP($A19,'Salary Projections 2026'!$A:$D,2,FALSE) -> 201 | I19: =G19-H19 -> -201 | J19: 7500 | K19: =VLOOKUP($A19,'Salary Projections 2026'!$A:$D,2,FALSE) -> 201 | L19: =J19-K19 -> 7299 | M19: 0 | N19: =VLOOKUP($A19,'Salary Projections 2026'!$A:$D,3,FALSE) -> 201 | O19: =M19-N19 -> -201 | P19: 0 | Q19: =VLOOKUP($A19,'Salary Projections 2026'!$A:$D,3,FALSE) -> 201 | R19: =P19-Q19 -> -201 | S19: 0 | T19: =VLOOKUP($A19,'Salary Projections 2026'!$A:$D,3,FALSE) -> 201 | U19: =S19-T19 -> -201 | W19: =VLOOKUP($A19,'Salary Projections 2026'!$A:$D,3,FALSE) -> 201 | X19: =V19-W19 -> -201 | Y19: 0 | Z19: =VLOOKUP($A19,'Salary Projections 2026'!$A:$D,3,FALSE) -> 201 | AA19: =Y19-Z19 -> -201 | AB19: 0 | AC19: =VLOOKUP($A19,'Salary Projections 2026'!$A:$D,3,FALSE) -> 201 | AD19: =AB19-AC19 -> -201 | AE19: 0 | AF19: =VLOOKUP($A19,'Salary Projections 2026'!$A:$D,4,FALSE) -> 201 | AG19: =AE19-AF19 -> -201 | AH19: 0 | AI19: =VLOOKUP($A19,'Salary Projections 2026'!$A:$D,4,FALSE) -> 201 | AJ19: =AH19-AI19 -> -201 | AK19: 0 | AL19: =VLOOKUP($A19,'Salary Projections 2026'!$A:$D,4,FALSE) -> 201 | AM19: =AK19-AL19 -> -201 | AN19: {=SUMPRODUCT((D$1:AK$1<>"Margin")*(D$1:AK$1<>"Salary_$600")*D19:AK19)} -> 7500 | AO19: {=SUMPRODUCT((D$1:AM$1="Margin")*D19:AM19)} -> 5088 | AP19: SOW valid until Dec 31, 2027 | AQ19: 100% | AR19: Churchs-Chicken | AS19: DS10_Secured | AU19: 7500 | AV19: 75000 | AW19: 0
A20: Databricks Ongoing Support | B20: Neeraj | C20: Staff Aug | D20: 60499 | E20: 34000 | F20: =D20-E20 -> 26499 | G20: =57475+8825 -> 66300 | H20: =VLOOKUP($A20,'Salary Projections 2026'!$A:$D,2,FALSE) -> 38488 | I20: =G20-H20 -> 27812 | J20: =57475+8825 -> 66300 | K20: =VLOOKUP($A20,'Salary Projections 2026'!$A:$D,2,FALSE) -> 38488 | L20: =J20-K20 -> 27812 | M20: 67885 | N20: 37870 | O20: =M20-N20 -> 30015 | P20: =57475+8825+3875 -> 70175 | Q20: =VLOOKUP($A20,'Salary Projections 2026'!$A:$D,3,FALSE)+1248 -> 39736 | R20: =P20-Q20 -> 30439 | S20: =57475+8825+3875 -> 70175 | T20: =VLOOKUP($A20,'Salary Projections 2026'!$A:$D,3,FALSE)+1248 -> 39736 | U20: =S20-T20 -> 30439 | V20: =57475+8825 -> 66300 | W20: =VLOOKUP($A20,'Salary Projections 2026'!$A:$D,3,FALSE) -> 38488 | X20: =V20-W20 -> 27812 | Y20: =57475+8825 -> 66300 | Z20: =VLOOKUP($A20,'Salary Projections 2026'!$A:$D,3,FALSE) -> 38488 | AA20: =Y20-Z20 -> 27812 | AB20: =57475+8825 -> 66300 | AC20: =VLOOKUP($A20,'Salary Projections 2026'!$A:$D,3,FALSE) -> 38488 | AD20: =AB20-AC20 -> 27812 | AE20: =57475+8825 -> 66300 | AF20: =VLOOKUP($A20,'Salary Projections 2026'!$A:$D,4,FALSE) -> 38488 | AG20: =AE20-AF20 -> 27812 | AH20: =57475+8825 -> 66300 | AI20: =VLOOKUP($A20,'Salary Projections 2026'!$A:$D,4,FALSE) -> 38488 | AJ20: =AH20-AI20 -> 27812 | AK20: =57475+8825 -> 66300 | AL20: =VLOOKUP($A20,'Salary Projections 2026'!$A:$D,4,FALSE) -> 38488 | AM20: =AK20-AL20 -> 27812 | AN20: {=SUMPRODUCT((D$1:AK$1<>"Margin")*(D$1:AK$1<>"Salary_$600")*D20:AK20)} -> 799134 | AO20: {=SUMPRODUCT((D$1:AM$1="Margin")*D20:AM20)} -> 339888 | AP20: Current SOW valid until Sep 30, 2026. Amendment approved for 2 additional resoruces with addiitonal billing $8,825/month (Starting Jan 2026) | AQ20: 100% | AR20: Databricks | AS20: DS10_Secured | AU20: 1099676 | AV20: 1817631 | AW20: 481904
A21: Databricks Planning Project | B21: Neeraj | C21: Staff Aug | D21: 5000 | E21: =VLOOKUP($A21,'Salary Projections 2026'!$A:$D,2,FALSE) -> 3517 | F21: =D21-E21 -> 1483 | G21: 5000 | H21: =VLOOKUP($A21,'Salary Projections 2026'!$A:$D,2,FALSE) -> 3517 | I21: =G21-H21 -> 1483 | J21: 5000 | K21: =VLOOKUP($A21,'Salary Projections 2026'!$A:$D,2,FALSE) -> 3517 | L21: =J21-K21 -> 1483 | M21: 5000 | N21: =VLOOKUP($A21,'Salary Projections 2026'!$A:$D,3,FALSE) -> 3517 | O21: =M21-N21 -> 1483 | P21: 5000 | Q21: =VLOOKUP($A21,'Salary Projections 2026'!$A:$D,3,FALSE) -> 3517 | R21: =P21-Q21 -> 1483 | S21: 5000 | T21: =VLOOKUP($A21,'Salary Projections 2026'!$A:$D,3,FALSE) -> 3517 | U21: =S21-T21 -> 1483 | V21: 5000 | W21: =VLOOKUP($A21,'Salary Projections 2026'!$A:$D,3,FALSE) -> 3517 | X21: =V21-W21 -> 1483 | Y21: 5000 | Z21: =VLOOKUP($A21,'Salary Projections 2026'!$A:$D,3,FALSE) -> 3517 | AA21: =Y21-Z21 -> 1483 | AB21: 5000 | AC21: =VLOOKUP($A21,'Salary Projections 2026'!$A:$D,3,FALSE) -> 3517 | AD21: =AB21-AC21 -> 1483 | AE21: 5000 | AF21: =VLOOKUP($A21,'Salary Projections 2026'!$A:$D,4,FALSE) -> 3517 | AG21: =AE21-AF21 -> 1483 | AH21: 5000 | AI21: =VLOOKUP($A21,'Salary Projections 2026'!$A:$D,4,FALSE) -> 3517 | AJ21: =AH21-AI21 -> 1483 | AK21: 5000 | AL21: =VLOOKUP($A21,'Salary Projections 2026'!$A:$D,4,FALSE) -> 3517 | AM21: =AK21-AL21 -> 1483 | AN21: {=SUMPRODUCT((D$1:AK$1<>"Margin")*(D$1:AK$1<>"Salary_$600")*D21:AK21)} -> 60000 | AO21: {=SUMPRODUCT((D$1:AM$1="Margin")*D21:AM21)} -> 17796 | AP21: SOW valid until April 30, 2026. | AQ21: 100% | AR21: Databricks | AS21: DS10_Secured
A22: Databricks Program Manager and Marketo | B22: Neeraj | C22: Staff Aug | D22: 81850 | E22: =VLOOKUP($A22,'Salary Projections 2026'!$A:$D,2,FALSE) -> 55460 | F22: =D22-E22 -> 26390 | G22: 81850 | H22: =VLOOKUP($A22,'Salary Projections 2026'!$A:$D,2,FALSE) -> 55460 | I22: =G22-H22 -> 26390 | J22: 81850 | K22: =VLOOKUP($A22,'Salary Projections 2026'!$A:$D,2,FALSE) -> 55460 | L22: =J22-K22 -> 26390 | M22: 81850 | N22: =VLOOKUP($A22,'Salary Projections 2026'!$A:$D,3,FALSE) -> 53358 | O22: =M22-N22 -> 28492 | P22: 78000 | Q22: =18650+39245 -> 57895 | R22: =P22-Q22 -> 20105 | S22: 78000 | T22: =80*56+39245+12716 -> 56441 | U22: =S22-T22 -> 21559 | V22: 78000 | W22: =VLOOKUP($A22,'Salary Projections 2026'!$A:$D,3,FALSE) -> 53358 | X22: =V22-W22 -> 24642 | Y22: 78000 | Z22: =VLOOKUP($A22,'Salary Projections 2026'!$A:$D,3,FALSE) -> 53358 | AA22: =Y22-Z22 -> 24642 | AB22: 78000 | AC22: =VLOOKUP($A22,'Salary Projections 2026'!$A:$D,3,FALSE) -> 53358 | AD22: =AB22-AC22 -> 24642 | AE22: 93000 | AF22: =VLOOKUP($A22,'Salary Projections 2026'!$A:$D,3,FALSE) -> 53358 | AG22: =AE22-AF22 -> 39642 | AH22: 93000 | AI22: =VLOOKUP($A22,'Salary Projections 2026'!$A:$D,4,FALSE) -> 65358 | AJ22: =AH22-AI22 -> 27642 | AK22: 93000 | AL22: =VLOOKUP($A22,'Salary Projections 2026'!$A:$D,4,FALSE) -> 65358 | AM22: =AK22-AL22 -> 27642 | AN22: {=SUMPRODUCT((D$1:AK$1<>"Margin")*(D$1:AK$1<>"Salary_$600")*D22:AK22)} -> 996400 | AO22: {=SUMPRODUCT((D$1:AM$1="Margin")*D22:AM22)} -> 318178 | AP22: SOW valid until April 30, 2026. | AQ22: 100% | AR22: Databricks | AS22: DS10_Secured
A23: Databricks SEO Project Management | B23: Neeraj | C23: Staff Aug | D23: 4500 | E23: =VLOOKUP($A23,'Salary Projections 2026'!$A:$D,2,FALSE) -> 3568 | F23: =D23-E23 -> 932 | G23: 4500 | H23: =VLOOKUP($A23,'Salary Projections 2026'!$A:$D,2,FALSE) -> 3568 | I23: =G23-H23 -> 932 | J23: 4500 | K23: =VLOOKUP($A23,'Salary Projections 2026'!$A:$D,2,FALSE) -> 3568 | L23: =J23-K23 -> 932 | M23: 4500 | N23: =VLOOKUP($A23,'Salary Projections 2026'!$A:$D,3,FALSE) -> 3568 | O23: =M23-N23 -> 932 | P23: 4500 | Q23: =VLOOKUP($A23,'Salary Projections 2026'!$A:$D,3,FALSE) -> 3568 | R23: =P23-Q23 -> 932 | S23: 4500 | T23: =VLOOKUP($A23,'Salary Projections 2026'!$A:$D,3,FALSE) -> 3568 | U23: =S23-T23 -> 932 | V23: 0 | W23: 0 | X23: 0 | Y23: 4500 | Z23: =VLOOKUP($A23,'Salary Projections 2026'!$A:$D,3,FALSE) -> 3568 | AA23: =Y23-Z23 -> 932 | AB23: 4500 | AC23: =VLOOKUP($A23,'Salary Projections 2026'!$A:$D,3,FALSE) -> 3568 | AD23: =AB23-AC23 -> 932 | AE23: 4500 | AF23: =VLOOKUP($A23,'Salary Projections 2026'!$A:$D,4,FALSE) -> 3568 | AG23: =AE23-AF23 -> 932 | AH23: 4500 | AI23: =VLOOKUP($A23,'Salary Projections 2026'!$A:$D,4,FALSE) -> 3568 | AJ23: =AH23-AI23 -> 932 | AK23: 4500 | AL23: =VLOOKUP($A23,'Salary Projections 2026'!$A:$D,4,FALSE) -> 3568 | AM23: =AK23-AL23 -> 932 | AN23: {=SUMPRODUCT((D$1:AK$1<>"Margin")*(D$1:AK$1<>"Salary_$600")*D23:AK23)} -> 49500 | AO23: {=SUMPRODUCT((D$1:AM$1="Margin")*D23:AM23)} -> 10252 | AP23: SOW valid until April 30, 2026. | AQ23: 100% | AR23: Databricks | AS23: DS10_Secured
A24: Databricks Martech Platform Operations Administrator | B24: Neeraj | C24: Staff Aug | D24: 13500 | E24: =VLOOKUP($A24,'Salary Projections 2026'!$A:$D,2,FALSE) -> 7419 | F24: =D24-E24 -> 6081 | G24: 13500 | H24: =VLOOKUP($A24,'Salary Projections 2026'!$A:$D,2,FALSE) -> 7419 | I24: =G24-H24 -> 6081 | J24: =13500 -> 13500 | K24: =VLOOKUP($A24,'Salary Projections 2026'!$A:$D,2,FALSE) -> 7419 | L24: =J24-K24 -> 6081 | M24: 9000 | N24: 4689 | O24: =M24-N24 -> 4311 | P24: =3*4500 -> 13500 | Q24: =VLOOKUP($A24,'Salary Projections 2026'!$A:$D,3,FALSE) -> 7511 | R24: =P24-Q24 -> 5989 | S24: =3*4500 -> 13500 | T24: =VLOOKUP($A24,'Salary Projections 2026'!$A:$D,3,FALSE) -> 7511 | U24: =S24-T24 -> 5989 | V24: =3*4500 -> 13500 | W24: =VLOOKUP($A24,'Salary Projections 2026'!$A:$D,3,FALSE) -> 7511 | X24: =V24-W24 -> 5989 | Y24: =3*4500 -> 13500 | Z24: =VLOOKUP($A24,'Salary Projections 2026'!$A:$D,3,FALSE) -> 7511 | AA24: =Y24-Z24 -> 5989 | AB24: =3*4500 -> 13500 | AC24: =VLOOKUP($A24,'Salary Projections 2026'!$A:$D,3,FALSE) -> 7511 | AD24: =AB24-AC24 -> 5989 | AE24: =3*4500 -> 13500 | AF24: =VLOOKUP($A24,'Salary Projections 2026'!$A:$D,4,FALSE) -> 7511 | AG24: =AE24-AF24 -> 5989 | AH24: =3*4500 -> 13500 | AI24: =VLOOKUP($A24,'Salary Projections 2026'!$A:$D,4,FALSE) -> 7511 | AJ24: =AH24-AI24 -> 5989 | AK24: =3*4500 -> 13500 | AL24: =VLOOKUP($A24,'Salary Projections 2026'!$A:$D,4,FALSE) -> 7511 | AM24: =AK24-AL24 -> 5989 | AN24: {=SUMPRODUCT((D$1:AK$1<>"Margin")*(D$1:AK$1<>"Salary_$600")*D24:AK24)} -> 157500 | AO24: {=SUMPRODUCT((D$1:AM$1="Margin")*D24:AM24)} -> 70466 | AP24: SOW valid until April 30, 2026. | AQ24: 100% | AR24: Databricks | AS24: DS10_Secured
A25: Doppel - Website Support & Maintenance | B25: Neeraj | C25: Staff Aug | D25: 0 | E25: 0 | F25: 0 | G25: 0 | H25: 0 | I25: 0 | J25: 0 | K25: 0 | L25: 0 | M25: 0 | N25: 0 | O25: 0 | P25: 0 | Q25: 0 | R25: 0 | S25: 0 | T25: 0 | U25: 0 | V25: 0 | W25: 0 | X25: 0 | Y25: 0 | Z25: 0 | AA25: 0 | AB25: 0 | AC25: 0 | AD25: 0 | AE25: 0 | AF25: 0 | AG25: 0 | AH25: 0 | AI25: 0 | AJ25: 0 | AK25: 0 | AL25: 0 | AM25: 0 | AN25: {=SUMPRODUCT((D$1:AK$1<>"Margin")*(D$1:AK$1<>"Salary_$600")*D25:AK25)} -> 0 | AO25: {=SUMPRODUCT((D$1:AM$1="Margin")*D25:AM25)} -> 0 | AQ25: 25% | AR25: Doppel | AS25: DS10_Secured | AU25: 0 | AV25: 0 | AW25: 0
A26: EGIA Development Support | B26: Neeraj | C26: Staff Aug | D26: 39000 | E26: =VLOOKUP($A26,'Salary Projections 2026'!$A:$D,2,FALSE) -> 17108 | F26: =D26-E26 -> 21892 | G26: 39000 | H26: =VLOOKUP($A26,'Salary Projections 2026'!$A:$D,2,FALSE) -> 17108 | I26: =G26-H26 -> 21892 | J26: 39000 | K26: =VLOOKUP($A26,'Salary Projections 2026'!$A:$D,2,FALSE) -> 17108 | L26: =J26-K26 -> 21892 | M26: 39000 | N26: =VLOOKUP($A26,'Salary Projections 2026'!$A:$D,3,FALSE) -> 17108 | O26: =M26-N26 -> 21892 | P26: 39000 | Q26: =VLOOKUP($A26,'Salary Projections 2026'!$A:$D,3,FALSE) -> 17108 | R26: =P26-Q26 -> 21892 | S26: 39000 | T26: =VLOOKUP($A26,'Salary Projections 2026'!$A:$D,3,FALSE) -> 17108 | U26: =S26-T26 -> 21892 | V26: 39000 | W26: =VLOOKUP($A26,'Salary Projections 2026'!$A:$D,3,FALSE) -> 17108 | X26: =V26-W26 -> 21892 | Y26: 39000 | Z26: =VLOOKUP($A26,'Salary Projections 2026'!$A:$D,3,FALSE) -> 17108 | AA26: =Y26-Z26 -> 21892 | AB26: 39000 | AC26: =VLOOKUP($A26,'Salary Projections 2026'!$A:$D,3,FALSE) -> 17108 | AD26: =AB26-AC26 -> 21892 | AE26: 39000 | AF26: =VLOOKUP($A26,'Salary Projections 2026'!$A:$D,4,FALSE) -> 17108 | AG26: =AE26-AF26 -> 21892 | AH26: 39000 | AI26: =VLOOKUP($A26,'Salary Projections 2026'!$A:$D,4,FALSE) -> 17108 | AJ26: =AH26-AI26 -> 21892 | AK26: 39000 | AL26: =VLOOKUP($A26,'Salary Projections 2026'!$A:$D,4,FALSE) -> 17108 | AM26: =AK26-AL26 -> 21892 | AN26: {=SUMPRODUCT((D$1:AK$1<>"Margin")*(D$1:AK$1<>"Salary_$600")*D26:AK26)} -> 468000 | AO26: {=SUMPRODUCT((D$1:AM$1="Margin")*D26:AM26)} -> 262704 | AP26: Open Ended SOW | AQ26: 100% | AR26: EGIA | AS26: DS10_Secured | AU26: 604000 | AV26: 468000 | AW26: 117000
A27: Hitachi Asia | B27: Vijay | C27: Project | D27: 0 | E27: =VLOOKUP($A27,'Salary Projections 2026'!$A:$D,2,FALSE) -> 22701.667 | F27: =D27-E27 -> -22701.667 | G27: 0 | H27: =VLOOKUP($A27,'Salary Projections 2026'!$A:$D,2,FALSE) -> 22701.667 | I27: =G27-H27 -> -22701.667 | J27: 116000 | K27: =VLOOKUP($A27,'Salary Projections 2026'!$A:$D,2,FALSE) -> 22701.667 | L27: =J27-K27 -> 93298.333 | M27: 0 | N27: 4566 | O27: =M27-N27 -> -4566 | P27: 0 | Q27: 4566 | R27: =P27-Q27 -> -4566 | S27: 0 | T27: 4566 | U27: =S27-T27 -> -4566 | V27: 0 | W27: 4566 | X27: =V27-W27 -> -4566 | Y27: 0 | Z27: 4566 | AA27: =Y27-Z27 -> -4566 | AB27: 131770 | AC27: 4566 | AD27: =AB27-AC27 -> 127204 | AE27: 0 | AF27: 4566 | AG27: =AE27-AF27 -> -4566 | AH27: 0 | AI27: 4566 | AJ27: =AH27-AI27 -> -4566 | AK27: 0 | AL27: 4566 | AM27: =AK27-AL27 -> -4566 | AN27: {=SUMPRODUCT((D$1:AK$1<>"Margin")*(D$1:AK$1<>"Salary_$600")*D27:AK27)} -> 247770 | AO27: {=SUMPRODUCT((D$1:AM$1="Margin")*D27:AM27)} -> 138571 | AP27: Revenue until March is actual Revenue April - Dec are projections based on proposals under discussion | AQ27: 75% | AR27: Hitachi Asia | AS27: DS10_Secured | AU27: 543456 | AV27: 546277 | AW27: 155360
A28: HEA Website Updates | B28: Vijay | C28: Project | D28: 0 | E28: 0 | F28: 0 | G28: 0 | H28: 0 | I28: 0 | J28: 0 | K28: 0 | L28: 0 | M28: 0 | N28: 0 | O28: 0 | P28: 2770 | Q28: 0 | R28: =P28-Q28 -> 2770 | S28: 0 | T28: 0 | U28: 0 | V28: 0 | W28: 0 | X28: 0 | Y28: 0 | Z28: 0 | AA28: 0 | AB28: 0 | AC28: 0 | AD28: 0 | AE28: 0 | AF28: 0 | AG28: 0 | AH28: 0 | AI28: 0 | AJ28: 0 | AK28: 0 | AL28: 0 | AM28: 0 | AN28: {=SUMPRODUCT((D$1:AK$1<>"Margin")*(D$1:AK$1<>"Salary_$600")*D28:AK28)} -> 2770 | AO28: {=SUMPRODUCT((D$1:AM$1="Margin")*D28:AM28)} -> 2770 | AQ28: 100% | AR28: Hitachi Asia | AS28: DS10_Secured
A29: HAL Creative Support | B29: Neeraj | C29: Staff Aug | D29: 0 | E29: =VLOOKUP($A29,'Salary Projections 2026'!$A:$D,2,FALSE) -> 2698 | F29: =D29-E29 -> -2698 | G29: 0 | H29: =VLOOKUP($A29,'Salary Projections 2026'!$A:$D,2,FALSE) -> 2698 | I29: =G29-H29 -> -2698 | J29: 12860 | K29: =VLOOKUP($A29,'Salary Projections 2026'!$A:$D,2,FALSE) -> 2698 | L29: =J29-K29 -> 10162 | M29: 0 | N29: 0 | O29: 0 | P29: 0 | Q29: 0 | R29: 0 | S29: 0 | T29: 0 | U29: 0 | V29: 0 | W29: 0 | X29: 0 | Y29: 0 | Z29: 0 | AA29: 0 | AB29: 0 | AC29: 0 | AD29: 0 | AE29: 0 | AF29: 0 | AG29: 0 | AH29: 0 | AI29: 0 | AJ29: 0 | AK29: 0 | AL29: 0 | AM29: 0 | AN29: {=SUMPRODUCT((D$1:AK$1<>"Margin")*(D$1:AK$1<>"Salary_$600")*D29:AK29)} -> 12860 | AO29: {=SUMPRODUCT((D$1:AM$1="Margin")*D29:AM29)} -> 4766 | AP29: SOW valid until Mar 31, 2026. | AQ29: 0% | AR29: HAL | AS29: DS10_Secured | AU29: 424016 | AV29: 413786 | AW29: 107501
A30: HAL Digital Web Marketing | B30: Neeraj | C30: Staff Aug | D30: 0 | E30: =VLOOKUP($A30,'Salary Projections 2026'!$A:$D,2,FALSE) -> 4478 | F30: =D30-E30 -> -4478 | G30: 0 | H30: =VLOOKUP($A30,'Salary Projections 2026'!$A:$D,2,FALSE) -> 4478 | I30: =G30-H30 -> -4478 | J30: 18900 | K30: =VLOOKUP($A30,'Salary Projections 2026'!$A:$D,2,FALSE) -> 4478 | L30: =J30-K30 -> 14422 | M30: 18000 | N30: =VLOOKUP($A30,'Salary Projections 2026'!$A:$D,3,FALSE) -> 4478 | O30: =M30-N30 -> 13522 | P30: 0 | Q30: =VLOOKUP($A30,'Salary Projections 2026'!$A:$D,3,FALSE) -> 4478 | R30: =P30-Q30 -> -4478 | S30: 0 | T30: =VLOOKUP($A30,'Salary Projections 2026'!$A:$D,3,FALSE) -> 4478 | U30: =S30-T30 -> -4478 | V30: 0 | W30: =VLOOKUP($A30,'Salary Projections 2026'!$A:$D,3,FALSE) -> 4478 | X30: =V30-W30 -> -4478 | Y30: 0 | Z30: =VLOOKUP($A30,'Salary Projections 2026'!$A:$D,3,FALSE) -> 4478 | AA30: =Y30-Z30 -> -4478 | AB30: 18900 | AC30: =VLOOKUP($A30,'Salary Projections 2026'!$A:$D,3,FALSE) -> 4478 | AD30: =AB30-AC30 -> 14422 | AE30: 18000 | AF30: =VLOOKUP($A30,'Salary Projections 2026'!$A:$D,4,FALSE) -> 4478 | AG30: =AE30-AF30 -> 13522 | AH30: 0 | AI30: =VLOOKUP($A30,'Salary Projections 2026'!$A:$D,4,FALSE) -> 4478 | AJ30: =AH30-AI30 -> -4478 | AK30: 0 | AL30: =VLOOKUP($A30,'Salary Projections 2026'!$A:$D,4,FALSE) -> 4478 | AM30: =AK30-AL30 -> -4478 | AN30: {=SUMPRODUCT((D$1:AK$1<>"Margin")*(D$1:AK$1<>"Salary_$600")*D30:AK30)} -> 73800 | AO30: {=SUMPRODUCT((D$1:AM$1="Margin")*D30:AM30)} -> 20064 | AP30: SOW valid until Mar 31, 2026. | AQ30: 100% | AR30: HAL | AS30: DS10_Secured
A31: HAL Marketo Support | B31: Neeraj | C31: Staff Aug | D31: 0 | E31: =VLOOKUP($A31,'Salary Projections 2026'!$A:$D,2,FALSE) -> 2543 | F31: =D31-E31 -> -2543 | G31: 0 | H31: =VLOOKUP($A31,'Salary Projections 2026'!$A:$D,2,FALSE) -> 2543 | I31: =G31-H31 -> -2543 | J31: 16490 | K31: =VLOOKUP($A31,'Salary Projections 2026'!$A:$D,2,FALSE) -> 2543 | L31: =J31-K31 -> 13947 | M31: 0 | N31: 0 | O31: 0 | P31: 0 | Q31: 0 | R31: 0 | S31: 0 | T31: 0 | U31: 0 | V31: 0 | W31: 0 | X31: 0 | Y31: 0 | Z31: 0 | AA31: 0 | AB31: 0 | AC31: 0 | AD31: 0 | AE31: 0 | AF31: 0 | AG31: 0 | AH31: 0 | AI31: 0 | AJ31: 0 | AK31: 0 | AL31: 0 | AM31: 0 | AN31: {=SUMPRODUCT((D$1:AK$1<>"Margin")*(D$1:AK$1<>"Salary_$600")*D31:AK31)} -> 16490 | AO31: {=SUMPRODUCT((D$1:AM$1="Margin")*D31:AM31)} -> 8861 | AP31: SOW valid until Mar 31, 2026. | AQ31: 0% | AR31: HAL | AS31: DS10_Secured
A32: HAL Critical Minerals AI Analysis solution | B32: Neeraj | C32: Project | D32: 0 | E32: 0 | F32: 0 | G32: 0 | H32: 0 | I32: 0 | J32: 22000 | K32: =8950+2933+2881+2915/2+0.1*(J32-8950) -> 17526.5 | L32: =J32-K32 -> 4473.5 | M32: 0 | N32: 0 | O32: 0 | P32: 0 | Q32: 0 | R32: 0 | S32: 0 | T32: 0 | U32: 0 | V32: 0 | W32: 0 | X32: 0 | Y32: 0 | Z32: 0 | AA32: 0 | AB32: 0 | AC32: 0 | AD32: 0 | AE32: 0 | AF32: 0 | AG32: 0 | AH32: 0 | AI32: 0 | AJ32: 0 | AK32: 0 | AL32: 0 | AM32: 0 | AN32: {=SUMPRODUCT((D$1:AK$1<>"Margin")*(D$1:AK$1<>"Salary_$600")*D32:AK32)} -> 22000 | AO32: {=SUMPRODUCT((D$1:AM$1="Margin")*D32:AM32)} -> 4473.5 | AR32: HAL | AS32: DS10_Secured
A33: HAL Marketing Operations Specialist | B33: Neeraj | C33: Project | D33: 0 | F33: 0 | G33: 0 | I33: 0 | J33: 0 | L33: 0 | M33: 0 | O33: 0 | P33: 0 | Q33: =(2300000/12/90+600)*0.25 -> 682.40741 | R33: =P33-Q33 -> -682.40741 | S33: 15000 | T33: =(2300000/12/90+600) -> 2729.6296 | U33: =S33-T33 -> 12270.37 | V33: 0 | W33: =(2300000/12/90+600) -> 2729.6296 | X33: =V33-W33 -> -2729.6296 | Y33: 0 | Z33: =(2300000/12/90+600) -> 2729.6296 | AA33: =Y33-Z33 -> -2729.6296 | AB33: 0 | AC33: =(2300000/12/90+600) -> 2729.6296 | AD33: =AB33-AC33 -> -2729.6296 | AE33: 15000 | AF33: =(2300000/12/90+600) -> 2729.6296 | AG33: =AE33-AF33 -> 12270.37 | AH33: 0 | AI33: =(2300000/12/90+600) -> 2729.6296 | AJ33: =AH33-AI33 -> -2729.6296 | AK33: 15000 | AL33: =(2300000/12/90+600) -> 2729.6296 | AM33: =AK33-AL33 -> 12270.37 | AN33: {=SUMPRODUCT((D$1:AK$1<>"Margin")*(D$1:AK$1<>"Salary_$600")*D33:AK33)} -> 45000 | AO33: {=SUMPRODUCT((D$1:AM$1="Margin")*D33:AM33)} -> 25210.185 | AP33: Started this new in May 2026 | AQ33: 100% | AR33: HAL | AS33: DS10_Secured
A34: Business Travel of Abhishek Kalsy to Las Vegas for Hitachi Americas Brand and Growth | B34: Neeraj | C34: Project | E34: 0 | F34: 0 | G34: 0 | H34: 0 | I34: 0 | J34: 0 | K34: 0 | L34: 0 | M34: 0 | N34: 0 | O34: 0 | P34: 0 | Q34: 0 | R34: 0 | S34: 7950 | T34: 7950 | U34: 0 | V34: 0 | W34: 0 | X34: 0 | Y34: 0 | Z34: 0 | AA34: 0 | AB34: 0 | AC34: 0 | AD34: 0 | AE34: 0 | AF34: 0 | AG34: 0 | AH34: 0 | AI34: 0 | AJ34: 0 | AK34: 0 | AL34: 0 | AM34: 9 | AN34: {=SUMPRODUCT((D$1:AK$1<>"Margin")*(D$1:AK$1<>"Salary_$600")*D34:AK34)} -> 7950 | AO34: {=SUMPRODUCT((D$1:AM$1="Margin")*D34:AM34)} -> 9 | AR34: HAL | AS34: DS10_Secured
A35: Hitachi ByState Enhancement | B35: Neeraj | C35: Project | D35: 0 | E35: 0 | F35: 0 | G35: 0 | H35: 0 | I35: 0 | J35: 3000 | K35: 1741 | L35: =J35-K35 -> 1259 | M35: 0 | N35: 0 | O35: 0 | P35: 0 | Q35: 0 | R35: 0 | S35: 0 | T35: 0 | U35: 0 | V35: 0 | W35: 0 | X35: 0 | Y35: 0 | Z35: 0 | AA35: 0 | AB35: 0 | AC35: 0 | AD35: 0 | AE35: 0 | AF35: 0 | AG35: 0 | AH35: 0 | AI35: 0 | AJ35: 0 | AK35: 0 | AL35: 0 | AM35: 0 | AN35: {=SUMPRODUCT((D$1:AK$1<>"Margin")*(D$1:AK$1<>"Salary_$600")*D35:AK35)} -> 3000 | AO35: {=SUMPRODUCT((D$1:AM$1="Margin")*D35:AM35)} -> 1259 | AR35: HAL | AS35: DS10_Secured
A36: Hitachi Stem - Development Support | B36: Neeraj | C36: Staff Aug | D36: 5250 | E36: =VLOOKUP($A36,'Salary Projections 2026'!$A:$D,2,FALSE) -> 3015 | F36: =D36-E36 -> 2235 | G36: 4000 | H36: =VLOOKUP($A36,'Salary Projections 2026'!$A:$D,2,FALSE) -> 3015 | I36: =G36-H36 -> 985 | J36: 4000 | K36: =VLOOKUP($A36,'Salary Projections 2026'!$A:$D,2,FALSE) -> 3015 | L36: =J36-K36 -> 985 | M36: 4000 | N36: =VLOOKUP($A36,'Salary Projections 2026'!$A:$D,3,FALSE) -> 3015 | O36: =M36-N36 -> 985 | P36: 4000 | Q36: =VLOOKUP($A36,'Salary Projections 2026'!$A:$D,3,FALSE) -> 3015 | R36: =P36-Q36 -> 985 | S36: 4000 | T36: =VLOOKUP($A36,'Salary Projections 2026'!$A:$D,3,FALSE) -> 3015 | U36: =S36-T36 -> 985 | V36: 4000 | W36: =VLOOKUP($A36,'Salary Projections 2026'!$A:$D,3,FALSE) -> 3015 | X36: =V36-W36 -> 985 | Y36: 4000 | Z36: =VLOOKUP($A36,'Salary Projections 2026'!$A:$D,3,FALSE) -> 3015 | AA36: =Y36-Z36 -> 985 | AB36: 4000 | AC36: =VLOOKUP($A36,'Salary Projections 2026'!$A:$D,3,FALSE) -> 3015 | AD36: =AB36-AC36 -> 985 | AE36: 4000 | AF36: =VLOOKUP($A36,'Salary Projections 2026'!$A:$D,4,FALSE) -> 3015 | AG36: =AE36-AF36 -> 985 | AH36: 4000 | AI36: =VLOOKUP($A36,'Salary Projections 2026'!$A:$D,4,FALSE) -> 3015 | AJ36: =AH36-AI36 -> 985 | AK36: 4000 | AL36: =VLOOKUP($A36,'Salary Projections 2026'!$A:$D,4,FALSE) -> 3015 | AM36: =AK36-AL36 -> 985 | AN36: {=SUMPRODUCT((D$1:AK$1<>"Margin")*(D$1:AK$1<>"Salary_$600")*D36:AK36)} -> 49250 | AO36: {=SUMPRODUCT((D$1:AM$1="Margin")*D36:AM36)} -> 13070 | AP36: Open Ended SOW | AQ36: 100% | AR36: Hitachi Stem | AS36: DS10_Secured
A37: HPE SEO PM HPE Store Hament Dudeja | B37: Neeraj | C37: Staff Aug | D37: =16800/4 -> 4200 | E37: =VLOOKUP($A37,'Salary Projections 2026'!$A:$D,2,FALSE) -> 748 | F37: =D37-E37 -> 3452 | G37: 0 | H37: =VLOOKUP($A37,'Salary Projections 2026'!$A:$D,2,FALSE) -> 748 | I37: =G37-H37 -> -748 | J37: 0 | K37: =VLOOKUP($A37,'Salary Projections 2026'!$A:$D,2,FALSE) -> 748 | L37: =J37-K37 -> -748 | M37: =16800/4 -> 4200 | N37: =VLOOKUP($A37,'Salary Projections 2026'!$A:$D,3,FALSE) -> 748 | O37: =M37-N37 -> 3452 | P37: 0 | Q37: =VLOOKUP($A37,'Salary Projections 2026'!$A:$D,3,FALSE) -> 748 | R37: =P37-Q37 -> -748 | S37: 0 | T37: =VLOOKUP($A37,'Salary Projections 2026'!$A:$D,3,FALSE) -> 748 | U37: =S37-T37 -> -748 | V37: =16800/4 -> 4200 | W37: =VLOOKUP($A37,'Salary Projections 2026'!$A:$D,3,FALSE) -> 748 | X37: =V37-W37 -> 3452 | Y37: 0 | Z37: =VLOOKUP($A37,'Salary Projections 2026'!$A:$D,3,FALSE) -> 748 | AA37: =Y37-Z37 -> -748 | AB37: 0 | AC37: =VLOOKUP($A37,'Salary Projections 2026'!$A:$D,3,FALSE) -> 748 | AD37: =AB37-AC37 -> -748 | AE37: =16800/4 -> 4200 | AF37: =VLOOKUP($A37,'Salary Projections 2026'!$A:$D,4,FALSE) -> 748 | AG37: =AE37-AF37 -> 3452 | AH37: 0 | AI37: =VLOOKUP($A37,'Salary Projections 2026'!$A:$D,4,FALSE) -> 748 | AJ37: =AH37-AI37 -> -748 | AK37: 0 | AL37: =VLOOKUP($A37,'Salary Projections 2026'!$A:$D,4,FALSE) -> 748 | AM37: =AK37-AL37 -> -748 | AN37: {=SUMPRODUCT((D$1:AK$1<>"Margin")*(D$1:AK$1<>"Salary_$600")*D37:AK37)} -> 16800 | AO37: {=SUMPRODUCT((D$1:AM$1="Margin")*D37:AM37)} -> 7824 | AP37: SOW valid until Oct 31, 2026 | AQ37: 100% | AR37: HPE | AS37: DS10_Secured | AU37: 829892 | AV37: 911397 | AW37: 216343
A38: HPE Marketing Strategy & Operations for the APJ Region | B38: Neeraj | C38: Staff Aug | D38: 5040 | E38: =VLOOKUP($A38,'Salary Projections 2026'!$A:$D,2,FALSE) -> 4802 | F38: =D38-E38 -> 238 | G38: 5600 | H38: =VLOOKUP($A38,'Salary Projections 2026'!$A:$D,2,FALSE) -> 4802 | I38: =G38-H38 -> 798 | J38: 5880 | K38: =VLOOKUP($A38,'Salary Projections 2026'!$A:$D,2,FALSE) -> 4802 | L38: =J38-K38 -> 1078 | M38: =1*35*'Working Days'!$C$5 -> 6160 | N38: =VLOOKUP($A38,'Salary Projections 2026'!$A:$D,3,FALSE) -> 4802 | O38: =M38-N38 -> 1358 | P38: 5600 | Q38: =VLOOKUP($A38,'Salary Projections 2026'!$A:$D,3,FALSE) -> 4802 | R38: =P38-Q38 -> 798 | S38: =1*35*'Working Days'!$C$7 -> 5880 | T38: =VLOOKUP($A38,'Salary Projections 2026'!$A:$D,3,FALSE) -> 4802 | U38: =S38-T38 -> 1078 | V38: =1*35*'Working Days'!$C$8 -> 6440 | W38: =VLOOKUP($A38,'Salary Projections 2026'!$A:$D,3,FALSE) -> 4802 | X38: =V38-W38 -> 1638 | Y38: =1*35*'Working Days'!$C$9 -> 5600 | Z38: =VLOOKUP($A38,'Salary Projections 2026'!$A:$D,3,FALSE) -> 4802 | AA38: =Y38-Z38 -> 798 | AB38: =1*35*'Working Days'!$C$10 -> 6160 | AC38: =VLOOKUP($A38,'Salary Projections 2026'!$A:$D,3,FALSE) -> 4802 | AD38: =AB38-AC38 -> 1358 | AE38: =1*35*'Working Days'!$C$11 -> 5600 | AF38: =VLOOKUP($A38,'Salary Projections 2026'!$A:$D,4,FALSE) -> 4802 | AG38: =AE38-AF38 -> 798 | AH38: =1*35*'Working Days'!$C$12 -> 5320 | AI38: =VLOOKUP($A38,'Salary Projections 2026'!$A:$D,4,FALSE) -> 4802 | AJ38: =AH38-AI38 -> 518 | AK38: =1*35*'Working Days'!$C$13 -> 4760 | AL38: =VLOOKUP($A38,'Salary Projections 2026'!$A:$D,4,FALSE) -> 4802 | AM38: =AK38-AL38 -> -42 | AN38: {=SUMPRODUCT((D$1:AK$1<>"Margin")*(D$1:AK$1<>"Salary_$600")*D38:AK38)} -> 68040 | AO38: {=SUMPRODUCT((D$1:AM$1="Margin")*D38:AM38)} -> 10416 | AP38: SOW valid until Oct 31, 2026 | AQ38: 100% | AR38: HPE | AS38: DS10_Secured
A39: HPE Data Foundations Shashidhar Iddamsetty | B39: Neeraj | C39: Staff Aug | D39: 11200 | E39: =VLOOKUP($A39,'Salary Projections 2026'!$A:$D,2,FALSE) -> 6597 | F39: =D39-E39 -> 4603 | G39: 10080 | H39: =VLOOKUP($A39,'Salary Projections 2026'!$A:$D,2,FALSE) -> 6597 | I39: =G39-H39 -> 3483 | J39: 11340 | K39: =VLOOKUP($A39,'Salary Projections 2026'!$A:$D,2,FALSE) -> 6597 | L39: =J39-K39 -> 4743 | M39: 11480 | N39: =VLOOKUP($A39,'Salary Projections 2026'!$A:$D,3,FALSE)+2265 -> 6598 | O39: =M39-N39 -> 4882 | P39: 7280 | Q39: =VLOOKUP($A39,'Salary Projections 2026'!$A:$D,3,FALSE) -> 4333 | R39: =P39-Q39 -> 2947 | S39: 5880 | T39: =VLOOKUP($A39,'Salary Projections 2026'!$A:$D,3,FALSE) -> 4333 | U39: =S39-T39 -> 1547 | V39: 5880 | W39: =VLOOKUP($A39,'Salary Projections 2026'!$A:$D,3,FALSE) -> 4333 | X39: =V39-W39 -> 1547 | Y39: 5880 | Z39: =VLOOKUP($A39,'Salary Projections 2026'!$A:$D,3,FALSE) -> 4333 | AA39: =Y39-Z39 -> 1547 | AB39: 5880 | AC39: =VLOOKUP($A39,'Salary Projections 2026'!$A:$D,3,FALSE) -> 4333 | AD39: =AB39-AC39 -> 1547 | AE39: 5880 | AF39: =VLOOKUP($A39,'Salary Projections 2026'!$A:$D,4,FALSE) -> 4333 | AG39: =AE39-AF39 -> 1547 | AH39: 5880 | AI39: =VLOOKUP($A39,'Salary Projections 2026'!$A:$D,4,FALSE) -> 4333 | AJ39: =AH39-AI39 -> 1547 | AK39: 5880 | AL39: =VLOOKUP($A39,'Salary Projections 2026'!$A:$D,4,FALSE) -> 4333 | AM39: =AK39-AL39 -> 1547 | AN39: {=SUMPRODUCT((D$1:AK$1<>"Margin")*(D$1:AK$1<>"Salary_$600")*D39:AK39)} -> 92540 | AO39: {=SUMPRODUCT((D$1:AM$1="Margin")*D39:AM39)} -> 31487 | AP39: SOW valid until Jan 31, 2026. | AQ39: 100% | AR39: HPE | AS39: DS10_Secured
A40: HPE Marketing Automation- Christian Voigt | B40: Neeraj | C40: Staff Aug | D40: 9240 | E40: =VLOOKUP($A40,'Salary Projections 2026'!$A:$D,2,FALSE) -> 7591 | F40: =D40-E40 -> 1649 | G40: 11200 | H40: =VLOOKUP($A40,'Salary Projections 2026'!$A:$D,2,FALSE) -> 7591 | I40: =G40-H40 -> 3609 | J40: 12320 | K40: =VLOOKUP($A40,'Salary Projections 2026'!$A:$D,2,FALSE) -> 7591 | L40: =J40-K40 -> 4729 | M40: 10640 | N40: =VLOOKUP($A40,'Salary Projections 2026'!$A:$D,3,FALSE) -> 7591 | O40: =M40-N40 -> 3049 | P40: 10080 | Q40: =VLOOKUP($A40,'Salary Projections 2026'!$A:$D,3,FALSE) -> 7591 | R40: =P40-Q40 -> 2489 | S40: =5880*2 -> 11760 | T40: =VLOOKUP($A40,'Salary Projections 2026'!$A:$D,3,FALSE) -> 7591 | U40: =S40-T40 -> 4169 | V40: =5880*2 -> 11760 | W40: =VLOOKUP($A40,'Salary Projections 2026'!$A:$D,3,FALSE) -> 7591 | X40: =V40-W40 -> 4169 | Y40: =5880*2 -> 11760 | Z40: =VLOOKUP($A40,'Salary Projections 2026'!$A:$D,3,FALSE) -> 7591 | AA40: =Y40-Z40 -> 4169 | AB40: =5880*2 -> 11760 | AC40: =VLOOKUP($A40,'Salary Projections 2026'!$A:$D,3,FALSE) -> 7591 | AD40: =AB40-AC40 -> 4169 | AE40: =5880*2 -> 11760 | AF40: =VLOOKUP($A40,'Salary Projections 2026'!$A:$D,4,FALSE) -> 7591 | AG40: =AE40-AF40 -> 4169 | AH40: =5880*2 -> 11760 | AI40: =VLOOKUP($A40,'Salary Projections 2026'!$A:$D,4,FALSE) -> 7591 | AJ40: =AH40-AI40 -> 4169 | AK40: =5880*2 -> 11760 | AL40: =VLOOKUP($A40,'Salary Projections 2026'!$A:$D,4,FALSE) -> 7591 | AM40: =AK40-AL40 -> 4169 | AN40: {=SUMPRODUCT((D$1:AK$1<>"Margin")*(D$1:AK$1<>"Salary_$600")*D40:AK40)} -> 135800 | AO40: {=SUMPRODUCT((D$1:AM$1="Margin")*D40:AM40)} -> 44708 | AP40: SOW valid until Jan 31, 2026. | AQ40: 100% | AR40: HPE | AS40: DS10_Secured
A41: HPE SEO PM HPE Store Srihari Gopinath | B41: Neeraj | C41: Staff Aug | D41: 1260 | E41: =VLOOKUP($A41,'Salary Projections 2026'!$A:$D,2,FALSE) -> 2245 | F41: =D41-E41 -> -985 | G41: 5600 | H41: =VLOOKUP($A41,'Salary Projections 2026'!$A:$D,2,FALSE) -> 2245 | I41: =G41-H41 -> 3355 | J41: 5880 | K41: =VLOOKUP($A41,'Salary Projections 2026'!$A:$D,2,FALSE) -> 2245 | L41: =J41-K41 -> 3635 | M41: 1680 | N41: =VLOOKUP($A41,'Salary Projections 2026'!$A:$D,3,FALSE) -> 2245 | O41: =M41-N41 -> -565 | P41: 5600 | Q41: =VLOOKUP($A41,'Salary Projections 2026'!$A:$D,3,FALSE) -> 2245 | R41: =P41-Q41 -> 3355 | S41: =35*'Working Days 2026'!C7 -> 6160 | T41: =VLOOKUP($A41,'Salary Projections 2026'!$A:$D,3,FALSE) -> 2245 | U41: =S41-T41 -> 3915 | V41: =35*'Working Days 2026'!C8-V37 -> 2240 | W41: =VLOOKUP($A41,'Salary Projections 2026'!$A:$D,3,FALSE) -> 2245 | X41: =V41-W41 -> -5 | Y41: =35*'Working Days 2026'!C9 -> 5600 | Z41: =VLOOKUP($A41,'Salary Projections 2026'!$A:$D,3,FALSE) -> 2245 | AA41: =Y41-Z41 -> 3355 | AB41: =35*'Working Days 2026'!C10 -> 6160 | AC41: =VLOOKUP($A41,'Salary Projections 2026'!$A:$D,3,FALSE) -> 2245 | AD41: =AB41-AC41 -> 3915 | AE41: =35*'Working Days 2026'!C11-AE37 -> 1680 | AF41: =VLOOKUP($A41,'Salary Projections 2026'!$A:$D,4,FALSE) -> 2245 | AG41: =AE41-AF41 -> -565 | AH41: =35*'Working Days 2026'!C12 -> 5040 | AI41: =VLOOKUP($A41,'Salary Projections 2026'!$A:$D,4,FALSE) -> 2245 | AJ41: =AH41-AI41 -> 2795 | AK41: =35*'Working Days 2026'!C13 -> 3920 | AL41: =VLOOKUP($A41,'Salary Projections 2026'!$A:$D,4,FALSE) -> 2245 | AM41: =AK41-AL41 -> 1675 | AN41: {=SUMPRODUCT((D$1:AK$1<>"Margin")*(D$1:AK$1<>"Salary_$600")*D41:AK41)} -> 50820 | AO41: {=SUMPRODUCT((D$1:AM$1="Margin")*D41:AM41)} -> 23880 | AP41: SOW valid until Jan 31, 2026 | AQ41: 100% | AR41: HPE | AS41: DS10_Secured
A42: HPE SEO Strategy Towa Ghosh (Projects) | B42: Neeraj | C42: Staff Aug | D42: 14166 | E42: =VLOOKUP($A42,'Salary Projections 2026'!$A:$D,2,FALSE) -> 4696 | F42: =D42-E42 -> 9470 | G42: 0 | H42: 0 | I42: 0 | J42: 0 | K42: 0 | L42: 0 | M42: 0 | N42: 0 | O42: 0 | P42: 0 | Q42: 0 | R42: 0 | S42: 0 | T42: 0 | U42: 0 | V42: 0 | W42: 0 | X42: 0 | Y42: 0 | Z42: 0 | AA42: 0 | AB42: 0 | AC42: 0 | AD42: 0 | AE42: 0 | AF42: 0 | AG42: 0 | AH42: 0 | AI42: 0 | AJ42: 0 | AK42: 0 | AL42: 0 | AM42: 0 | AN42: {=SUMPRODUCT((D$1:AK$1<>"Margin")*(D$1:AK$1<>"Salary_$600")*D42:AK42)} -> 14166 | AO42: {=SUMPRODUCT((D$1:AM$1="Margin")*D42:AM42)} -> 9470 | AP42: SOW was discontinued from Feb 1, 2026 | AQ42: 0% | AR42: HPE | AS42: DS10_Secured
A43: HPE Data & Analytics Zainab Jamal | B43: Neeraj | C43: Staff Aug | D43: 10360 | E43: =VLOOKUP($A43,'Salary Projections 2026'!$A:$D,2,FALSE) -> 5268 | F43: =D43-E43 -> 5092 | G43: 10360 | H43: =VLOOKUP($A43,'Salary Projections 2026'!$A:$D,2,FALSE) -> 5268 | I43: =G43-H43 -> 5092 | J43: 11480 | K43: =VLOOKUP($A43,'Salary Projections 2026'!$A:$D,2,FALSE) -> 5268 | L43: =J43-K43 -> 6212 | M43: =5880*2 -> 11760 | N43: 5268 | O43: =M43-N43 -> 6492 | P43: 5880 | Q43: 2500 | R43: =P43-Q43 -> 3380 | S43: 0 | T43: 0 | U43: 0 | V43: =5880 -> 5880 | W43: 1800 | X43: =V43-W43 -> 4080 | Y43: =5880*2 -> 11760 | Z43: =VLOOKUP($A43,'Salary Projections 2026'!$A:$D,3,FALSE) -> 3727 | AA43: =Y43-Z43 -> 8033 | AB43: =5880*2 -> 11760 | AC43: =VLOOKUP($A43,'Salary Projections 2026'!$A:$D,3,FALSE) -> 3727 | AD43: =AB43-AC43 -> 8033 | AE43: =5880*2 -> 11760 | AF43: =VLOOKUP($A43,'Salary Projections 2026'!$A:$D,4,FALSE) -> 3727 | AG43: =AE43-AF43 -> 8033 | AH43: =5880*2 -> 11760 | AI43: =VLOOKUP($A43,'Salary Projections 2026'!$A:$D,4,FALSE) -> 3727 | AJ43: =AH43-AI43 -> 8033 | AK43: =5880*2 -> 11760 | AL43: =VLOOKUP($A43,'Salary Projections 2026'!$A:$D,4,FALSE) -> 3727 | AM43: =AK43-AL43 -> 8033 | AN43: {=SUMPRODUCT((D$1:AK$1<>"Margin")*(D$1:AK$1<>"Salary_$600")*D43:AK43)} -> 114520 | AO43: {=SUMPRODUCT((D$1:AM$1="Margin")*D43:AM43)} -> 70513 | AP43: SOW valid until Jan 31, 2026 | AQ43: 100% | AR43: HPE | AS43: DS10_Secured
A44: HPE- Documents Rebranding Landmark | B44: Neeraj | C44: Project | D44: 8505 | E44: 2247 | F44: =D44-E44 -> 6258 | G44: 6965 | H44: 2247 | I44: =G44-H44 -> 4718 | J44: 12740 | K44: 2247 | L44: =J44-K44 -> 10493 | M44: 105 | N44: 2247 | O44: =M44-N44 -> -2142 | P44: 11445 | Q44: 2247 | R44: =P44-Q44 -> 9198 | S44: =67200/12 -> 5600 | T44: 2247 | U44: =S44-T44 -> 3353 | V44: =67200/12 -> 5600 | W44: 2247 | X44: =V44-W44 -> 3353 | Y44: =67200/12 -> 5600 | Z44: 2247 | AA44: =Y44-Z44 -> 3353 | AB44: =67200/12 -> 5600 | AC44: 2247 | AD44: =AB44-AC44 -> 3353 | AE44: =67200/12 -> 5600 | AF44: 2247 | AG44: =AE44-AF44 -> 3353 | AH44: =67200/12 -> 5600 | AI44: 2247 | AJ44: =AH44-AI44 -> 3353 | AK44: =67200/12 -> 5600 | AL44: 2247 | AM44: =AK44-AL44 -> 3353 | AN44: {=SUMPRODUCT((D$1:AK$1<>"Margin")*(D$1:AK$1<>"Salary_$600")*D44:AK44)} -> 78960 | AO44: {=SUMPRODUCT((D$1:AM$1="Margin")*D44:AM44)} -> 51996 | AP44: SOW valid until Apr 30, 2026 | AQ44: 100% | AR44: HPE | AS44: DS10_Secured
A45: HPE Documents Rebranding Juniper | B45: Neeraj | C45: Project | D45: 3220 | E45: 3240 | F45: =D45-E45 -> -20 | G45: 6720 | H45: 3240 | I45: =G45-H45 -> 3480 | J45: 875 | K45: 3240 | L45: =J45-K45 -> -2365 | M45: 12145 | N45: 3240 | O45: =M45-N45 -> 8905 | P45: 0 | Q45: 3240 | R45: =P45-Q45 -> -3240 | T45: 3240 | U45: =S45-T45 -> -3240 | V45: =67200/12 -> 5600 | W45: 3240 | X45: =V45-W45 -> 2360 | Y45: =67200/12 -> 5600 | Z45: 3240 | AA45: =Y45-Z45 -> 2360 | AB45: =67200/12 -> 5600 | AC45: 3240 | AD45: =AB45-AC45 -> 2360 | AE45: =67200/12 -> 5600 | AF45: 3240 | AG45: =AE45-AF45 -> 2360 | AH45: =67200/12 -> 5600 | AI45: 3240 | AJ45: =AH45-AI45 -> 2360 | AK45: =67200/12 -> 5600 | AL45: 3240 | AM45: =AK45-AL45 -> 2360 | AN45: {=SUMPRODUCT((D$1:AK$1<>"Margin")*(D$1:AK$1<>"Salary_$600")*D45:AK45)} -> 56560 | AO45: {=SUMPRODUCT((D$1:AM$1="Margin")*D45:AM45)} -> 17680 | AP45: SOW valid until Apr 30, 2026 | AQ45: 100% | AR45: HPE | AS45: DS10_Secured
A46: SOW- Finder Fee -Full Stack Developer Resource for HPE Hire - Dilpreet Kaur | B46: Neeraj | C46: Project | D46: 0 | E46: 0 | F46: 0 | G46: 0 | H46: 0 | I46: 0 | J46: 0 | K46: 0 | L46: 0 | M46: 7000 | N46: 0 | O46: 7000 | P46: 0 | Q46: 0 | R46: 0 | S46: 0 | T46: 0 | U46: 0 | V46: 0 | W46: 0 | X46: 0 | Y46: 0 | Z46: 0 | AA46: 0 | AB46: 0 | AC46: 0 | AD46: 0 | AE46: 0 | AF46: 0 | AG46: 0 | AH46: 0 | AI46: 0 | AJ46: 0 | AK46: 0 | AL46: 0 | AM46: 0 | AN46: {=SUMPRODUCT((D$1:AK$1<>"Margin")*(D$1:AK$1<>"Salary_$600")*D46:AK46)} -> 7000 | AO46: {=SUMPRODUCT((D$1:AM$1="Margin")*D46:AM46)} -> 7000 | AR46: HPE | AS46: DS10_Secured
A47: HPE Proof Reader | B47: Neeraj | C47: Project | D47: 0 | E47: 0 | F47: 0 | G47: 0 | H47: 0 | I47: 0 | J47: 0 | K47: 0 | L47: 0 | M47: 0 | N47: 2247 | O47: =M47-N47 -> -2247 | P47: 0 | Q47: 2247 | R47: =P47-Q47 -> -2247 | S47: 5600 | T47: 2247 | U47: =S47-T47 -> 3353 | V47: 5600 | W47: 2247 | X47: =V47-W47 -> 3353 | Y47: 5600 | Z47: 2247 | AA47: =Y47-Z47 -> 3353 | AB47: 5600 | AC47: 2247 | AD47: =AB47-AC47 -> 3353 | AE47: 5600 | AF47: 2247 | AG47: =AE47-AF47 -> 3353 | AH47: 5600 | AI47: 2247 | AJ47: =AH47-AI47 -> 3353 | AK47: 5600 | AL47: 2247 | AM47: =AK47-AL47 -> 3353 | AN47: {=SUMPRODUCT((D$1:AK$1<>"Margin")*(D$1:AK$1<>"Salary_$600")*D47:AK47)} -> 39200 | AO47: {=SUMPRODUCT((D$1:AM$1="Margin")*D47:AM47)} -> 18977 | AQ47: 100% | AR47: HPE | AS47: DS10_Secured
A48: Icertis Web dev and Creative | B48: Neeraj | C48: Staff Aug | D48: 7000 | E48: =VLOOKUP($A48,'Salary Projections 2026'!$A:$D,2,FALSE) -> 4979 | F48: =D48-E48 -> 2021 | G48: 7000 | H48: =VLOOKUP($A48,'Salary Projections 2026'!$A:$D,2,FALSE) -> 4979 | I48: =G48-H48 -> 2021 | J48: 7000 | K48: =VLOOKUP($A48,'Salary Projections 2026'!$A:$D,2,FALSE) -> 4979 | L48: =J48-K48 -> 2021 | M48: 7000 | N48: =VLOOKUP($A48,'Salary Projections 2026'!$A:$D,3,FALSE) -> 4979 | O48: =M48-N48 -> 2021 | P48: 7000 | Q48: =VLOOKUP($A48,'Salary Projections 2026'!$A:$D,3,FALSE) -> 4979 | R48: =P48-Q48 -> 2021 | S48: 7000 | T48: =VLOOKUP($A48,'Salary Projections 2026'!$A:$D,3,FALSE) -> 4979 | U48: =S48-T48 -> 2021 | V48: 7000 | W48: =VLOOKUP($A48,'Salary Projections 2026'!$A:$D,3,FALSE) -> 4979 | X48: =V48-W48 -> 2021 | Y48: 7000 | Z48: =VLOOKUP($A48,'Salary Projections 2026'!$A:$D,3,FALSE) -> 4979 | AA48: =Y48-Z48 -> 2021 | AB48: 7000 | AC48: =VLOOKUP($A48,'Salary Projections 2026'!$A:$D,3,FALSE) -> 4979 | AD48: =AB48-AC48 -> 2021 | AE48: 7000 | AF48: =VLOOKUP($A48,'Salary Projections 2026'!$A:$D,4,FALSE) -> 4979 | AG48: =AE48-AF48 -> 2021 | AH48: 7000 | AI48: =VLOOKUP($A48,'Salary Projections 2026'!$A:$D,4,FALSE) -> 4979 | AJ48: =AH48-AI48 -> 2021 | AK48: 7000 | AL48: =VLOOKUP($A48,'Salary Projections 2026'!$A:$D,4,FALSE) -> 4979 | AM48: =AK48-AL48 -> 2021 | AN48: {=SUMPRODUCT((D$1:AK$1<>"Margin")*(D$1:AK$1<>"Salary_$600")*D48:AK48)} -> 84000 | AO48: {=SUMPRODUCT((D$1:AM$1="Margin")*D48:AM48)} -> 24252 | AP48: SOW valid until Mar 3, 2026 | AQ48: 75% | AR48: Icertis | AS48: DS10_Secured | AU48: 86428 | AV48: 84100 | AW48: 21000
A49: IDBS Help-Center | B49: Neeraj | C49: Project | D49: 0 | E49: 0 | F49: 0 | G49: 0 | H49: 0 | I49: 0 | J49: 0 | K49: 0 | L49: 0 | M49: 0 | N49: 0 | O49: 0 | P49: 0 | Q49: 2036 | R49: =P49-Q49 -> -2036 | S49: 13000 | T49: =3777+1600 -> 5377 | U49: =S49-T49 -> 7623 | V49: 0 | W49: 0 | X49: 0 | Y49: 0 | Z49: 0 | AA49: 0 | AB49: 0 | AC49: 0 | AD49: 0 | AE49: 0 | AF49: 0 | AG49: 0 | AH49: 0 | AI49: 0 | AJ49: 0 | AK49: 0 | AL49: 0 | AM49: 0 | AN49: {=SUMPRODUCT((D$1:AK$1<>"Margin")*(D$1:AK$1<>"Salary_$600")*D49:AK49)} -> 13000 | AO49: {=SUMPRODUCT((D$1:AM$1="Margin")*D49:AM49)} -> 5587 | AP49: Project need to be delivered by end Sep 2026 | AQ49: 100% | AR49: IDBS | AS49: DS10_Secured | AU49: 18000 | AV49: 35000 | AW49: 33000
A50: IDBS: Support to make consistency with the top banners across IDBS website | B50: Neeraj | C50: Project | D50: 0 | E50: 0 | F50: 0 | G50: 0 | H50: 0 | I50: 0 | J50: 0 | K50: 0 | L50: 0 | M50: 7000 | N50: 3777 | O50: =M50-N50 -> 3223 | P50: 0 | Q50: 1741 | R50: =P50-Q50 -> -1741 | S50: 7300 | T50: 1741 | U50: =S50-T50 -> 5559 | V50: 0 | W50: 0 | X50: 0 | Y50: 0 | Z50: 0 | AA50: 0 | AB50: 0 | AC50: 0 | AD50: 0 | AE50: 0 | AF50: 0 | AG50: 0 | AH50: 0 | AI50: 0 | AJ50: 0 | AK50: 0 | AL50: 0 | AM50: 0 | AN50: {=SUMPRODUCT((D$1:AK$1<>"Margin")*(D$1:AK$1<>"Salary_$600")*D50:AK50)} -> 14300 | AO50: {=SUMPRODUCT((D$1:AM$1="Margin")*D50:AM50)} -> 7041 | AQ50: 100% | AR50: IDBS | AS50: DS10_Secured
A51: LiveRamp Marketo & Analytics | B51: Neeraj | C51: Staff Aug | D51: 13780 | E51: =VLOOKUP($A51,'Salary Projections 2026'!$A:$D,2,FALSE) -> 9270 | F51: =D51-E51 -> 4510 | G51: 13780 | H51: =VLOOKUP($A51,'Salary Projections 2026'!$A:$D,2,FALSE) -> 9270 | I51: =G51-H51 -> 4510 | J51: 13780 | K51: =VLOOKUP($A51,'Salary Projections 2026'!$A:$D,2,FALSE) -> 9270 | L51: =J51-K51 -> 4510 | M51: 13780 | N51: =VLOOKUP($A51,'Salary Projections 2026'!$A:$D,3,FALSE) -> 9270 | O51: =M51-N51 -> 4510 | P51: 13780 | Q51: =VLOOKUP($A51,'Salary Projections 2026'!$A:$D,3,FALSE) -> 9270 | R51: =P51-Q51 -> 4510 | S51: 13780 | T51: =VLOOKUP($A51,'Salary Projections 2026'!$A:$D,3,FALSE) -> 9270 | U51: =S51-T51 -> 4510 | V51: 13780 | W51: =VLOOKUP($A51,'Salary Projections 2026'!$A:$D,3,FALSE) -> 9270 | X51: =V51-W51 -> 4510 | Y51: 13780 | Z51: =VLOOKUP($A51,'Salary Projections 2026'!$A:$D,3,FALSE) -> 9270 | AA51: =Y51-Z51 -> 4510 | AB51: 13780 | AC51: =VLOOKUP($A51,'Salary Projections 2026'!$A:$D,3,FALSE) -> 9270 | AD51: =AB51-AC51 -> 4510 | AE51: 13780 | AF51: =VLOOKUP($A51,'Salary Projections 2026'!$A:$D,4,FALSE) -> 9270 | AG51: =AE51-AF51 -> 4510 | AH51: 13780 | AI51: =VLOOKUP($A51,'Salary Projections 2026'!$A:$D,4,FALSE) -> 9270 | AJ51: =AH51-AI51 -> 4510 | AK51: 13780 | AL51: =VLOOKUP($A51,'Salary Projections 2026'!$A:$D,4,FALSE) -> 9270 | AM51: =AK51-AL51 -> 4510 | AN51: {=SUMPRODUCT((D$1:AK$1<>"Margin")*(D$1:AK$1<>"Salary_$600")*D51:AK51)} -> 165360 | AO51: {=SUMPRODUCT((D$1:AM$1="Margin")*D51:AM51)} -> 54120 | AP51: SOW valid until Dec 31, 2026 There is a reduction of 140 billed hours per month compared to 2025. Additionally, the hourly billing rate for the remaining team members has increased by 10% in 2026. | AQ51: 100% | AR51: LiveRamp | AS51: DS10_Secured | AU51: 192000 | AV51: 192000 | AW51: 48000
A52: Molecular Devices Web development, SEO, Ceros Designer | B52: Neeraj | C52: Staff Aug | D52: 19030 | E52: =VLOOKUP($A52,'Salary Projections 2026'!$A:$D,2,FALSE) -> 11884 | F52: =D52-E52 -> 7146 | G52: 19030 | H52: =VLOOKUP($A52,'Salary Projections 2026'!$A:$D,2,FALSE) -> 11884 | I52: =G52-H52 -> 7146 | J52: 19030 | K52: =VLOOKUP($A52,'Salary Projections 2026'!$A:$D,2,FALSE) -> 11884 | L52: =J52-K52 -> 7146 | M52: 19030 | N52: =VLOOKUP($A52,'Salary Projections 2026'!$A:$D,3,FALSE) -> 11884 | O52: =M52-N52 -> 7146 | P52: 19030 | Q52: =VLOOKUP($A52,'Salary Projections 2026'!$A:$D,3,FALSE) -> 11884 | R52: =P52-Q52 -> 7146 | S52: 19030 | T52: =VLOOKUP($A52,'Salary Projections 2026'!$A:$D,3,FALSE) -> 11884 | U52: =S52-T52 -> 7146 | V52: 19030 | W52: =VLOOKUP($A52,'Salary Projections 2026'!$A:$D,3,FALSE) -> 11884 | X52: =V52-W52 -> 7146 | Y52: 19030 | Z52: =VLOOKUP($A52,'Salary Projections 2026'!$A:$D,3,FALSE) -> 11884 | AA52: =Y52-Z52 -> 7146 | AB52: 19030 | AC52: =VLOOKUP($A52,'Salary Projections 2026'!$A:$D,3,FALSE) -> 11884 | AD52: =AB52-AC52 -> 7146 | AE52: 19030 | AF52: =VLOOKUP($A52,'Salary Projections 2026'!$A:$D,4,FALSE) -> 11884 | AG52: =AE52-AF52 -> 7146 | AH52: 19030 | AI52: =VLOOKUP($A52,'Salary Projections 2026'!$A:$D,4,FALSE) -> 11884 | AJ52: =AH52-AI52 -> 7146 | AK52: 19030 | AL52: =VLOOKUP($A52,'Salary Projections 2026'!$A:$D,4,FALSE) -> 11884 | AM52: =AK52-AL52 -> 7146 | AN52: {=SUMPRODUCT((D$1:AK$1<>"Margin")*(D$1:AK$1<>"Salary_$600")*D52:AK52)} -> 228360 | AO52: {=SUMPRODUCT((D$1:AM$1="Margin")*D52:AM52)} -> 85752 | AP52: SOW valid until Dec 31, 2026. In the 2026 SOW the bill rate has been increased by 10% | AQ52: 100% | AR52: Molecular Devices | AS52: DS10_Secured | AU52: 188454 | AV52: 193200 | AW52: 51900
A53: RingCentral Web Development | B53: Neeraj | C53: Staff Aug | D53: 27325 | E53: =VLOOKUP($A53,'Salary Projections 2026'!$A:$D,2,FALSE) -> 13073 | F53: =D53-E53 -> 14252 | G53: 29275 | H53: =VLOOKUP($A53,'Salary Projections 2026'!$A:$D,2,FALSE) -> 13073 | I53: =G53-H53 -> 16202 | J53: =650+27325 -> 27975 | K53: =VLOOKUP($A53,'Salary Projections 2026'!$A:$D,2,FALSE) -> 13073 | L53: =J53-K53 -> 14902 | M53: =650+27325 -> 27975 | N53: =VLOOKUP($A53,'Salary Projections 2026'!$A:$D,3,FALSE) -> 13973 | O53: =M53-N53 -> 14002 | P53: =650+27325 -> 27975 | Q53: =VLOOKUP($A53,'Salary Projections 2026'!$A:$D,3,FALSE) -> 13973 | R53: =P53-Q53 -> 14002 | S53: =650+27325 -> 27975 | T53: =VLOOKUP($A53,'Salary Projections 2026'!$A:$D,3,FALSE) -> 13973 | U53: =S53-T53 -> 14002 | V53: =650+27325 -> 27975 | W53: =VLOOKUP($A53,'Salary Projections 2026'!$A:$D,3,FALSE) -> 13973 | X53: =V53-W53 -> 14002 | Y53: =650+27325 -> 27975 | Z53: =VLOOKUP($A53,'Salary Projections 2026'!$A:$D,3,FALSE) -> 13973 | AA53: =Y53-Z53 -> 14002 | AB53: =650+27325 -> 27975 | AC53: =VLOOKUP($A53,'Salary Projections 2026'!$A:$D,3,FALSE) -> 13973 | AD53: =AB53-AC53 -> 14002 | AE53: =650+27325 -> 27975 | AF53: =VLOOKUP($A53,'Salary Projections 2026'!$A:$D,4,FALSE) -> 13973 | AG53: =AE53-AF53 -> 14002 | AH53: =650+27325 -> 27975 | AI53: =VLOOKUP($A53,'Salary Projections 2026'!$A:$D,4,FALSE) -> 13973 | AJ53: =AH53-AI53 -> 14002 | AK53: =650+27325 -> 27975 | AL53: =VLOOKUP($A53,'Salary Projections 2026'!$A:$D,4,FALSE) -> 13973 | AM53: =AK53-AL53 -> 14002 | AN53: {=SUMPRODUCT((D$1:AK$1<>"Margin")*(D$1:AK$1<>"Salary_$600")*D53:AK53)} -> 336350 | AO53: {=SUMPRODUCT((D$1:AM$1="Margin")*D53:AM53)} -> 171374 | AP53: Sow for the period Jan - Mar 2026 has been submitted for approval Compared to 2025, the client has reduced the team size by four resources. | AQ53: 100% | AR53: RingCentral | AS53: DS10_Secured | AU53: 551110 | AV53: 503752 | AW53: 125925
A54: SEMI - PM, Drupal Developer, Designer & Shopify Full Stack Developer | B54: Neeraj | C54: Staff Aug | D54: 16666 | E54: =VLOOKUP($A54,'Salary Projections 2026'!$A:$D,2,FALSE) -> 14938 | F54: =D54-E54 -> 1728 | G54: 16666 | H54: =VLOOKUP($A54,'Salary Projections 2026'!$A:$D,2,FALSE) -> 14938 | I54: =G54-H54 -> 1728 | J54: 16666 | K54: =VLOOKUP($A54,'Salary Projections 2026'!$A:$D,2,FALSE) -> 14938 | L54: =J54-K54 -> 1728 | M54: 16666 | N54: =VLOOKUP($A54,'Salary Projections 2026'!$A:$D,3,FALSE) -> 14938 | O54: =M54-N54 -> 1728 | P54: 16666 | Q54: =VLOOKUP($A54,'Salary Projections 2026'!$A:$D,3,FALSE) -> 14938 | R54: =P54-Q54 -> 1728 | S54: 16666 | T54: =VLOOKUP($A54,'Salary Projections 2026'!$A:$D,3,FALSE) -> 14938 | U54: =S54-T54 -> 1728 | V54: 16666 | W54: =VLOOKUP($A54,'Salary Projections 2026'!$A:$D,3,FALSE) -> 14938 | X54: =V54-W54 -> 1728 | Y54: 16666 | Z54: =VLOOKUP($A54,'Salary Projections 2026'!$A:$D,3,FALSE) -> 14938 | AA54: =Y54-Z54 -> 1728 | AB54: 16666 | AC54: =VLOOKUP($A54,'Salary Projections 2026'!$A:$D,3,FALSE) -> 14938 | AD54: =AB54-AC54 -> 1728 | AE54: 16666 | AF54: =VLOOKUP($A54,'Salary Projections 2026'!$A:$D,3,FALSE) -> 14938 | AG54: =AE54-AF54 -> 1728 | AH54: 16666 | AI54: =VLOOKUP($A54,'Salary Projections 2026'!$A:$D,3,FALSE) -> 14938 | AJ54: =AH54-AI54 -> 1728 | AK54: 16666 | AL54: =VLOOKUP($A54,'Salary Projections 2026'!$A:$D,3,FALSE) -> 14938 | AM54: =AK54-AL54 -> 1728 | AN54: {=SUMPRODUCT((D$1:AK$1<>"Margin")*(D$1:AK$1<>"Salary_$600")*D54:AK54)} -> 199992 | AO54: {=SUMPRODUCT((D$1:AM$1="Margin")*D54:AM54)} -> 20736 | AP54: SOW valid for duration Aug16, 2025 to Aug 15, 2026 | AQ54: 100% | AR54: SEMI | AS54: DS10_Secured | AU54: 200992 | AV54: 199992 | AW54: 49998
A55: UiPath Web Development | B55: Neeraj | C55: Staff Aug | D55: =45600-4600 -> 41000 | E55: 25641 | F55: =D55-E55 -> 15359 | G55: 31800 | H55: =VLOOKUP($A55,'Salary Projections 2026'!$A:$D,2,FALSE) -> 20001 | I55: =G55-H55 -> 11799 | J55: 31800 | K55: =VLOOKUP($A55,'Salary Projections 2026'!$A:$D,2,FALSE) -> 20001 | L55: =J55-K55 -> 11799 | M55: 31800 | N55: =VLOOKUP($A55,'Salary Projections 2026'!$A:$D,3,FALSE) -> 20001 | O55: =M55-N55 -> 11799 | P55: 31800 | Q55: =VLOOKUP($A55,'Salary Projections 2026'!$A:$D,3,FALSE) -> 20001 | R55: =P55-Q55 -> 11799 | S55: 31800 | T55: =VLOOKUP($A55,'Salary Projections 2026'!$A:$D,3,FALSE) -> 20001 | U55: =S55-T55 -> 11799 | V55: 31800 | W55: =VLOOKUP($A55,'Salary Projections 2026'!$A:$D,3,FALSE) -> 20001 | X55: =V55-W55 -> 11799 | Y55: 31800 | Z55: =VLOOKUP($A55,'Salary Projections 2026'!$A:$D,3,FALSE) -> 20001 | AA55: =Y55-Z55 -> 11799 | AB55: 31800 | AC55: =VLOOKUP($A55,'Salary Projections 2026'!$A:$D,3,FALSE) -> 20001 | AD55: =AB55-AC55 -> 11799 | AE55: 31800 | AF55: =VLOOKUP($A55,'Salary Projections 2026'!$A:$D,4,FALSE) -> 20001 | AG55: =AE55-AF55 -> 11799 | AH55: 31800 | AI55: =VLOOKUP($A55,'Salary Projections 2026'!$A:$D,4,FALSE) -> 20001 | AJ55: =AH55-AI55 -> 11799 | AK55: 31800 | AL55: =VLOOKUP($A55,'Salary Projections 2026'!$A:$D,4,FALSE) -> 20001 | AM55: =AK55-AL55 -> 11799 | AN55: {=SUMPRODUCT((D$1:AK$1<>"Margin")*(D$1:AK$1<>"Salary_$600")*D55:AK55)} -> 390800 | AO55: {=SUMPRODUCT((D$1:AM$1="Margin")*D55:AM55)} -> 145148 | AP55: SOW valid until 31 Jan, 2026 For SOW Renewal period Feb-Apr 2026 there is a reduction in team size by 1 resource | AQ55: 100% | AR55: UiPath | AS55: DS10_Secured | AU55: 486086 | AV55: 533400 | AW55: 127600
A56: YetiMyFriend App | B56: Neeraj | C56: Staff Aug | D56: 5060 | E56: =VLOOKUP($A56,'Salary Projections 2026'!$A:$D,2,FALSE) -> 3698 | F56: =D56-E56 -> 1362 | G56: 4700 | H56: =VLOOKUP($A56,'Salary Projections 2026'!$A:$D,2,FALSE) -> 3698 | I56: =G56-H56 -> 1002 | J56: 4680 | K56: =VLOOKUP($A56,'Salary Projections 2026'!$A:$D,2,FALSE) -> 3698 | L56: =J56-K56 -> 982 | M56: 4580 | N56: =VLOOKUP($A56,'Salary Projections 2026'!$A:$D,3,FALSE) -> 3698 | O56: =M56-N56 -> 882 | P56: 4560 | Q56: =VLOOKUP($A56,'Salary Projections 2026'!$A:$D,3,FALSE) -> 3698 | R56: =P56-Q56 -> 862 | S56: 4500 | T56: =VLOOKUP($A56,'Salary Projections 2026'!$A:$D,3,FALSE) -> 3698 | U56: =S56-T56 -> 802 | V56: 4500 | W56: =VLOOKUP($A56,'Salary Projections 2026'!$A:$D,3,FALSE) -> 3698 | X56: =V56-W56 -> 802 | Y56: 4500 | Z56: =VLOOKUP($A56,'Salary Projections 2026'!$A:$D,3,FALSE) -> 3698 | AA56: =Y56-Z56 -> 802 | AB56: 4500 | AC56: =VLOOKUP($A56,'Salary Projections 2026'!$A:$D,3,FALSE) -> 3698 | AD56: =AB56-AC56 -> 802 | AE56: 4500 | AF56: =VLOOKUP($A56,'Salary Projections 2026'!$A:$D,4,FALSE) -> 3698 | AG56: =AE56-AF56 -> 802 | AH56: 4500 | AI56: =VLOOKUP($A56,'Salary Projections 2026'!$A:$D,4,FALSE) -> 3698 | AJ56: =AH56-AI56 -> 802 | AK56: 4500 | AL56: =VLOOKUP($A56,'Salary Projections 2026'!$A:$D,4,FALSE) -> 3698 | AM56: =AK56-AL56 -> 802 | AN56: {=SUMPRODUCT((D$1:AK$1<>"Margin")*(D$1:AK$1<>"Salary_$600")*D56:AK56)} -> 55080 | AO56: {=SUMPRODUCT((D$1:AM$1="Margin")*D56:AM56)} -> 10704 | AP56: Open-ended SOW. | AQ56: 100% | AR56: YetiMyFriend | AS56: DS10_Secured | AU56: 29847 | AV56: 58661 | AW56: 13981
A58: Sub-total : Track 1 | D58: =SUM(D4:D57) -> 442851 | F58: =SUM(F4:F57) -> 92992.333 | G58: =SUM(G4:G57) -> 431076 | I58: =SUM(I4:I57) -> 85926.333 | J58: =SUM(J4:J57) -> 636198 | L58: =SUM(L4:L57) -> 274409.83 | M58: =SUM(M4:M57) -> 465386 | O58: =SUM(O4:O57) -> 139597 | P58: =SUM(P4:P57) -> 426791 | R58: =SUM(R4:R57) -> 95988.093 | S58: =SUM(S4:S57) -> 459706 | U58: =SUM(U4:U57) -> 115582.37 | V58: =SUM(V4:V57) -> 420401 | X58: =SUM(X4:X57) -> 97444.37 | Y58: =SUM(Y4:Y57) -> 432451 | AA58: =SUM(AA4:AA57) -> 103999.37 | AB58: =SUM(AB4:AB57) -> 584241 | AD58: =SUM(AD4:AD57) -> 255789.37 | AE58: =SUM(AE4:AE57) -> 480731 | AG58: =SUM(AG4:AG57) -> 152279.37 | AH58: =SUM(AH4:AH57) -> 446611 | AJ58: =SUM(AJ4:AJ57) -> 106159.37 | AK58: =SUM(AK4:AK57) -> 459931 | AM58: =SUM(AM4:AM57) -> 119488.37 | AN58: =SUM(AN4:AN57) -> 5686374 | AO58: =SUM(AO4:AO57) -> 1639656.2
A60: Solutions and Staff Augmentation (Projects) - Track 2 | D60: 0 | E60: 0 | F60: 0 | G60: 0 | H60: 0 | I60: 0 | J60: 0 | K60: 0 | L60: 0 | M60: 0 | N60: 0 | O60: 0 | P60: 0 | Q60: 0 | R60: 0 | S60: 0 | T60: 0 | U60: 0 | V60: 0 | W60: 0 | X60: 0 | Y60: 0 | Z60: 0 | AA60: 0 | AB60: 0 | AC60: 0 | AD60: 0 | AE60: 0 | AF60: 0 | AG60: 0 | AH60: 0 | AI60: 0 | AJ60: 0 | AK60: 0 | AL60: 0 | AM60: 0 | AN60: 0 | AO60: 0 | AR60: Track 2-Secured
AS61: DS20_Secured
AS62: DS20_Secured
A63: Sub-total : Track 2 | D63: =SUM(D61:D62) -> 0 | G63: =SUM(G61:G62) -> 0 | J63: =SUM(J61:J62) -> 0 | M63: =SUM(M61:M62) -> 0 | P63: =SUM(P61:P62) -> 0 | S63: =SUM(S61:S62) -> 0 | V63: =SUM(V61:V62) -> 0 | Y63: =SUM(Y61:Y62) -> 0 | AB63: =SUM(AB61:AB62) -> 0 | AE63: =SUM(AE61:AE62) -> 0 | AH63: =SUM(AH61:AH62) -> 0 | AK63: =SUM(AK61:AK62) -> 0 | AN63: =SUM(AN61:AN62) -> 0
A65: TOTAL Secured | D65: =+D58+D63 -> 442851 | G65: =+G58+G63 -> 431076 | J65: =+J58+J63 -> 636198 | M65: =+M58+M63 -> 465386 | P65: =+P58+P63 -> 426791 | S65: =+S58+S63 -> 459706 | V65: =+V58+V63 -> 420401 | Y65: =+Y58+Y63 -> 432451 | AB65: =+AB58+AB63 -> 584241 | AE65: =+AE58+AE63 -> 480731 | AH65: =+AH58+AH63 -> 446611 | AK65: =+AK58+AK63 -> 459931 | AN65: =+AN58+AN63 -> 5686374 | AO65: {=SUMPRODUCT((D$1:AK$1="Margin")*D65:AK65)} -> 0
A67: Track 1 | AR67: Track 1-Projections
A68: Floma - Figma Design Production Services | B68: Neeraj | C68: Project | P68: =3500/2 -> 1750 | Q68: 900 | R68: =P68-Q68 -> 850 | X68: =V68-W68 -> 0 | Y68: =3500 -> 3500 | Z68: 900 | AA68: =Y68-Z68 -> 2600 | AB68: =3500 -> 3500 | AC68: 900 | AD68: =AB68-AC68 -> 2600 | AE68: =3500 -> 3500 | AF68: 900 | AG68: =AE68-AF68 -> 2600 | AH68: =3500 -> 3500 | AI68: 900 | AJ68: =AH68-AI68 -> 2600 | AK68: =3500 -> 3500 | AL68: 900 | AM68: =AK68-AL68 -> 2600 | AN68: {=SUMPRODUCT((D$1:AK$1<>"Margin")*(D$1:AK$1<>"Salary_$600")*D68:AK68)} -> 19250 | AO68: {=SUMPRODUCT((D$1:AK$1="Margin")*D68:AK68)} -> 11250 | AP68: Proposal submitted | AQ68: 50% | AR68: HAL | AS68: DS30_Projection
A69: HIL - Resolve AI | B69: Vijay | T69: =V69/4 -> 4600 | U69: =S69-T69 -> -4600 | V69: 18400 | W69: =V69/4 -> 4600 | X69: =V69-W69 -> 13800 | Y69: 2700 | Z69: =Y69/2 -> 1350 | AA69: =Y69-Z69 -> 1350 | AB69: 2700 | AC69: =AB69/2 -> 1350 | AD69: =AB69-AC69 -> 1350 | AE69: 2700 | AF69: =AE69/2 -> 1350 | AG69: =AE69-AF69 -> 1350 | AH69: 2700 | AI69: =AH69/2 -> 1350 | AJ69: =AH69-AI69 -> 1350 | AK69: 2700 | AL69: =AK69/2 -> 1350 | AM69: =AK69-AL69 -> 1350 | AN69: {=SUMPRODUCT((D$1:AK$1<>"Margin")*(D$1:AK$1<>"Salary_$600")*D69:AK69)} -> 31900 | AO69: {=SUMPRODUCT((D$1:AK$1="Margin")*D69:AK69)} -> 14600 | AP69: Proposal submitted | AQ69: 75% | AR69: Hitachi Asia | AS69: DS30_Projection
A70: HAL: Event ROI Framework and Executive Dashboards | B70: Neeraj | C70: Project | V70: 5500 | W70: 4000 | X70: =V70-W70 -> 1500 | Y70: 5500 | Z70: 4000 | AA70: =Y70-Z70 -> 1500 | AB70: 5500 | AC70: 4000 | AD70: =AB70-AC70 -> 1500 | AE70: 5500 | AF70: 4000 | AG70: =AE70-AF70 -> 1500 | AH70: 5500 | AI70: 4000 | AJ70: =AH70-AI70 -> 1500 | AK70: 5500 | AL70: 4000 | AM70: =AK70-AL70 -> 1500 | AN70: {=SUMPRODUCT((D$1:AK$1<>"Margin")*(D$1:AK$1<>"Salary_$600")*D70:AK70)} -> 33000 | AO70: {=SUMPRODUCT((D$1:AK$1="Margin")*D70:AK70)} -> 7500 | AP70: Proposal under discussion | AQ70: 50% | AR70: HAL | AS70: DS30_Projection
A71: Hitachi Asia (Rail Europe) | B71: Vijay | C71: Project | D71: 0 | F71: =D71*0.3 -> 0 | G71: 0 | I71: =G71*0.3 -> 0 | J71: 0 | L71: =J71*0.3 -> 0 | M71: 0 | O71: =M71*0.3 -> 0 | P71: 0 | R71: =P71*0.3 -> 0 | S71: 75000 | U71: =S71*0.3 -> 22500 | V71: 0 | X71: =V71*0.3 -> 0 | Y71: 0 | AA71: =Y71*0.3 -> 0 | AB71: 0 | AD71: =AB71*0.3 -> 0 | AE71: 75000 | AG71: =AE71*0.3 -> 22500 | AH71: 0 | AJ71: =AH71*0.3 -> 0 | AK71: 0 | AM71: =AK71*0.3 -> 0 | AN71: {=SUMPRODUCT((D$1:AK$1<>"Margin")*(D$1:AK$1<>"Salary_$600")*D71:AK71)} -> 150000 | AO71: {=SUMPRODUCT((D$1:AK$1="Margin")*D71:AK71)} -> 45000 | AQ71: 50% | AR71: Hitachi Asia | AS71: DS30_Projection
A72: AI solutions for Databricks | B72: Neeraj | C72: Project | D72: 0 | F72: =D72*0.3 -> 0 | G72: 0 | I72: =G72*0.3 -> 0 | L72: =J72*0.3 -> 0 | M72: 0 | O72: =M72*0.3 -> 0 | P72: 0 | R72: =P72*0.3 -> 0 | V72: 0 | X72: =V72*0.3 -> 0 | Y72: 0 | AA72: =Y72*0.3 -> 0 | AD72: =AB72*0.3 -> 0 | AE72: 0 | AG72: =AE72*0.3 -> 0 | AH72: 0 | AJ72: =AH72*0.3 -> 0 | AM72: =AK72*0.3 -> 0 | AN72: {=SUMPRODUCT((D$1:AK$1<>"Margin")*(D$1:AK$1<>"Salary_$600")*D72:AK72)} -> 0 | AO72: {=SUMPRODUCT((D$1:AK$1="Margin")*D72:AK72)} -> 0 | AQ72: 50% | AR72: Databricks | AS72: DS30_Projection
A73: Aldevron.com Website Overhaul- Technical RFP | B73: Neeraj | C73: Project | D73: 0 | F73: 0 | G73: 0 | I73: 0 | J73: 0 | L73: 0 | M73: 0 | O73: 0 | P73: 0 | R73: 0 | S73: 35000 | T73: =S73*0.6 -> 21000 | U73: =S73-T73 -> 14000 | V73: 35000 | W73: =V73*0.6 -> 21000 | X73: =V73-W73 -> 14000 | Y73: 35000 | Z73: =Y73*0.6 -> 21000 | AA73: =Y73-Z73 -> 14000 | AB73: 35000 | AC73: =AB73*0.6 -> 21000 | AD73: =AB73-AC73 -> 14000 | AE73: 40000 | AF73: =AE73*0.6 -> 24000 | AG73: =AE73-AF73 -> 16000 | AH73: 0 | AJ73: 0 | AK73: 0 | AM73: 0 | AN73: {=SUMPRODUCT((D$1:AK$1<>"Margin")*(D$1:AK$1<>"Salary_$600")*D73:AK73)} -> 180000 | AO73: {=SUMPRODUCT((D$1:AK$1="Margin")*D73:AK73)} -> 72000 | AP73: Proposal submitted | AR73: Aldevron | AS73: DS30_Projection
D74: =SUM(D68:D73) -> 0 | G74: =SUM(G68:G73) -> 0 | J74: =SUM(J68:J73) -> 0 | M74: =SUM(M68:M73) -> 0 | P74: =SUM(P68:P73) -> 1750 | S74: =SUM(S68:S73) -> 110000 | V74: =SUM(V68:V73) -> 58900 | Y74: =SUM(Y68:Y73) -> 46700 | AB74: =SUM(AB68:AB73) -> 46700 | AE74: =SUM(AE68:AE73) -> 126700 | AH74: =SUM(AH68:AH73) -> 11700 | AK74: =SUM(AK68:AK73) -> 11700 | AN74: =SUM(AN68:AN72) -> 234150
A75: Track 2 | AR75: Track 2-Projections
A76: ADNOC - Mobile Application, CRM and Web Development | B76: Ankur/Neeraj | C76: Staff Aug | D76: 0 | F76: =D76*0.3 -> 0 | G76: 0 | I76: =G76*0.3 -> 0 | J76: 0 | L76: =J76*0.3 -> 0 | M76: 0 | O76: =M76*0.3 -> 0 | P76: 0 | R76: =P76*0.3 -> 0 | S76: 300000 | U76: =S76*0.3 -> 90000 | V76: 0 | X76: =V76*0.3 -> 0 | Y76: 0 | AA76: =Y76*0.3 -> 0 | AB76: 0 | AD76: =AB76*0.3 -> 0 | AE76: 0 | AG76: =AE76*0.3 -> 0 | AH76: 0 | AJ76: =AH76*0.3 -> 0 | AK76: 0 | AM76: =AK76*0.3 -> 0 | AN76: {=SUMPRODUCT((D$1:AK$1<>"Margin")*(D$1:AK$1<>"Salary_$600")*D76:AK76)} -> 300000 | AO76: {=SUMPRODUCT((D$1:AK$1="Margin")*D76:AK76)} -> 90000 | AP76: Top-of-funnel activities - Working with Ankur Rana | AQ76: 25% | AR76: ADNOC | AS76: DS50_Projection
A77: Alliance Technical Group | B77: Raghu/Neeraj | C77: Staff Aug | D77: 0 | F77: =D77*0.3 -> 0 | G77: 0 | I77: =G77*0.3 -> 0 | J77: 0 | L77: =J77*0.3 -> 0 | M77: 0 | O77: =M77*0.3 -> 0 | P77: 0 | R77: =P77*0.3 -> 0 | S77: 200000 | U77: =S77*0.3 -> 60000 | V77: 0 | X77: =V77*0.3 -> 0 | Y77: 0 | AA77: =Y77*0.3 -> 0 | AB77: 0 | AD77: =AB77*0.3 -> 0 | AE77: 0 | AG77: =AE77*0.3 -> 0 | AH77: 0 | AJ77: =AH77*0.3 -> 0 | AK77: 0 | AM77: =AK77*0.3 -> 0 | AN77: {=SUMPRODUCT((D$1:AK$1<>"Margin")*(D$1:AK$1<>"Salary_$600")*D77:AK77)} -> 200000 | AO77: {=SUMPRODUCT((D$1:AK$1="Margin")*D77:AK77)} -> 60000 | AP77: Raghu is working with Romeen to move this | AQ77: 5% | AR77: Alliance Technical Group | AS77: DS50_Projection
A78: Anurag | B78: Anurag/Neeraj | C78: Project | D78: 0 | F78: =D78*0.3 -> 0 | G78: 0 | I78: =G78*0.3 -> 0 | J78: 0 | L78: =J78*0.3 -> 0 | M78: 0 | O78: =M78*0.3 -> 0 | P78: 0 | R78: =P78*0.3 -> 0 | S78: 500000 | U78: =S78*0.3 -> 150000 | V78: 0 | X78: =V78*0.3 -> 0 | Y78: 0 | AA78: =Y78*0.3 -> 0 | AB78: 0 | AD78: =AB78*0.3 -> 0 | AE78: 0 | AG78: =AE78*0.3 -> 0 | AH78: 0 | AJ78: =AH78*0.3 -> 0 | AK78: 0 | AM78: =AK78*0.3 -> 0 | AN78: {=SUMPRODUCT((D$1:AK$1<>"Margin")*(D$1:AK$1<>"Salary_$600")*D78:AK78)} -> 500000 | AO78: {=SUMPRODUCT((D$1:AK$1="Margin")*D78:AK78)} -> 150000 | AQ78: 75% | AR78: Anurag | AS78: DS50_Projection
A79: Fannie Mae RFP | B79: Sukumar/Neeraj | C79: Staff Aug | D79: 0 | F79: =D79*0.3 -> 0 | G79: 0 | I79: =G79*0.3 -> 0 | J79: 0 | L79: =J79*0.3 -> 0 | M79: 0 | O79: =M79*0.3 -> 0 | P79: 0 | R79: =P79*0.3 -> 0 | S79: 0 | U79: =S79*0.3 -> 0 | V79: 0 | X79: =V79*0.3 -> 0 | Y79: 0 | AA79: =Y79*0.3 -> 0 | AB79: 0 | AD79: =AB79*0.3 -> 0 | AE79: 0 | AG79: =AE79*0.3 -> 0 | AH79: 0 | AJ79: =AH79*0.3 -> 0 | AK79: 0 | AM79: =AK79*0.3 -> 0 | AN79: {=SUMPRODUCT((D$1:AK$1<>"Margin")*(D$1:AK$1<>"Salary_$600")*D79:AK79)} -> 0 | AO79: {=SUMPRODUCT((D$1:AK$1="Margin")*D79:AK79)} -> 0 | AP79: Fannie Mae RFP being developed in collaboration with OSG. On hold for now | AQ79: 5% | AR79: Fannie Mae | AS79: DS50_Projection
A80: GIZ - Nigeria Energy Support Programme | B80: Ankur/Neeraj | C80: Project | D80: 0 | F80: =D80*0.3 -> 0 | G80: 0 | I80: =G80*0.3 -> 0 | J80: 0 | L80: =J80*0.3 -> 0 | M80: 0 | O80: =M80*0.3 -> 0 | P80: 0 | R80: =P80*0.3 -> 0 | S80: 190000 | U80: =S80*0.3 -> 57000 | V80: 0 | X80: =V80*0.3 -> 0 | Y80: 0 | AA80: =Y80*0.3 -> 0 | AB80: 0 | AD80: =AB80*0.3 -> 0 | AE80: 0 | AG80: =AE80*0.3 -> 0 | AH80: 0 | AJ80: =AH80*0.3 -> 0 | AK80: 0 | AM80: =AK80*0.3 -> 0 | AN80: {=SUMPRODUCT((D$1:AK$1<>"Margin")*(D$1:AK$1<>"Salary_$600")*D80:AK80)} -> 190000 | AO80: {=SUMPRODUCT((D$1:AK$1="Margin")*D80:AK80)} -> 57000 | AP80: RFP response submitted - Working with Ankur Rana | AQ80: 10% | AR80: GIZ - I | AS80: DS50_Projection
A81: GIZ - II | B81: Ankur/Neeraj | C81: Project | D81: 0 | F81: =D81*0.3 -> 0 | G81: 0 | I81: =G81*0.3 -> 0 | J81: 0 | L81: =J81*0.3 -> 0 | M81: 0 | O81: =M81*0.3 -> 0 | P81: 0 | R81: =P81*0.3 -> 0 | S81: 200000 | U81: =S81*0.3 -> 60000 | V81: 0 | X81: =V81*0.3 -> 0 | Y81: 0 | AA81: =Y81*0.3 -> 0 | AB81: 0 | AD81: =AB81*0.3 -> 0 | AE81: 0 | AG81: =AE81*0.3 -> 0 | AH81: 0 | AJ81: =AH81*0.3 -> 0 | AK81: 0 | AM81: =AK81*0.3 -> 0 | AN81: {=SUMPRODUCT((D$1:AK$1<>"Margin")*(D$1:AK$1<>"Salary_$600")*D81:AK81)} -> 200000 | AO81: {=SUMPRODUCT((D$1:AK$1="Margin")*D81:AK81)} -> 60000 | AP81: RFP response submitted - Working with Ankur Rana | AQ81: 10% | AR81: GIZ - II | AS81: DS50_Projection
A82: Web Marketing IHG | B82: Ankur/Raj/Neeraj | C82: Project | D82: 0 | F82: =D82*0.3 -> 0 | G82: 0 | I82: =G82*0.3 -> 0 | J82: 0 | L82: =J82*0.3 -> 0 | M82: 0 | O82: =M82*0.3 -> 0 | P82: 0 | R82: =P82*0.3 -> 0 | S82: 300000 | U82: =S82*0.3 -> 90000 | V82: 0 | X82: =V82*0.3 -> 0 | Y82: 0 | AA82: =Y82*0.3 -> 0 | AB82: 0 | AD82: =AB82*0.3 -> 0 | AE82: 0 | AG82: =AE82*0.3 -> 0 | AH82: 0 | AJ82: =AH82*0.3 -> 0 | AK82: 0 | AM82: =AK82*0.3 -> 0 | AN82: {=SUMPRODUCT((D$1:AK$1<>"Margin")*(D$1:AK$1<>"Salary_$600")*D82:AK82)} -> 300000 | AO82: {=SUMPRODUCT((D$1:AK$1="Margin")*D82:AK82)} -> 90000 | AP82: Request sent to Raj Verma to follow up with Vivien. In addition to this met with Ketan through Ankur Rana | AQ82: 25% | AR82: IHG | AS82: DS50_Projection
A83: Web Marketing support for Inatech | B83: Ram/Neeraj | C83: Project | D83: 0 | F83: =D83*0.3 -> 0 | G83: 0 | I83: =G83*0.3 -> 0 | J83: 0 | L83: =J83*0.3 -> 0 | M83: 0 | O83: =M83*0.3 -> 0 | P83: 0 | R83: =P83*0.3 -> 0 | S83: 300000 | U83: =S83*0.3 -> 90000 | V83: 0 | X83: =V83*0.3 -> 0 | Y83: 0 | AA83: =Y83*0.3 -> 0 | AB83: 0 | AD83: =AB83*0.3 -> 0 | AE83: 0 | AG83: =AE83*0.3 -> 0 | AH83: 0 | AJ83: =AH83*0.3 -> 0 | AK83: 0 | AM83: =AK83*0.3 -> 0 | AN83: {=SUMPRODUCT((D$1:AK$1<>"Margin")*(D$1:AK$1<>"Salary_$600")*D83:AK83)} -> 300000 | AO83: {=SUMPRODUCT((D$1:AK$1="Margin")*D83:AK83)} -> 90000 | AP83: Top-of-funnel activities. Ram working with Raghu to discuss the options | AQ83: 25% | AR83: Inatech | AS83: DS50_Projection
A84: Social Media Management Platform Provider - Miller Knoll | B84: Ankur/Neeraj | C84: Project | D84: 0 | F84: =D84*0.3 -> 0 | G84: 0 | I84: =G84*0.3 -> 0 | J84: 0 | L84: =J84*0.3 -> 0 | M84: 0 | O84: =M84*0.3 -> 0 | P84: 0 | R84: =P84*0.3 -> 0 | U84: =S84*0.3 -> 0 | V84: 0 | X84: =V84*0.3 -> 0 | Y84: 0 | AA84: =Y84*0.3 -> 0 | AB84: 0 | AD84: =AB84*0.3 -> 0 | AE84: 0 | AG84: =AE84*0.3 -> 0 | AH84: 0 | AJ84: =AH84*0.3 -> 0 | AK84: 0 | AM84: =AK84*0.3 -> 0 | AN84: {=SUMPRODUCT((D$1:AK$1<>"Margin")*(D$1:AK$1<>"Salary_$600")*D84:AK84)} -> 0 | AO84: {=SUMPRODUCT((D$1:AK$1="Margin")*D84:AK84)} -> 0 | AP84: POC approach dropped. Raghu and Raj met the Millet Knoll at Miami and will make it moving | AQ84: 5% | AR84: Miller Knoll | AS84: DS50_Projection
A85: OSG - Castrol | B85: Raghu/Neeraj | C85: Project | D85: 0 | F85: =D85*0.3 -> 0 | G85: 0 | I85: =G85*0.3 -> 0 | J85: 0 | L85: =J85*0.3 -> 0 | M85: 0 | O85: =M85*0.3 -> 0 | P85: 0 | R85: =P85*0.3 -> 0 | S85: 300000 | U85: =S85*0.3 -> 90000 | V85: 0 | X85: =V85*0.3 -> 0 | Y85: 0 | AA85: =Y85*0.3 -> 0 | AB85: 0 | AD85: =AB85*0.3 -> 0 | AE85: 0 | AG85: =AE85*0.3 -> 0 | AH85: 0 | AJ85: =AH85*0.3 -> 0 | AK85: 0 | AM85: =AK85*0.3 -> 0 | AN85: {=SUMPRODUCT((D$1:AK$1<>"Margin")*(D$1:AK$1<>"Salary_$600")*D85:AK85)} -> 300000 | AO85: {=SUMPRODUCT((D$1:AK$1="Margin")*D85:AK85)} -> 90000 | AQ85: 50% | AR85: OSG - Castrol | AS85: DS50_Projection
A86: OSG - Dewsy | B86: Sukumar/Neeraj | C86: Project | D86: 0 | F86: =D86*0.3 -> 0 | G86: 0 | I86: =G86*0.3 -> 0 | J86: 0 | L86: =J86*0.3 -> 0 | M86: 0 | O86: =M86*0.3 -> 0 | P86: 0 | R86: =P86*0.3 -> 0 | S86: 500000 | U86: =S86*0.3 -> 150000 | V86: 0 | X86: =V86*0.3 -> 0 | Y86: 0 | AA86: =Y86*0.3 -> 0 | AB86: 0 | AD86: =AB86*0.3 -> 0 | AE86: 0 | AG86: =AE86*0.3 -> 0 | AH86: 0 | AJ86: =AH86*0.3 -> 0 | AK86: 0 | AM86: =AK86*0.3 -> 0 | AN86: {=SUMPRODUCT((D$1:AK$1<>"Margin")*(D$1:AK$1<>"Salary_$600")*D86:AK86)} -> 500000 | AO86: {=SUMPRODUCT((D$1:AK$1="Margin")*D86:AK86)} -> 150000 | AQ86: 25% | AR86: OSG - Dewsy | AS86: DS50_Projection
A87: OSG - DHA | B87: Sukumar/Neeraj | C87: Project | D87: 0 | F87: =D87*0.3 -> 0 | G87: 0 | I87: =G87*0.3 -> 0 | J87: 0 | L87: =J87*0.3 -> 0 | M87: 0 | O87: =M87*0.3 -> 0 | P87: 0 | R87: =P87*0.3 -> 0 | S87: 1500000 | U87: =S87*0.3 -> 450000 | V87: 0 | X87: =V87*0.3 -> 0 | Y87: 0 | AA87: =Y87*0.3 -> 0 | AB87: 0 | AD87: =AB87*0.3 -> 0 | AE87: 0 | AG87: =AE87*0.3 -> 0 | AH87: 0 | AJ87: =AH87*0.3 -> 0 | AK87: 0 | AM87: =AK87*0.3 -> 0 | AN87: {=SUMPRODUCT((D$1:AK$1<>"Margin")*(D$1:AK$1<>"Salary_$600")*D87:AK87)} -> 1500000 | AO87: {=SUMPRODUCT((D$1:AK$1="Margin")*D87:AK87)} -> 450000 | AQ87: 25% | AR87: OSG - DHA | AS87: DS50_Projection
A88: OSG - DHA TB | B88: Sukumar/Neeraj | C88: Project | D88: 0 | F88: =D88*0.3 -> 0 | G88: 0 | I88: =G88*0.3 -> 0 | J88: 0 | L88: =J88*0.3 -> 0 | M88: 0 | O88: =M88*0.3 -> 0 | P88: 0 | R88: =P88*0.3 -> 0 | S88: 2500000 | U88: =S88*0.3 -> 750000 | V88: 0 | X88: =V88*0.3 -> 0 | Y88: 0 | AA88: =Y88*0.3 -> 0 | AB88: 0 | AD88: =AB88*0.3 -> 0 | AE88: 0 | AG88: =AE88*0.3 -> 0 | AH88: 0 | AJ88: =AH88*0.3 -> 0 | AK88: 0 | AM88: =AK88*0.3 -> 0 | AN88: {=SUMPRODUCT((D$1:AK$1<>"Margin")*(D$1:AK$1<>"Salary_$600")*D88:AK88)} -> 2500000 | AO88: {=SUMPRODUCT((D$1:AK$1="Margin")*D88:AK88)} -> 750000 | AQ88: 25% | AR88: OSG - DHA TB | AS88: DS50_Projection
A89: OSG - Misc | B89: Sukumar/Neeraj | C89: Project | D89: 0 | F89: =D89*0.3 -> 0 | G89: 0 | I89: =G89*0.3 -> 0 | J89: 0 | L89: =J89*0.3 -> 0 | M89: 0 | O89: =M89*0.3 -> 0 | P89: 0 | R89: =P89*0.3 -> 0 | S89: 3000000 | U89: =S89*0.3 -> 900000 | V89: 0 | X89: =V89*0.3 -> 0 | Y89: 0 | AA89: =Y89*0.3 -> 0 | AB89: 0 | AD89: =AB89*0.3 -> 0 | AE89: 0 | AG89: =AE89*0.3 -> 0 | AH89: 0 | AJ89: =AH89*0.3 -> 0 | AK89: 0 | AM89: =AK89*0.3 -> 0 | AN89: {=SUMPRODUCT((D$1:AK$1<>"Margin")*(D$1:AK$1<>"Salary_$600")*D89:AK89)} -> 3000000 | AO89: {=SUMPRODUCT((D$1:AK$1="Margin")*D89:AK89)} -> 900000 | AP89: Church and Dwight, BP/Castrol, Lloyds Banking Group, Medline, Tandem Diabetes, Boston Scientific, BD (Becton Dickinson) Breast Surgery, Johnson and Johnson Medical Devices, Kenvue, Abbott Diagnostics | AQ89: 25% | AR89: OSG - Misc | AS89: DS50_Projection
A90: Reasonant Clinical | B90: Raghu/Neeraj | C90: Project | D90: 0 | F90: =D90*0.3 -> 0 | G90: 0 | I90: =G90*0.3 -> 0 | J90: 0 | L90: =J90*0.3 -> 0 | M90: 0 | O90: =M90*0.3 -> 0 | P90: 0 | R90: =P90*0.3 -> 0 | S90: 0 | U90: =S90*0.3 -> 0 | V90: 0 | X90: =V90*0.3 -> 0 | Y90: 0 | AA90: =Y90*0.3 -> 0 | AB90: 0 | AD90: =AB90*0.3 -> 0 | AE90: 0 | AG90: =AE90*0.3 -> 0 | AH90: 0 | AJ90: =AH90*0.3 -> 0 | AK90: 0 | AM90: =AK90*0.3 -> 0 | AN90: {=SUMPRODUCT((D$1:AK$1<>"Margin")*(D$1:AK$1<>"Salary_$600")*D90:AK90)} -> 0 | AO90: {=SUMPRODUCT((D$1:AK$1="Margin")*D90:AK90)} -> 0 | AQ90: 5% | AR90: Reasonant Clinical | AS90: DS50_Projection
A91: Ogilvy | B91: Raghu/Neeraj | C91: Project | D91: 0 | F91: 0 | G91: 0 | I91: 0 | J91: 0 | L91: 0 | M91: 0 | O91: 0 | P91: 0 | R91: 0 | S91: 0 | U91: 0 | V91: 0 | X91: 0 | Y91: 0 | AA91: 0 | AB91: 0 | AD91: 0 | AE91: 0 | AG91: 0 | AH91: 0 | AJ91: 0 | AK91: 0 | AM91: 0 | AN91: {=SUMPRODUCT((D$1:AK$1<>"Margin")*(D$1:AK$1<>"Salary_$600")*D91:AK91)} -> 0 | AO91: {=SUMPRODUCT((D$1:AK$1="Margin")*D91:AK91)} -> 0 | AQ91: 5% | AR91: Ogilvy | AS91: DS50_Projection
A92: Alcon/Web Marketing | B92: Ram/Neeraj | D92: =SUM(D76:D91) -> 0 | F92: =SUM(F76:F91) -> 0 | G92: =SUM(G76:G91) -> 0 | I92: =SUM(I76:I91) -> 0 | J92: =SUM(J76:J91) -> 0 | L92: =SUM(L76:L91) -> 0 | M92: =SUM(M76:M91) -> 0 | O92: =SUM(O76:O91) -> 0 | P92: =SUM(P76:P91) -> 0 | S92: =SUM(S76:S91) -> 9790000 | U92: =SUM(U76:U91) -> 2937000 | V92: =SUM(V76:V91) -> 0 | X92: =SUM(X76:X91) -> 0 | Y92: =SUM(Y76:Y91) -> 0 | AA92: =SUM(AA76:AA91) -> 0 | AB92: =SUM(AB76:AB91) -> 0 | AE92: =SUM(AE76:AE91) -> 0 | AH92: =SUM(AH76:AH91) -> 0 | AK92: =SUM(AK76:AK91) -> 0 | AN92: =SUM(AN76:AN91) -> 9790000 | AR92: Alcone | AS92: DS50_Projection
A93: TOTAL Projection | D93: =SUM(D68:D91) -> 0 | F93: =D93*0.3 -> 0 | G93: =SUM(G68:G91) -> 0 | I93: =G93*0.3 -> 0 | J93: =SUM(J68:J91) -> 0 | L93: =J93*0.3 -> 0 | M93: =SUM(M68:M91) -> 0 | O93: =M93*0.3 -> 0 | P93: =SUM(P68:P91) -> 3500 | R93: =P93*0.3 -> 1050 | S93: =SUM(S68:S91) -> 10010000 | U93: =S93*0.3 -> 3003000 | V93: =SUM(V68:V91) -> 117800 | X93: =V93*0.3 -> 35340 | Y93: =SUM(Y68:Y91) -> 93400 | AA93: =Y93*0.3 -> 28020 | AB93: =SUM(AB68:AB91) -> 93400 | AD93: =AB93*0.3 -> 28020 | AE93: =SUM(AE68:AE91) -> 253400 | AG93: =AE93*0.3 -> 76020 | AH93: =SUM(AH68:AH91) -> 23400 | AJ93: =AH93*0.3 -> 7020 | AK93: =SUM(AK68:AK91) -> 23400 | AM93: =AK93*0.3 -> 7020 | AN93: =+AN92+AN74 -> 10024150 | AO93: {=SUMPRODUCT((D$1:AK$1="Margin")*D93:AK93)} -> 3178470
A98: TOTAL Prospecting
A100: Secured | D100: =D65 -> 442851 | G100: =G65 -> 431076 | J100: =J65 -> 636198 | M100: =M65 -> 465386 | P100: =P65 -> 426791 | S100: =S65 -> 459706 | V100: =V65 -> 420401 | Y100: =Y65 -> 432451 | AB100: =AB65 -> 584241 | AE100: =AE65 -> 480731 | AH100: =AH65 -> 446611 | AK100: =AK65 -> 459931 | AN100: =AN65 -> 5686374
A101: Projection | D101: =D93 -> 0 | G101: =G93 -> 0 | J101: =J93 -> 0 | M101: =M93 -> 0 | P101: =P93 -> 3500 | S101: =S93 -> 10010000 | V101: =V93 -> 117800 | Y101: =Y93 -> 93400 | AB101: =AB93 -> 93400 | AE101: =AE93 -> 253400 | AH101: =AH93 -> 23400 | AK101: =AK93 -> 23400 | AN101: =AN93 -> 10024150
A102: Prospecting | D102: =SUM(D95:D96) -> 0 | G102: =SUM(G95:G96) -> 0 | J102: =SUM(J95:J96) -> 0 | M102: =SUM(M95:M96) -> 0 | P102: =SUM(P95:P96) -> 0 | S102: =SUM(S95:S96) -> 0 | V102: =SUM(V95:V96) -> 0 | Y102: =SUM(Y95:Y96) -> 0 | AB102: =SUM(AB95:AB96) -> 0 | AE102: =SUM(AE95:AE96) -> 0 | AH102: =SUM(AH95:AH96) -> 0 | AK102: =SUM(AK95:AK96) -> 0 | AN102: =SUM(D102:AK102) -> 0
A103: Solutions and Staff Augmentation Total | D103: =D100+D101+D102 -> 442851 | G103: =G100+G101+G102 -> 431076 | J103: =J100+J101+J102 -> 636198 | M103: =M100+M101+M102 -> 465386 | P103: =P100+P101+P102 -> 430291 | S103: =S100+S101+S102 -> 10469706 | V103: =V100+V101+V102 -> 538201 | Y103: =Y100+Y101+Y102 -> 525851 | AB103: =AB100+AB101+AB102 -> 677641 | AE103: =AE100+AE101+AE102 -> 734131 | AH103: =AH100+AH101+AH102 -> 470011 | AK103: =AK100+AK101+AK102 -> 483331 | AN103: =SUM(D103:AK103) -> 16304674
A105: Staffing | AR105: Staffing-Secured
A106: HPE Ami Noss | B106: Manmeet | C106: Staffing | D106: 22692 | F106: 1604.56 | G106: 19728 | I106: 2644.704 | J106: 24112 | L106: 3232.42 | M106: 24112 | O106: 3232.42 | P106: 22194 | R106: 1607 | S106: 22194 | U106: 1607 | V106: 20276 | X106: 1541 | Y106: 23290 | AA106: 1644 | AB106: 20139 | AD106: 1536 | AE106: 22194 | AG106: 1607 | AH106: 20139 | AJ106: 1536 | AK106: 19180 | AM106: 1504 | AN106: {=SUMPRODUCT((D$1:AK$1<>"Margin")*(D$1:AK$1<>"Salary_$600")*D106:AK106)} -> 260250 | AO106: {=SUMPRODUCT((D$1:AM$1="Margin")*D106:AM106)} -> 23296.104 | AP106: SOW valid until Apr 30, 2026 | AQ106: 100% | AR106: HPE | AS106: DS70_Secured | AU106: 1708784 | AV106: 1544346 | AW106: 335532
A107: HPE Rebecca Wissinger | B107: Manmeet | C107: Staffing | D107: 12000 | F107: 640 | G107: 11400 | I107: 1611.2 | J107: 13200 | L107: 1866 | M107: 13200 | O107: 1865.6 | P107: 12150 | R107: 648 | S107: 12150 | U107: 648 | V107: 11100 | X107: 592 | Y107: 12750 | AA107: 680 | AB107: 11025 | AD107: 588 | AE107: 12150 | AG107: 648 | AH107: 11025 | AJ107: 588 | AK107: 10500 | AM107: 560 | AN107: {=SUMPRODUCT((D$1:AK$1<>"Margin")*(D$1:AK$1<>"Salary_$600")*D107:AK107)} -> 142650 | AO107: {=SUMPRODUCT((D$1:AM$1="Margin")*D107:AM107)} -> 10934.8 | AP107: SOW valid until Oct 31, 2026 | AQ107: 100% | AR107: HPE | AS107: DS70_Secured
A108: HPE Budget Mgmt | B108: Manmeet | C108: Staffing | D108: 12096 | F108: 1176 | G108: 8064 | I108: 943.2 | J108: 12096 | L108: 1176 | M108: 11088 | O108: 1078 | P108: 11664 | R108: 1134 | S108: 11664 | U108: 1134 | V108: 10656 | X108: 1036 | Y108: 12240 | AA108: 1190 | AB108: 10584 | AD108: 1029 | AE108: 11664 | AG108: 1134 | AH108: 10584 | AJ108: 1029 | AK108: 10080 | AM108: 980 | AN108: {=SUMPRODUCT((D$1:AK$1<>"Margin")*(D$1:AK$1<>"Salary_$600")*D108:AK108)} -> 132480 | AO108: {=SUMPRODUCT((D$1:AM$1="Margin")*D108:AM108)} -> 13039.2 | AP108: SOW valid until Apr 30, 2026 | AQ108: 100% | AR108: HPE | AS108: DS70_Secured
A109: HPE Tech Compliance | B109: Manmeet | C109: Staffing | D109: 14708 | F109: 700.27 | G109: 12308 | I109: 1308 | J109: 13538.8 | L109: 1438.8 | M109: 13538 | O109: 1438.8 | P109: 19939 | R109: 949 | S109: 19939 | U109: 949 | V109: 18216 | X109: 867 | Y109: 20924 | AA109: 996 | AB109: 18093 | AD109: 861 | AE109: 19939 | AG109: 949 | AH109: 18093 | AJ109: 861 | AK109: 17231 | AM109: 820 | AN109: {=SUMPRODUCT((D$1:AK$1<>"Margin")*(D$1:AK$1<>"Salary_$600")*D109:AK109)} -> 206466.8 | AO109: {=SUMPRODUCT((D$1:AM$1="Margin")*D109:AM109)} -> 12137.87 | AP109: SOW valid until Apr 30, 2026 | AQ109: 100% | AR109: HPE | AS109: DS70_Secured
A110: HPE Data Foundation | B110: Manmeet | C110: Staffing | D110: 33592 | F110: 2196 | G110: 30856 | I110: 3424.66 | J110: 36328 | L110: 3496.68 | M110: 36784 | O110: 4095.08 | P110: 33858 | R110: 2187 | S110: 33858 | U110: 2187 | V110: 30932 | X110: 1998 | Y110: 35530 | AA110: 2295 | AB110: 30723 | AD110: 1985 | AE110: 33858 | AG110: 2187 | AH110: 30723 | AJ110: 1985 | AK110: 29260 | AM110: 1890 | AN110: {=SUMPRODUCT((D$1:AK$1<>"Margin")*(D$1:AK$1<>"Salary_$600")*D110:AK110)} -> 396302 | AO110: {=SUMPRODUCT((D$1:AM$1="Margin")*D110:AM110)} -> 29926.42 | AP110: SOW valid until Apr 30, 2026 | AQ110: 100% | AR110: HPE | AS110: DS70_Secured
...

Sheet 2026_ClientComments
A1: Group | B1: Client List | C1: Confidence | D1: Comments
A2: DS10_Secured | B2: Automation Anywhere | C2: 100% | D2: Renewal SOW approved for 1. 6-month duration until July 2026 2. Team size reduced from current 10 to 9 resources 3. Monthly billing $30,000 SOW for period Aug - Oct 2026 submitted for approval
A3: DS10_Secured | B3: AIS Solutions | C3: 0% | D3: Opened the account with 1 full time FED for 3 months. Client is not going to renew this account post May 15
A4: DS10_Secured | B4: Aldevron | C4: 100% | D4: Initiated engagement with the client through a small project valued at $1,200. Successfully secured an ongoing maintenance SOW worth $8,150 per month, with a start date of February 2, 2026.
A5: DS10_Secured | B5: CheckPoint | C5: 0% | D5: The client has discontinued our services from April onwards.
A6: DS10_Secured | B6: Churchs-Chicken | C6: 100% | D6: SOW valid until Dec 31, 2027.
A7: DS10_Secured | B7: Databricks | C7: 100% | D7: We have 6 active SOWs with Databricks. 1. The Website maintenance SOW with monthly billing of ~$66,300 is approved until Sep 30, 2026 2. The rest of the SOWs are approved with a total monthly billing of ~$115,000 and approved until April 30, 2026. The SOWs are a. SEO Content Strategist b. SEO Program Management (This position is now being moved to the US. We are working with the client on identifying an appropriate resource. Interviews in progress. c. Planning Project d. Martech Platform Operations e. Program Manager and Marketo
A8: DS10_Secured | B8: Doppel | C8: 25% | D8: Secured a maintenance SOW for $4,200 a month with a start date of Feb 2, 2026. We have been following up with the client on tasks since Feb 1, but we haven't received a response.
A9: DS10_Secured | B9: EGIA | C9: 100% | D9: Open-ended SOW for the last many of years. Growth in 2026 is expected as EGIA wins more RFPs
A10: DS10_Secured | B10: HAL | C10: 100% | D10: 1. We started 2026 with 3 Staff Augmentation SOWs. Two of these SOW (Creative and Marketo) were discontinued from April 2026 and were left with "Digital Web Marketing" SOW, which is approved until Sep 2026 ($36,900 for 6 months) and has high confidence in getting it further renewed. 2. Signed a new SOW for Digital Marketing Operation Specialist $5000/month. Start date May 18 3. Delivered a fixed cost project, "Critical Minerals AI Analysis solution," for $22,000.
A11: DS10_Secured | B11: Hitachi Asia | C11: 75% | D11: The client visited our India office on May 6- 7 to go over the 2026 projects. Client agreed on 4 proposals and the same have been submitted for approval with a total billing value of $93K. Another AI project proposal has been submitted for approval Phase 1 - Pilot: INR 9,95,500 Phase 2 - full rollout: INR 7,53,300 + monthly subscription of $2,500
A12: DS10_Secured | B12: Hitachi Stem | C12: 100% | D12: Open Ended SOW
... A20: DS10_Secured | B20: YetiMyFriend | C20: 100% | D20: Open-ended SOW.
A22: DS10_Secured | B22: AI Forward
A23: DS10_Secured | B23: Bench
A24: DS10_Secured | B24: Bench Deployed
A25: DS10_Secured | B25: MetaSys Payroll Portal-Truist
A26: DS10_Secured | B26: MetaSys Staffing Reports Wendy
A27: DS10_Secured | B27: MetaSys, Marlow Content and Design
A28: DS10_Secured | B28: Ovis Programming + MetaSys Websites
A29: DS10_Secured | B29: Ovis- Creative Support
A30: DS10_Secured | B30: Sales & Marketing (Nvish & MetaSys)
A35: DS30_Projection | B35: HAL | C35: 50% | D35: Proposal submitted in Dec 2025. Client has come back with feedback. Updated proposal will be shared with client in the week of Jan 18.
A36: DS30_Projection | B36: Hitachi Asia | C36: 50% | D36: Client is visit India Office on May 6,7 to discuss projects
A37: DS30_Projection | B37: IDBS | C37: 75% | D37: Signed a Help-Center project for $53,900 with go-live Sep 25, 2026 Working to win additional SOW for Website enhacements
A38: DS30_Projection | B38: NorthWest Storage | C38: 25% | D38: Discussions pushed till Jan 2026
A39: DS30_Projection
A44: DS50_Projection | B44: ADNOC | C44: 25% | D44: Top-of-funnel activities - Working with Ankur Rana
A45: DS50_Projection | B45: Alliance Technical Group | C45: 5% | D45: Raghu is working with Romeen to move this
A46: DS50_Projection | B46: Anurag | C46: 75%
A47: DS50_Projection | B47: Fannie Mae | C47: 5% | D47: Fannie Mae RFP being developed in collaboration with OSG. On hold for now
A48: DS50_Projection | B48: GIZ - I | C48: 75% | D48: RFP response submitted - Working with Ankur Rana
A49: DS50_Projection | B49: GIZ - II | C49: 75% | D49: RFP response submitted - Working with Ankur Rana
A50: DS50_Projection | B50: IHG | C50: 25% | D50: Request sent to Raj Verma to follow up with Vivien. In addition to this met with Ketan through Ankur Rana
A51: DS50_Projection | B51: Inatech | C51: 25% | D51: Top-of-funnel activities. Ram working with Raghu to discuss the options
A52: DS50_Projection | B52: Miller Knoll | C52: 50% | D52: POC approach dropped. Raghu and Raj met the Millet Knoll at Miami and will make it moving
A53: DS50_Projection | B53: OSG - Castrol | C53: 50%
A54: DS50_Projection | B54: OSG - Dewsy | C54: 25%
A55: DS50_Projection | B55: OSG - DHA | C55: 25%
A56: DS50_Projection | B56: OSG - DHA TB | C56: 25%
A57: DS50_Projection | B57: OSG - Misc | C57: 25% | D57: Church and Dwight, BP/Castrol, Lloyds Banking Group, Medline, Tandem Diabetes, Boston Scientific, BD (Becton Dickinson) Breast Surgery, Johnson and Johnson Medical Devices, Kenvue, Abbott Diagnostics
A58: DS50_Projection | B58: Reasonant Clinical | C58: 50%
A59: DS50_Projection | B59: New Logos | C59: 25% | D59: We should also focus on winning new clients to create more business opportunities
B64: NetApp | C64: 25%
B65: Moveworks | C65: 25%
A70: DS70_Secured | B70: HPE | C70: 100% | D70: SOW renewed for Q1, Q2, and selective for a 12-month period.
A71: DS80_Secured | B71: Marvell India
A72: DS85_Secured | B72: AZU Solutions | C72: 100% | D72: The respective SOWs are valid for 6-month and 9-month durations
A73: DS85_Secured | B73: Databricks | C73: 100% | D73: SOW valid until Aug 31, 2026

Sheet Sales by Customer- 2025
A1: NVISH Solutions Inc.
A2: Sales by Customer Summary
A3: Green: Legacy account Green background with approved SOW Blue not yet approved but confidence high
A4: Blue: Legacy Account with Growth,
A5: Yellow: New Logo with jobs, Orange: Pipeline
A7: Name | B7: POC | C7: LOB | D7: Jan_Act | E7: Jan_Sal | F7: Jan_Mar | G7: Feb_Act | H7: Feb_Sal | I7: Feb_Mar | J7: Mar_Act | K7: Mar_Sal | L7: Mar_Mar | M7: Apr_Act | N7: Apr_Sal | O7: Apr_Mar | P7: May_Act | Q7: May_Sal | R7: May_Mar | S7: Jun_Act | T7: Jun_Sal | U7: Jun_Mar | V7: Jul_Act | W7: Jul_Sal | X7: Jul_Mar | Y7: Aug_Act | Z7: Aug_Sal | AA7: Aug_Mar | AB7: Sep_Act | AC7: Sep_Sal | AD7: Sep_Mar | AE7: Oct_Act | AF7: Oct_Sal | AG7: Oct_Mar | AH7: Nov_Act | AI7: Nov_Sal | AJ7: Nov_Mar | AK7: Dec_Act | AL7: Dec_Sal | AM7: Dec_Mar | AN7: Total_Rev | AO7: Total_NM | AP7: Comments | AQ7: Renewal Confidence | AR7: Project Id | AS7: Group | AT7: Notes
D8: Actual | E8: Salary_$600 | F8: Margin | G8: Actual | H8: Salary_$600 | I8: Margin | J8: Actual | K8: Salary_$600 | L8: Margin | M8: Actual | N8: Salary_$600 | O8: Margin | P8: Actuals | Q8: Salary_$600 | R8: Margin | S8: Actual | T8: Salary_$600 | U8: Margin | V8: Actual | W8: Salary_$600 | X8: Margin | Y8: Actual | Z8: Salary_$600 | AA8: Margin | AB8: Actual | AC8: Salary_$600 | AD8: Margin | AE8: Actual | AF8: Salary_$600 | AG8: Margin | AH8: Actual | AI8: Salary_$600 | AJ8: Margin | AK8: Actual | AL8: Salary_$600 | AM8: Margin
A9: Name | B9: POC | C9: Service | D9: 45658 | E9: 45658 | F9: 45658 | G9: 45689 | H9: 45689 | I9: 45689 | J9: 45717 | K9: 45741 | L9: 45741 | M9: 45748 | N9: 45772 | O9: 45772 | P9: 45778 | Q9: 45778 | R9: 45802 | S9: 45809 | T9: 45809 | U9: 45809 | V9: 45839 | W9: 45839 | X9: 45839 | Y9: 45870 | Z9: 45870 | AA9: 45870 | AB9: 45901 | AC9: 45901 | AD9: 45901 | AE9: 45931 | AF9: 45931 | AG9: 45931 | AH9: 45962 | AI9: 45962 | AJ9: 45962 | AK9: 45992 | AL9: 45992 | AM9: 45992 | AN9: Total (Revenue) | AO9: Total Margin | AP9: Comments | AQ9: Renewal Confidence | AR9: Group | AS9: Sub-Group
A10: Solutions and Staff Augmentation (Projects) - Track 1 | I10: =G10-H10 -> 0
A11: Bench | B11: Vijay | C11: Non Billable | E11: 13586 | F11: =D11-E11 -> -13586 | H11: 18217 | I11: =G11-H11 -> -18217 | K11: 21649 | L11: =J11-K11 -> -21649 | N11: 25403 | O11: =M11-N11 -> -25403 | Q11: 4610 | R11: =P11-Q11 -> -4610 | T11: 2558 | U11: =S11-T11 -> -2558 | W11: 2558 | X11: =V11-W11 -> -2558 | Z11: 4129 | AA11: =Y11-Z11 -> -4129 | AC11: 3914 | AD11: =AB11-AC11 -> -3914 | AF11: 6886 | AG11: =AE11-AF11 -> -6886 | AI11: 5753 | AJ11: =AH11-AI11 -> -5753 | AL11: 11533 | AM11: =AK11-AL11 -> -11533 | AN11: {=SUMPRODUCT((D$8:AK$8<>"Margin")*(D$8:AK$8<>"Salary_$600")*D11:AK11)} -> 0 | AO11: {=SUMPRODUCT((D$8:AN$8="Margin")*D11:AN11)} -> -120796
A12: MetaSys Reporting Project Wendy | B12: Vijay | C12: Non Billable | F12: =D12-E12 -> 0 | I12: =G12-H12 -> 0 | L12: =J12-K12 -> 0 | O12: =M12-N12 -> 0 | R12: =P12-Q12 -> 0 | U12: =S12-T12 -> 0 | X12: =V12-W12 -> 0 | AA12: =Y12-Z12 -> 0 | AD12: =AB12-AC12 -> 0 | AG12: =AE12-AF12 -> 0 | AI12: 3295 | AJ12: =AH12-AI12 -> -3295 | AL12: 3295 | AM12: =AK12-AL12 -> -3295 | AN12: {=SUMPRODUCT((D$8:AK$8<>"Margin")*(D$8:AK$8<>"Salary_$600")*D12:AK12)} -> 0 | AO12: {=SUMPRODUCT((D$8:AN$8="Margin")*D12:AN12)} -> -6590
A13: Sales & Marketing (Nvish & MetaSys) | B13: Vijay | C13: Non Billable | E13: 3628 | F13: =D13-E13 -> -3628 | H13: 3628 | I13: =G13-H13 -> -3628 | K13: 6838 | L13: =J13-K13 -> -6838 | N13: 7574 | O13: =M13-N13 -> -7574 | Q13: 7574 | R13: =P13-Q13 -> -7574 | T13: 10186 | U13: =S13-T13 -> -10186 | W13: 10186 | X13: =V13-W13 -> -10186 | Z13: 10186 | AA13: =Y13-Z13 -> -10186 | AC13: 10186 | AD13: =AB13-AC13 -> -10186 | AF13: 10448 | AG13: =AE13-AF13 -> -10448 | AI13: 10630 | AJ13: =AH13-AI13 -> -10630 | AL13: 10630 | AM13: =AK13-AL13 -> -10630 | AN13: {=SUMPRODUCT((D$8:AK$8<>"Margin")*(D$8:AK$8<>"Salary_$600")*D13:AK13)} -> 0 | AO13: {=SUMPRODUCT((D$8:AN$8="Margin")*D13:AN13)} -> -101694
A14: AuditBoard | B14: Neeraj | C14: Staff Aug | D14: 4000 | F14: 817 | G14: 4000 | I14: 817 | J14: 2400 | K14: 1583 | L14: 817 | M14: 0 | P14: 0 | S14: 0 | V14: 0 | Y14: 0 | AB14: 0 | AC14: 0 | AD14: 0 | AE14: 0 | AF14: 0 | AG14: 0 | AH14: 0 | AI14: 0 | AJ14: 0 | AK14: 0 | AL14: 0 | AM14: 0 | AN14: {=SUMPRODUCT((D$8:AK$8<>"Margin")*(D$8:AK$8<>"Salary_$600")*D14:AK14)} -> 10400 | AO14: {=SUMPRODUCT((D$8:AN$8="Margin")*D14:AN14)} -> 2451 | AP14: Tasks were completed and client has asked to terminate contract. | AR14: AuditBoard | AS14: DS10_Secured
A15: Automation Anywhere Web Dev | B15: Neeraj | C15: Staff Aug | D15: 36580 | F15: 4772 | G15: 32922 | I15: 4772 | J15: 32922 | K15: 28150 | L15: 4772 | M15: 32922 | N15: 29735 | O15: 3187 | P15: 32922 | Q15: 29735 | R15: 3187 | S15: 32922 | T15: 29735 | U15: 3187 | V15: 32922 | W15: 29735 | X15: 3187 | Y15: 32922 | Z15: 29735 | AA15: 3187 | AB15: 32922 | AC15: 29735 | AD15: 3187 | AE15: 32922 | AF15: 29735 | AG15: 3187 | AH15: 32922 | AI15: 29735 | AJ15: 3187 | AK15: 32922 | AL15: 29735 | AM15: 3187 | AN15: {=SUMPRODUCT((D$8:AK$8<>"Margin")*(D$8:AK$8<>"Salary_$600")*D15:AK15)} -> 398722 | AO15: {=SUMPRODUCT((D$8:AN$8="Margin")*D15:AN15)} -> 42999 | AP15: SOW valid until Jan 2026. | AQ15: 100% | AR15: Automation Anywhere | AS15: DS10_Secured
A16: Automation Anywhere University Creative | B16: Neeraj | C16: Staff Aug | D16: 3850 | E16: 2850 | F16: =D16-E16 -> 1000 | G16: 9240 | I16: 9240 | J16: 0 | K16: 0 | L16: 0 | M16: 0 | P16: 0 | S16: 0 | V16: 0 | Y16: 0 | AB16: 0 | AC16: 0 | AE16: 0 | AF16: 0 | AG16: 0 | AH16: 0 | AI16: 0 | AJ16: 0 | AK16: 0 | AL16: 0 | AM16: 0 | AN16: {=SUMPRODUCT((D$8:AK$8<>"Margin")*(D$8:AK$8<>"Salary_$600")*D16:AK16)} -> 13090 | AO16: {=SUMPRODUCT((D$8:AN$8="Margin")*D16:AN16)} -> 10240 | AP16: SOW was valid until Jan 31, 2025. | AR16: Automation Anywhere | AS16: DS10_Secured
A17: CheckPoint Desktop publishing of translated assets | B17: Neeraj | C17: Staff Aug | D17: 5000 | F17: 1999 | G17: 0 | I17: 1999 | J17: 4995 | K17: 1555 | L17: 1999 | M17: 0 | N17: 849 | O17: 1150 | P17: 0 | Q17: 849 | R17: 1150 | S17: 5000 | T17: 849 | U17: 1150 | V17: 0 | W17: 849 | X17: 1150 | Y17: 4995 | Z17: 849 | AA17: 1150 | AB17: 0 | AC17: 849 | AD17: 1150 | AE17: 0 | AF17: 849 | AG17: 1150 | AH17: 5000 | AI17: 849 | AJ17: 1150 | AK17: 0 | AL17: 849 | AM17: 1150 | AN17: {=SUMPRODUCT((D$8:AK$8<>"Margin")*(D$8:AK$8<>"Salary_$600")*D17:AK17)} -> 24990 | AO17: {=SUMPRODUCT((D$8:AN$8="Margin")*D17:AN17)} -> 16347 | AP17: SOW valid Feb 2026 | AQ17: 100% | AR17: CheckPoint | AS17: DS10_Secured
A18: Chooch | B18: Neeraj | C18: Staff Aug | D18: 3500 | F18: 1682 | G18: 3500 | I18: 1682 | J18: 3500 | K18: 1818 | L18: 1682 | M18: 3500 | N18: 1818 | O18: 1682 | P18: 3500 | Q18: 1818 | R18: 1682 | S18: 3500 | T18: 1818 | U18: 1682 | V18: 3500 | W18: 1818 | X18: 1682 | Y18: 2000 | Z18: 1818 | AA18: 1682 | AN18: {=SUMPRODUCT((D$8:AK$8<>"Margin")*(D$8:AK$8<>"Salary_$600")*D18:AK18)} -> 26500 | AO18: {=SUMPRODUCT((D$8:AN$8="Margin")*D18:AN18)} -> 13456 | AP18: SOW concluded in Aug 2025. | AR18: Chooch | AS18: DS10_Secured
A19: Church's Chicken & IT Support | B19: Neeraj | C19: Project | D19: 0 | F19: 444 | G19: 0 | I19: 444 | J19: 7500 | K19: 201 | L19: 444 | M19: 0 | N19: 201 | O19: 404 | P19: 0 | Q19: 201 | R19: 404 | S19: 0 | T19: 201 | U19: 404 | V19: 1500 | W19: =201+238 -> 439 | X19: =404+(1500-238) -> 1666 | Y19: 0 | Z19: 0 | AA19: 0 | AB19: 0 | AC19: 201 | AD19: 404 | AE19: 0 | AF19: 201 | AG19: 404 | AH19: 0 | AI19: 201 | AJ19: 404 | AK19: 0 | AL19: 201 | AM19: 404 | AN19: {=SUMPRODUCT((D$8:AK$8<>"Margin")*(D$8:AK$8<>"Salary_$600")*D19:AK19)} -> 9000 | AO19: {=SUMPRODUCT((D$8:AN$8="Margin")*D19:AN19)} -> 5826 | AP19: SOW valid until Dec 31, 2027 | AQ19: 100% | AR19: Churchs-Chicken | AS19: DS10_Secured
A20: Databricks Ongoing Support | B20: Neeraj | C20: Staff Aug | D20: 0 | F20: 30990 | G20: 64150 | I20: 30990 | J20: 64150 | K20: 33160 | L20: 30990 | M20: 64150 | N20: 34406 | O20: 29744 | P20: 64150 | Q20: 34406 | R20: 29744 | S20: 64150 | T20: 34406 | U20: 29744 | V20: 64150 | W20: 34406 | X20: 29744 | Y20: 64150 | Z20: 34406 | AA20: 29744 | AB20: 64150 | AC20: 34406 | AD20: 29744 | AE20: 57475 | AF20: 30406 | AG20: =AE20-AF20 -> 27069 | AH20: 57475 | AI20: 30406 | AJ20: =AH20-AI20 -> 27069 | AK20: 57475 | AL20: 30406 | AM20: =AK20-AL20 -> 27069 | AN20: {=SUMPRODUCT((D$8:AK$8<>"Margin")*(D$8:AK$8<>"Salary_$600")*D20:AK20)} -> 685625 | AO20: {=SUMPRODUCT((D$8:AN$8="Margin")*D20:AN20)} -> 352641 | AP20: In the renewed SOW, the client reduced Web Producers by 3 and added a Sr. QA. This will result in a monthly billing decrease of $6,675. | AQ20: 100% | AR20: Databricks | AS20: DS10_Secured
A21: Databricks Planning Project | B21: Neeraj | C21: Staff Aug | D21: 5000 | F21: 1634 | G21: 5000 | I21: 1634 | J21: 5000 | K21: 3366 | L21: 1634 | M21: 5000 | N21: 3494 | O21: 1506 | P21: 5000 | Q21: 3494 | R21: 1506 | S21: 5000 | T21: 3494 | U21: 1506 | V21: 5000 | W21: 3494 | X21: 1506 | Y21: 5000 | Z21: 3494 | AA21: 1506 | AB21: 5000 | AC21: 3494 | AD21: 1506 | AE21: 5000 | AF21: 3494 | AG21: 1506 | AH21: 5000 | AI21: 3494 | AJ21: 1506 | AK21: 5000 | AL21: 3494 | AM21: 1506 | AN21: {=SUMPRODUCT((D$8:AK$8<>"Margin")*(D$8:AK$8<>"Salary_$600")*D21:AK21)} -> 60000 | AO21: {=SUMPRODUCT((D$8:AN$8="Margin")*D21:AN21)} -> 18456 | AP21: SOW valid until April 30, 2026 | AQ21: 100% | AR21: Databricks | AS21: DS10_Secured
A22: Databricks Program Manager and Marketo | B22: Neeraj | C22: Staff Aug | D22: 80350 | F22: 32238 | G22: 79225 | I22: 32238 | J22: 87457 | K22: 55219 | L22: 32238 | M22: 91957 | N22: 56148 | O22: 28702 | P22: 75850 | Q22: 51289 | R22: 24561 | S22: 75850 | T22: 51289 | U22: 24561 | V22: 75850 | W22: 51289 | X22: 24561 | Y22: 62279 | Z22: 51289 | AA22: 24561 | AB22: 60009 | AC22: =48999-12133/2-2096+4000/2+4000/4+10000/2 -> 48836.5 | AD22: =AB22-AC22 -> 11172.5 | AE22: 76779 | AF22: =48999 + 10000+4000+4100-2096-2363-3417 -> 59223 | AG22: =AE22-AF22 -> 17556 | AH22: 81850 | AI22: =48999 + 10000+4000+4100-2096-2363-3417 -> 59223 | AJ22: =AH22-AI22 -> 22627 | AK22: 81850 | AL22: =48999 + 10000+4000+4100-2096-2363-3417 -> 59223 | AM22: =AK22-AL22 -> 22627 | AN22: {=SUMPRODUCT((D$8:AK$8<>"Margin")*(D$8:AK$8<>"Salary_$600")*D22:AK22)} -> 929306 | AO22: {=SUMPRODUCT((D$8:AN$8="Margin")*D22:AN22)} -> 297642.5 | AP22: SOW valid until April 30, 2026. From August 2025, the client removed the Analytics resource, impacting monthly billing by $4,500. Additionally, in Aug and Sep, one of our US employees resigned, and a new resource was onboarded starting Sep 22, further impacting billing for those months. Impact Aug: $13,571 Impact Sep: $15841 Impact Oct: $1,522 | AQ22: 100% | AR22: Databricks | AS22: DS10_Secured
A23: Databricks SEO Project Management | B23: Neeraj | C23: Staff Aug | D23: 4500 | E23: =0.92*3713 -> 3415.96 | F23: =D23-E23 -> 1084.04 | G23: 4500 | H23: =0.92*3713 -> 3415.96 | I23: =G23-H23 -> 1084.04 | J23: 4500 | K23: =0.92*3713 -> 3415.96 | L23: =J23-K23 -> 1084.04 | M23: 4500 | N23: 3713 | O23: =M23-N23 -> 787 | P23: 4500 | Q23: 3713 | R23: =P23-Q23 -> 787 | S23: 4500 | T23: 3713 | U23: =S23-T23 -> 787 | V23: 4500 | W23: 3713 | X23: =V23-W23 -> 787 | Y23: 4500 | Z23: 3713 | AA23: =Y23-Z23 -> 787 | AB23: 4500 | AC23: 3713 | AD23: =AB23-AC23 -> 787 | AE23: 4500 | AF23: 3713 | AG23: =AE23-AF23 -> 787 | AH23: 4500 | AI23: 3713 | AJ23: =AH23-AI23 -> 787 | AK23: 4500 | AL23: 3713 | AM23: =AK23-AL23 -> 787 | AN23: {=SUMPRODUCT((D$8:AK$8<>"Margin")*(D$8:AK$8<>"Salary_$600")*D23:AK23)} -> 54000 | AO23: {=SUMPRODUCT((D$8:AN$8="Margin")*D23:AN23)} -> 10335.12 | AP23: SOW valid until April 30, 2026 | AQ23: 100% | AR23: Databricks | AS23: DS10_Secured
A24: Databricks Martech Platform Operations Administrator | B24: Neeraj | C24: Staff Aug | D24: 4500 | F24: 1666 | G24: 4500 | I24: 1666 | J24: 4500 | K24: 2834 | L24: 1666 | M24: 4500 | N24: 2834 | O24: =M24-N24 -> 1666 | P24: =3*4500 -> 13500 | Q24: 7693 | R24: 5807 | S24: =3*4500 -> 13500 | T24: 7693 | U24: 5807 | V24: =3*4500 -> 13500 | W24: 7693 | X24: 5807 | Y24: =3*4500 -> 13500 | Z24: 7693 | AA24: 5807 | AB24: =3*4500 -> 13500 | AC24: 7693 | AD24: 5807 | AE24: =3*4500 -> 13500 | AF24: 7693 | AG24: 5807 | AH24: =3*4500 -> 13500 | AI24: 7693 | AJ24: 5807 | AK24: =3*4500 -> 13500 | AL24: 7693 | AM24: 5807 | AN24: {=SUMPRODUCT((D$8:AK$8<>"Margin")*(D$8:AK$8<>"Salary_$600")*D24:AK24)} -> 126000 | AO24: {=SUMPRODUCT((D$8:AN$8="Margin")*D24:AN24)} -> 53120 | AP24: SOW valid until April 30, 2026 | AQ24: 100% | AR24: Databricks | AS24: DS10_Secured
A25: EGIA Development Support | B25: Neeraj | C25: Staff Aug | D25: 39000 | F25: 23090 | G25: 39000 | I25: 23090 | J25: 39000 | K25: 15910 | L25: 23090 | M25: 39000 | N25: 16978 | O25: 22022 | P25: 39000 | Q25: 16978 | R25: 22022 | S25: 39000 | T25: 16978 | U25: 22022 | V25: 39000 | W25: 16978 | X25: 22022 | Y25: 39000 | Z25: 16978 | AA25: 22022 | AB25: 39000 | AC25: 16978 | AD25: 22022 | AE25: 39000 | AF25: 16978 | AG25: 22022 | AH25: 39000 | AI25: 16978 | AJ25: 22022 | AK25: 39000 | AL25: 16978 | AM25: 22022 | AN25: {=SUMPRODUCT((D$8:AK$8<>"Margin")*(D$8:AK$8<>"Salary_$600")*D25:AK25)} -> 468000 | AO25: {=SUMPRODUCT((D$8:AN$8="Margin")*D25:AN25)} -> 267468 | AP25: Open Ended SOW | AQ25: 100% | AR25: EGIA | AS25: DS10_Secured
A26: HAL Creative Support | B26: Neeraj | C26: Staff Aug | D26: 0 | F26: 1482 | G26: 0 | I26: 1482 | J26: 12150 | K26: 2543 | L26: 1482 | M26: 13000 | N26: 2543 | O26: 1767 | P26: 0 | Q26: 2543 | R26: 1767 | S26: 0 | T26: 2543 | U26: 1767 | V26: 0 | W26: 2543 | X26: 1767 | Y26: 0 | Z26: 2543 | AA26: 1767 | AB26: 12860 | AC26: 2543 | AD26: 1767 | AE26: 13000 | AF26: 2543 | AG26: 1767 | AH26: 0 | AI26: 2543 | AJ26: 1767 | AK26: 0 | AL26: 2543 | AM26: 1767 | AN26: {=SUMPRODUCT((D$8:AK$8<>"Margin")*(D$8:AK$8<>"Salary_$600")*D26:AK26)} -> 51010 | AO26: {=SUMPRODUCT((D$8:AN$8="Margin")*D26:AN26)} -> 20349 | AP26: SOW valid until Mar 31, 2026. | AQ26: 100% | AR26: HAL | AS26: DS10_Secured
A27: HAL Social Media community | B27: Neeraj | C27: Project | D27: 0 | E27: 7737 | F27: 5614 | G27: 36625 | H27: 7737 | I27: 5614 | J27: 0 | K27: 0 | L27: 0 | M27: 0 | P27: 0 | S27: 0 | V27: 0 | Y27: 0 | AB27: 0 | AC27: 0 | AD27: 0 | AE27: 0 | AF27: 0 | AG27: 0 | AH27: 0 | AI27: 0 | AJ27: 0 | AK27: 0 | AL27: 0 | AM27: 0 | AN27: {=SUMPRODUCT((D$8:AK$8<>"Margin")*(D$8:AK$8<>"Salary_$600")*D27:AK27)} -> 36625 | AO27: {=SUMPRODUCT((D$8:AN$8="Margin")*D27:AN27)} -> 11228 | AP27: Social Media delivery is now managed by Hitachi Japan. Our SOW has not been renewed. | AR27: HAL | AS27: DS10_Secured
A28: HAL Digital Web Marketing | B28: Neeraj | C28: Staff Aug | D28: 0 | F28: 1624 | G28: 0 | I28: 1624 | J28: 17500 | K28: 4126 | L28: 1624 | M28: 18000 | N28: 4478 | O28: 1672 | P28: 0 | Q28: 4478 | R28: 1672 | S28: 0 | T28: 4478 | U28: 1672 | V28: 0 | W28: 4478 | X28: 1672 | Y28: 0 | Z28: 4478 | AA28: 1672 | AB28: 18900 | AC28: 4478 | AD28: 1672 | AE28: 18000 | AF28: 4478 | AG28: 1672 | AH28: 0 | AI28: 4478 | AJ28: 1672 | AK28: 0 | AL28: 4478 | AM28: 1672 | AN28: {=SUMPRODUCT((D$8:AK$8<>"Margin")*(D$8:AK$8<>"Salary_$600")*D28:AK28)} -> 72400 | AO28: {=SUMPRODUCT((D$8:AN$8="Margin")*D28:AN28)} -> 19920 | AP28: SOW valid until Mar 31, 2026. | AQ28: 100% | AR28: HAL | AS28: DS10_Secured
A29: HAL Marketo Support | B29: Neeraj | C29: Staff Aug | D29: 0 | F29: 2517 | G29: 0 | I29: 2517 | J29: 15360 | K29: 2543 | L29: 2517 | M29: 16000 | N29: 2543 | O29: 2872 | P29: 0 | Q29: 2543 | R29: 2872 | S29: 0 | T29: 2543 | U29: 2872 | V29: 0 | W29: 2543 | X29: 2872 | Y29: 0 | Z29: 2543 | AA29: 2872 | AB29: 16490 | AC29: 2543 | AD29: 2872 | AE29: 16000 | AF29: 2543 | AG29: 2872 | AH29: 0 | AI29: 2543 | AJ29: 2872 | AK29: 0 | AL29: 2543 | AM29: 2872 | AN29: {=SUMPRODUCT((D$8:AK$8<>"Margin")*(D$8:AK$8<>"Salary_$600")*D29:AK29)} -> 63850 | AO29: {=SUMPRODUCT((D$8:AN$8="Margin")*D29:AN29)} -> 33399 | AP29: SOW valid until Mar 31, 2026. | AQ29: 100% | AR29: HAL | AS29: DS10_Secured
A30: HAL AI Principle Purpose-Built Video (Feb 10, 2025 – Mar 10, 2025) | B30: Neeraj | C30: Project | D30: 0 | F30: 8000 | G30: 0 | I30: 8000 | J30: 20000 | K30: 12000 | L30: 8000 | M30: 0 | P30: 0 | S30: 0 | V30: 0 | Y30: 0 | AB30: 0 | AC30: 0 | AD30: 0 | AE30: 0 | AF30: 0 | AG30: 0 | AH30: 0 | AI30: 0 | AJ30: 0 | AK30: 0 | AL30: 0 | AM30: 0 | AN30: {=SUMPRODUCT((D$8:AK$8<>"Margin")*(D$8:AK$8<>"Salary_$600")*D30:AK30)} -> 20000 | AO30: {=SUMPRODUCT((D$8:AN$8="Margin")*D30:AN30)} -> 24000 | AP30: One-time SOW. Delivered and billed. | AR30: HAL | AS30: DS10_Secured
A31: Hitachi Astemo Enhancements 2025 | B31: Neeraj | C31: Project | D31: 0 | F31: 0 | G31: 0 | I31: 0 | J31: 0 | K31: 0 | L31: 0 | M31: 4000 | N31: 1960 | O31: 874 | P31: 0 | Q31: 1960 | R31: 874 | S31: 4500 | T31: 1960 | U31: 874 | V31: 0 | W31: 0 | X31: 0 | Y31: 0 | Z31: 0 | AA31: 0 | AB31: 0 | AC31: 0 | AD31: 0 | AE31: 0 | AF31: 0 | AG31: 0 | AH31: 0 | AI31: 0 | AJ31: 0 | AK31: 0 | AL31: 0 | AM31: 0 | AN31: {=SUMPRODUCT((D$8:AK$8<>"Margin")*(D$8:AK$8<>"Salary_$600")*D31:AK31)} -> 8500 | AO31: {=SUMPRODUCT((D$8:AN$8="Margin")*D31:AN31)} -> 2622 | AP31: One-time SOW. Delivered and billed. | AR31: Hitachi Astemo | AS31: DS10_Secured
A32: Hitachi Asia Ltd | B32: Neeraj | C32: Project | D32: 0 | F32: 5352 | G32: 0 | I32: 5352 | J32: 116474 | K32: 11843 | L32: 5352 | M32: 0 | N32: 14226 | O32: -2845 | P32: 0 | Q32: 11504 | R32: -123 | S32: 0 | T32: 11504 | U32: -123 | V32: 0 | W32: 11504 | X32: -123 | Y32: 0 | Z32: 11504 | AA32: -123 | AB32: 37856 | AC32: 11504 | AD32: -123 | AE32: 0 | AH32: 0 | AK32: 0 | AN32: {=SUMPRODUCT((D$8:AK$8<>"Margin")*(D$8:AK$8<>"Salary_$600")*D32:AK32)} -> 154330 | AO32: {=SUMPRODUCT((D$8:AN$8="Margin")*D32:AN32)} -> 12596 | AP32: All projected Invoiced until Oct 31 added to Monthly Actual | AQ32: 100% | AR32: Hitachi Asia | AS32: DS10_Secured
A33: Hitachi Elevator Asia Pte Ltd. | B33: Neeraj | C33: Project | D33: 0 | F33: 468 | G33: 0 | I33: 468 | J33: 468 | K33: 0 | L33: 468 | M33: 0 | P33: 0 | S33: 0 | V33: 0 | Y33: 0 | AB33: 0 | AC33: 0 | AD33: 0 | AE33: 0 | AF33: 0 | AG33: 0 | AH33: 0 | AI33: 0 | AJ33: 0 | AK33: 0 | AL33: 0 | AM33: 0 | AN33: {=SUMPRODUCT((D$8:AK$8<>"Margin")*(D$8:AK$8<>"Salary_$600")*D33:AK33)} -> 468 | AO33: {=SUMPRODUCT((D$8:AN$8="Margin")*D33:AN33)} -> 1404 | AP33: One-time SOW. Delivered and billed. | AR33: Hitachi Elevator | AS33: DS10_Secured
A34: Hitachi Stem - Development Support | B34: Neeraj | C34: Staff Aug | D34: 4000 | F34: 1244 | G34: 4000 | I34: 1244 | J34: 4000 | K34: 2756 | L34: 1244 | M34: 4000 | N34: 3015 | O34: 985 | P34: 4000 | Q34: 3015 | R34: 985 | S34: 4000 | T34: 3015 | U34: 985 | V34: 4000 | W34: 3015 | X34: 985 | Y34: 4000 | Z34: 3015 | AA34: 985 | AB34: 4000 | AC34: 3015 | AD34: 985 | AE34: 4000 | AF34: 3015 | AG34: 985 | AH34: 4000 | AI34: 3015 | AJ34: 985 | AK34: 5250 | AL34: 3015 | AM34: 985 | AN34: {=SUMPRODUCT((D$8:AK$8<>"Margin")*(D$8:AK$8<>"Salary_$600")*D34:AK34)} -> 49250 | AO34: {=SUMPRODUCT((D$8:AN$8="Margin")*D34:AN34)} -> 12597 | AP34: Open Ended SOW | AQ34: 100% | AR34: Hitachi Stem | AS34: DS10_Secured
A35: Hitachi America Ltd - Migration RFP | B35: Neeraj | C35: Project | D35: 0 | F35: 0 | G35: 0 | I35: 0 | J35: 0 | K35: 0 | L35: 0 | M35: 0 | N35: 0 | O35: 0 | P35: 0 | Q35: 8634 | R35: 12794 | S35: 0 | T35: 8634 | U35: 12794 | V35: 45000 | W35: 8634 | X35: 12794 | Y35: 0 | Z35: 8634 | AA35: 12794 | AB35: 50000 | AC35: 8634 | AD35: 12794 | AE35: 30000 | AF35: 8634 | AG35: 12794 | AH35: 0 | AI35: 8634 | AJ35: 12794 | AK35: 25000 | AL35: 8634 | AM35: 12794 | AN35: {=SUMPRODUCT((D$8:AK$8<>"Margin")*(D$8:AK$8<>"Salary_$600")*D35:AK35)} -> 150000 | AO35: {=SUMPRODUCT((D$8:AN$8="Margin")*D35:AN35)} -> 102352 | AP35: One-time SOW. Delivery to complete end Nov 2025 | AR35: HAL | AS35: DS10_Secured
A36: Hitachi India Ltd - Migration RFP | B36: Neeraj | C36: Project | D36: 0 | F36: 0 | G36: 0 | I36: 0 | J36: 0 | K36: 0 | L36: 0 | M36: 0 | N36: 0 | O36: 0 | P36: 0 | Q36: 8332 | R36: 14897 | S36: 0 | T36: 8332 | U36: 14897 | V36: 0 | W36: 8332 | X36: 14897 | Y36: 0 | Z36: 8332 | AA36: 14897 | AB36: 0 | AC36: 8332 | AD36: 14897 | AE36: =107792*0.9 -> 97012.8 | AF36: 8332 | AG36: 14897 | AH36: 0 | AI36: 0 | AJ36: 0 | AK36: 0 | AL36: 0 | AM36: 0 | AN36: {=SUMPRODUCT((D$8:AK$8<>"Margin")*(D$8:AK$8<>"Salary_$600")*D36:AK36)} -> 97012.8 | AO36: {=SUMPRODUCT((D$8:AN$8="Margin")*D36:AN36)} -> 89382 | AP36: One-time SOW. Delivered and billed. | AR36: Hitachi Asia | AS36: DS10_Secured
A37: Hitachi Asia and Oceania - Migration RFP | B37: Neeraj | C37: Project | D37: 0 | G37: 0 | J37: 0 | K37: 0 | L37: 0 | M37: 0 | N37: 0 | O37: 0 | P37: 0 | Q37: 0 | R37: 0 | S37: 0 | T37: 0 | V37: 0 | Y37: 0 | Z37: 8422 | AA37: 19156 | AB37: 0 | AC37: 8422 | AD37: 19156 | AE37: 0 | AF37: 8422 | AG37: 19156 | AH37: 0 | AI37: 8422 | AJ37: 19156 | AK37: 155360 | AL37: 8422 | AM37: 19156 | AN37: {=SUMPRODUCT((D$8:AK$8<>"Margin")*(D$8:AK$8<>"Salary_$600")*D37:AK37)} -> 155360 | AO37: {=SUMPRODUCT((D$8:AN$8="Margin")*D37:AN37)} -> 95780 | AP37: One-time SOW. Delivery to complete end Nov 2025 | AR37: Hitachi Asia | AS37: DS10_Secured
A38: Hitachi Bystate Enhancement | B38: Neeraj | C38: Project | D38: 0 | F38: 0 | G38: 0 | I38: 0 | J38: 0 | K38: 0 | L38: 0 | M38: 0 | N38: 0 | O38: 0 | P38: 0 | Q38: 3028 | R38: 1172 | S38: 8400 | T38: 3028 | U38: 1172 | V38: 0 | W38: 0 | X38: 0 | Y38: 0 | Z38: 0 | AA38: 0 | AB38: 0 | AC38: 0 | AD38: 0 | AE38: 0 | AF38: 0 | AG38: 0 | AH38: 0 | AI38: 0 | AJ38: 0 | AK38: 0 | AL38: 0 | AM38: 0 | AN38: {=SUMPRODUCT((D$8:AK$8<>"Margin")*(D$8:AK$8<>"Salary_$600")*D38:AK38)} -> 8400 | AO38: {=SUMPRODUCT((D$8:AN$8="Margin")*D38:AN38)} -> 2344 | AP38: One-time SOW. Delivered and billed. | AR38: Hitachi Bystate | AS38: DS10_Secured
A39: HPE-SOW- Data CDP- Akhila Aiyer | B39: Neeraj | C39: Staff Aug | D39: =4*35*'Working Days'!$C$2 -> 24640 | E39: 13375 | F39: =D39-E39 -> 11265 | G39: 0 | I39: 0 | J39: 0 | K39: 0 | L39: 0 | M39: 0 | P39: 0 | S39: 0 | V39: 0 | Y39: 0 | AB39: 0 | AC39: 0 | AD39: 0 | AE39: 0 | AF39: 0 | AG39: 0 | AH39: 0 | AI39: 0 | AJ39: 0 | AK39: 0 | AL39: 0 | AM39: 0 | AN39: {=SUMPRODUCT((D$8:AK$8<>"Margin")*(D$8:AK$8<>"Salary_$600")*D39:AK39)} -> 24640 | AO39: {=SUMPRODUCT((D$8:AN$8="Margin")*D39:AN39)} -> 11265 | AP39: SOW has been merged with “HPE-SOW – Data Foundations – Shashidhar Iddamsetty.” | AR39: HPE | AS39: DS10_Secured
A40: HPE SEO PM HPE Store Hament Dudeja | B40: Neeraj | C40: Staff Aug | D40: 4699 | E40: 0 | F40: 0 | G40: 0 | H40: 0 | I40: 0 | J40: 0 | K40: 0 | L40: 0 | M40: 4699 | N40: 0 | O40: 0 | P40: 0 | Q40: 0 | R40: 0 | S40: 0 | T40: 0 | U40: 0 | V40: 4699 | W40: 0 | X40: 0 | Y40: 0 | Z40: 0 | AA40: 0 | AB40: 0 | AC40: 0 | AD40: 0 | AE40: 4698 | AF40: 0 | AG40: 0 | AH40: 0 | AI40: 0 | AJ40: 0 | AK40: 0 | AL40: 0 | AM40: 0 | AN40: {=SUMPRODUCT((D$8:AK$8<>"Margin")*(D$8:AK$8<>"Salary_$600")*D40:AK40)} -> 18795 | AO40: {=SUMPRODUCT((D$8:AN$8="Margin")*D40:AN40)} -> 0 | AP40: SOW valid until Oct 31, 2026 | AQ40: 100% | AR40: HPE | AS40: DS10_Secured | AT40: Ajay Mehra
A41: HPE Marketing Strategy & Operations for the APJ Region | B41: Neeraj | C41: Staff Aug | D41: 5600 | F41: 361 | G41: 5320 | I41: 361 | J41: 5040 | K41: 4679 | L41: =J41-K41 -> 361 | M41: =1*35*'Working Days'!$C$5 -> 6160 | N41: 4679 | O41: =M41-N41 -> 1481 | P41: 5880 | Q41: 4679 | R41: =P41-Q41 -> 1201 | S41: =1*35*'Working Days'!$C$7 -> 5880 | T41: 4679 | U41: =S41-T41 -> 1201 | V41: 6160 | W41: 4679 | X41: =V41-W41 -> 1481 | Y41: =1*35*'Working Days'!$C$9 -> 5600 | Z41: 4679 | AA41: =Y41-Z41 -> 921 | AB41: =1*35*'Working Days'!$C$10 -> 6160 | AC41: 4679 | AD41: =AB41-AC41 -> 1481 | AE41: 5320 | AF41: 4679 | AG41: =AE41-AF41 -> 641 | AH41: =1*35*'Working Days'!$C$12 -> 5320 | AI41: 4679 | AJ41: =AH41-AI41 -> 641 | AK41: 4480 | AL41: 4679 | AM41: =AK41-AL41 -> -199 | AN41: {=SUMPRODUCT((D$8:AK$8<>"Margin")*(D$8:AK$8<>"Salary_$600")*D41:AK41)} -> 66920 | AO41: {=SUMPRODUCT((D$8:AN$8="Margin")*D41:AN41)} -> 9932 | AP41: SOW valid until Oct 31, 2026 | AQ41: 100% | AR41: HPE | AS41: DS10_Secured | AT41: Saju Verghese
A42: HPE Data Foundations Shashidhar Iddamsetty | B42: Neeraj | C42: Staff Aug | D42: 5880 | F42: 7144 | G42: 15400 | I42: 7144 | J42: 16520 | K42: 9376 | L42: =J42-K42 -> 7144 | M42: 17640 | N42: 9884 | O42: =M42-N42 -> 7756 | P42: 18200 | Q42: 9884 | R42: =P42-Q42 -> 8316 | S42: 17080 | T42: 9884 | U42: =S42-T42 -> 7196 | V42: =3*35*'Working Days'!$C$8 -> 19320 | W42: 9884 | X42: =V42-W42 -> 9436 | Y42: 15680 | Z42: 9884 | AA42: =Y42-Z42 -> 5796 | AB42: 18200 | AC42: 9884 | AD42: =AB42-AC42 -> 8316 | AE42: =3*35*'Working Days'!$C$11 -> 16800 | AF42: 9884 | AG42: =AE42-AF42 -> 6916 | AH42: =2*35*'Working Days'!$C$12 -> 10640 | AJ42: =AH42*0.4 -> 4256 | AK42: 8680 | AM42: =AK42*0.4 -> 3472 | AN42: {=SUMPRODUCT((D$8:AK$8<>"Margin")*(D$8:AK$8<>"Salary_$600")*D42:AK42)} -> 180040 | AO42: {=SUMPRODUCT((D$8:AN$8="Margin")*D42:AN42)} -> 82892 | AP42: SOW valid until Jan 31, 2026. | AQ42: 100% | AR42: HPE | AS42: DS10_Secured | AT42: Dilpreet, Akanksha, Anmol
A43: HPE Marketing Automation- Christian Voigt | B43: Neeraj | C43: Staff Aug | D43: 11760 | F43: 3601 | G43: 10920 | I43: 3601 | J43: 10920 | K43: 7319 | L43: =J43-K43 -> 3601 | M43: 10640 | N43: 7319 | O43: =M43-N43 -> 3321 | P43: 11200 | Q43: 7319 | R43: =P43-Q43 -> 3881 | S43: 10640 | T43: 7319 | U43: =S43-T43 -> 3321 | V43: 12600 | W43: 7319 | X43: =V43-W43 -> 5281 | Y43: =2*35*'Working Days'!$C$9 -> 11200 | Z43: 7319 | AA43: =Y43-Z43 -> 3881 | AB43: 11480 | AC43: 7319 | AD43: =AB43-AC43 -> 4161 | AE43: 10640 | AF43: 7319 | AG43: =AE43-AF43 -> 3321 | AH43: =2*35*'Working Days'!$C$12 -> 10640 | AI43: 7319 | AJ43: =AH43-AI43 -> 3321 | AK43: 7560 | AL43: 7319 | AM43: =AK43-AL43 -> 241 | AN43: {=SUMPRODUCT((D$8:AK$8<>"Margin")*(D$8:AK$8<>"Salary_$600")*D43:AK43)} -> 130200 | AO43: {=SUMPRODUCT((D$8:AN$8="Margin")*D43:AN43)} -> 41532 | AP43: SOW valid until Jan 31, 2026. | AQ43: 100% | AR43: HPE | AS43: DS10_Secured | AT43: Pradeep, Samuel
A44: HPE SEO PM HPE Store Srihari Gopinath | B44: Neeraj | C44: Staff Aug | X44: =V44-W44 -> 0 | Y44: 5600 | Z44: 2245 | AA44: =Y44-Z44+Y40 -> 3355 | AB44: 6020 | AC44: 2245 | AD44: =AB44-AC44+AB40 -> 3775 | AE44: 0 | AF44: 2245 | AG44: =AE44-AF44+AE40 -> 2453 | AH44: 5600 | AI44: 2245 | AJ44: =AH44-AI44+AH40 -> 3355 | AK44: 4480 | AL44: 2245 | AM44: =AK44-AL44+AK40 -> 2235 | AN44: {=SUMPRODUCT((D$8:AK$8<>"Margin")*(D$8:AK$8<>"Salary_$600")*D44:AK44)} -> 21700 | AO44: {=SUMPRODUCT((D$8:AN$8="Margin")*D44:AN44)} -> 15173 | AP44: SOW valid until Jan 31, 2026 | AR44: HPE | AS44: DS10_Secured
A45: HPE SEO Strategy Towa Ghosh (Projects) | B45: Neeraj | C45: Staff Aug | D45: 14166 | E45: 4800 | F45: =D45-E45 -> 9366 | G45: 14166 | H45: 4800 | I45: =G45-H45 -> 9366 | J45: 14166 | K45: 4800 | L45: =J45-K45 -> 9366 | M45: 14166 | N45: 4800 | O45: =M45-N45 -> 9366 | P45: 14166 | Q45: 4800 | R45: =P45-Q45 -> 9366 | S45: 14166 | T45: 4800 | U45: =S45-T45 -> 9366 | V45: =12500+1666 -> 14166 | W45: 4800 | X45: =V45-W45 -> 9366 | Y45: 14166 | Z45: 4800 | AA45: =Y45-Z45 -> 9366 | AB45: 14166 | AC45: 4800 | AD45: =AB45-AC45 -> 9366 | AE45: 14166 | AF45: 4800 | AG45: =AE45-AF45 -> 9366 | AH45: 14166 | AI45: 4800 | AJ45: =AH45-AI45 -> 9366 | AK45: 14166 | AL45: 4800 | AM45: =AK45-AL45 -> 9366 | AN45: {=SUMPRODUCT((D$8:AK$8<>"Margin")*(D$8:AK$8<>"Salary_$600")*D45:AK45)} -> 169992 | AO45: {=SUMPRODUCT((D$8:AN$8="Margin")*D45:AN45)} -> 112392 | AP45: SOW valid until Jan 31, 2026 | AQ45: 100% | AR45: HPE | AS45: DS10_Secured | AT45: Project + Ajay
A46: HPE SEO Strategy Towa Ghosh (HPE Store) | B46: Neeraj | C46: Staff Aug | D46: 1041 | E46: 2245 | F46: =D46-E46+D40 -> 3495 | G46: 5320 | H46: 2245 | I46: =G46-H46+G40 -> 3075 | J46: 5320 | K46: 2245 | L46: =J46-K46+J40 -> 3075 | M46: 1181 | N46: 2245 | O46: =M46-N46+M40 -> 3635 | P46: 6160 | Q46: 2245 | R46: =P46-Q46+P40 -> 3915 | S46: 5740 | T46: 2245 | U46: =S46-T46+S40 -> 3495 | V46: 1461 | W46: 2245 | X46: =V46-W46+V40 -> 3915 | Y46: 0 | Z46: 0 | AA46: 0 | AB46: 0 | AC46: 0 | AD46: 0 | AE46: 0 | AF46: 0 | AG46: 0 | AH46: 0 | AI46: 0 | AJ46: 0 | AK46: 0 | AL46: 0 | AM46: 0 | AN46: {=SUMPRODUCT((D$8:AK$8<>"Margin")*(D$8:AK$8<>"Salary_$600")*D46:AK46)} -> 26223 | AO46: {=SUMPRODUCT((D$8:AN$8="Margin")*D46:AN46)} -> 24605 | AP46: SOW valid until Jan 31, 2026 | AQ46: 100% | AR46: HPE | AS46: DS10_Secured | AT46: Project + Ajay
A47: HPE Social Media Management Leslie | B47: Neeraj | C47: Staff Aug | D47: =2*35*'Working Days'!$C$2 -> 12320 | F47: 6698 | G47: 10360 | I47: 6698 | J47: 11200 | K47: 4502 | L47: =J47-K47 -> 6698 | M47: 12040 | N47: 4942 | O47: =M47-N47 -> 7098 | P47: =2*35*'Working Days'!$C$6 -> 12320 | Q47: 4942 | R47: =P47-Q47 -> 7378 | S47: 11480 | T47: 4942 | U47: =S47-T47 -> 6538 | V47: 12320 | W47: 4942 | X47: =V47-W47 -> 7378 | Y47: 10920 | Z47: 4942 | AA47: =Y47-Z47 -> 5978 | AB47: =2*35*'Working Days'!$C$10 -> 12320 | AC47: 4942 | AD47: =AB47-AC47 -> 7378 | AE47: =2*35*'Working Days'!$C$11 -> 11200 | AF47: 4942 | AG47: =AE47-AF47 -> 6258 | AH47: 0 | AI47: 0 | AJ47: 0 | AK47: 0 | AL47: 0 | AM47: 0 | AN47: {=SUMPRODUCT((D$8:AK$8<>"Margin")*(D$8:AK$8<>"Salary_$600")*D47:AK47)} -> 116480 | AO47: {=SUMPRODUCT((D$8:AN$8="Margin")*D47:AN47)} -> 68100 | AP47: SOW valid until Apr 30, 2026 | AQ47: 100% | AR47: HPE | AS47: DS10_Secured | AT47: Abhay, Varun
A48: HPE Data & Analytics Zainab Jamal | B48: Neeraj | C48: Staff Aug | D48: =1*35*'Working Days'!$C$2 -> 6160 | F48: 2863 | G48: 5180 | I48: 2863 | J48: 5600 | K48: 2737 | L48: =J48-K48 -> 2863 | M48: 5880 | N48: 2993 | O48: =M48-N48 -> 2887 | P48: =1*35*'Working Days'!$C$6 -> 6160 | Q48: 2993 | R48: =P48-Q48 -> 3167 | S48: 5320 | T48: 2993 | U48: =S48-T48 -> 2327 | V48: =1*35*'Working Days'!$C$8 -> 6440 | W48: 2993 | X48: =V48-W48 -> 3447 | Y48: 5460 | Z48: 2993 | AA48: =Y48-Z48 -> 2467 | AB48: =1*35*'Working Days'!$C$10 -> 6160 | AC48: 2993 | AD48: =AB48-AC48 -> 3167 | AE48: =1*35*'Working Days'!$C$11 -> 5600 | AF48: 2993 | AG48: =AE48-AF48 -> 2607 | AH48: =2*1*35*'Working Days'!$C$12 -> 10640 | AI48: =2993*2 -> 5986 | AJ48: =AH48-AI48 -> 4654 | AK48: 8680 | AL48: =2993*2 -> 5986 | AM48: =AK48-AL48 -> 2694 | AN48: {=SUMPRODUCT((D$8:AK$8<>"Margin")*(D$8:AK$8<>"Salary_$600")*D48:AK48)} -> 77280 | AO48: {=SUMPRODUCT((D$8:AN$8="Margin")*D48:AN48)} -> 36006 | AP48: SOW valid until Apr 30, 2026 | AQ48: 100% | AR48: HPE | AS48: DS10_Secured | AT48: Abhishek Das
A49: HPE- Documents Rebranding Landmark | B49: Neeraj | C49: Project | D49: 0 | E49: 0 | F49: 0 | G49: 0 | H49: 0 | I49: 0 | J49: 0 | K49: 0 | L49: 0 | M49: 0 | N49: 0 | O49: 0 | P49: 0 | Q49: 0 | R49: 0 | S49: 0 | T49: 0 | U49: 0 | V49: 0 | W49: 0 | X49: 0 | Y49: 5600 | Z49: 3369 | AA49: =Y49-Z49 -> 2231 | AB49: 6475 | AC49: 3369 | AD49: =AB49-AC49 -> 3106 | AE49: 10325 | AF49: =3369+2*2400 -> 8169 | AG49: =AE49-AF49 -> 2156 | AH49: =67200/12 -> 5600 | AI49: =0.5*(3369+2*2400) -> 4084.5 | AJ49: =AH49-AI49 -> 1515.5 | AK49: 5145 | AL49: =0.5*(3369+2*2400) -> 4084.5 | AM49: =AK49-AL49 -> 1060.5 | AN49: {=SUMPRODUCT((D$8:AK$8<>"Margin")*(D$8:AK$8<>"Salary_$600")*D49:AK49)} -> 33145 | AO49: {=SUMPRODUCT((D$8:AN$8="Margin")*D49:AN49)} -> 10069 | AP49: SOW valid until Apr 30, 2026 | AQ49: 100% | AR49: HPE | AS49: DS10_Secured | AT49: Yogesh
A50: HPE Documents Rebranding Juniper | B50: Neeraj | C50: Project | D50: 0 | E50: 0 | F50: 0 | G50: 0 | H50: 0 | I50: 0 | J50: 0 | K50: 0 | L50: 0 | M50: 0 | N50: 0 | O50: 0 | P50: 0 | Q50: 0 | R50: 0 | S50: 0 | T50: 0 | U50: 0 | V50: 0 | W50: 0 | X50: 0 | Y50: 0 | Z50: 0 | AA50: 0 | AB50: 0 | AC50: 0 | AD50: 0 | AE50: 0 | AF50: 0 | AG50: 0 | AH50: =100000/12 -> 8333.3333 | AI50: =0.5*(3369+2*2400) -> 4084.5 | AJ50: =AH50-AI50 -> 4248.8333 | AK50: 7070 | AL50: =0.5*(3369+2*2400) -> 4084.5 | AM50: =AK50-AL50 -> 2985.5 | AN50: {=SUMPRODUCT((D$8:AK$8<>"Margin")*(D$8:AK$8<>"Salary_$600")*D50:AK50)} -> 15403.333 | AO50: {=SUMPRODUCT((D$8:AN$8="Margin")*D50:AN50)} -> 7234.3333 | AP50: SOW valid until Apr 30, 2026 | AQ50: 100% | AR50: HPE | AS50: DS10_Secured
A51: SOW- Finder Fee - Social Media Resource for HPE Hire - Jennifer Coles | B51: Neeraj | C51: Staff Aug | AH51: 7000 | AN51: {=SUMPRODUCT((D$8:AK$8<>"Margin")*(D$8:AK$8<>"Salary_$600")*D51:AK51)} -> 7000 | AO51: {=SUMPRODUCT((D$8:AN$8="Margin")*D51:AN51)} -> 0 | AP51: Finder Fee SOW for Abhay Mokhal. PO Awaited | AQ51: 100% | AR51: HPE | AS51: DS10_Secured
A52: Icertis Web dev and Creative | B52: Neeraj | C52: Staff Aug | D52: 7050 | F52: 2429 | G52: 7050 | I52: 2429 | J52: 7050 | K52: 4621 | L52: =J52-K52 -> 2429 | M52: 7050 | N52: 4818 | O52: 2182 | P52: 7050 | Q52: 4818 | R52: 2182 | S52: 7050 | T52: 4818 | U52: 2182 | V52: 7050 | W52: 4818 | X52: 2182 | Y52: 7050 | Z52: 4818 | AA52: 2182 | AB52: 7000 | AC52: 4818 | AD52: 2182 | AE52: 7000 | AF52: 4818 | AG52: 2182 | AH52: 7000 | AI52: 4818 | AJ52: 2182 | AK52: 7000 | AL52: 4818 | AM52: 2182 | AN52: {=SUMPRODUCT((D$8:AK$8<>"Margin")*(D$8:AK$8<>"Salary_$600")*D52:AK52)} -> 84400 | AO52: {=SUMPRODUCT((D$8:AN$8="Margin")*D52:AN52)} -> 26925 | AP52: SOW valid until Mar 3, 2026 | AQ52: 100% | AR52: Icertis | AS52: DS10_Secured
A53: IDBS – Email Templates | B53: Neeraj | C53: Project | D53: 0 | F53: 0 | G53: 0 | I53: 0 | J53: 0 | K53: 0 | L53: 0 | M53: 0 | N53: 0 | O53: 0 | P53: 0 | Q53: 0 | R53: 0 | S53: 0 | T53: 0 | V53: 2000 | X53: 800 | Y53: 0 | AB53: 0 | AE53: 0 | AH53: 0 | AK53: 0 | AN53: {=SUMPRODUCT((D$8:AK$8<>"Margin")*(D$8:AK$8<>"Salary_$600")*D53:AK53)} -> 2000 | AO53: {=SUMPRODUCT((D$8:AN$8="Margin")*D53:AN53)} -> 800 | AP53: One-time SOW. Delivered and billed. | AR53: IDBS | AS53: DS10_Secured
A54: IDBS: making gated PDF content accessible for AI/LLM tools | B54: Neeraj | C54: Project | D54: 0 | G54: 0 | J54: 0 | M54: 0 | P54: 0 | S54: 0 | V54: 0 | Y54: 0 | AB54: 0 | AE54: 0 | AH54: 10000 | AJ54: =AH54*0.4 -> 4000 | AK54: 0 | AM54: =AK54*0.4 -> 0 | AN54: {=SUMPRODUCT((D$8:AK$8<>"Margin")*(D$8:AK$8<>"Salary_$600")*D54:AK54)} -> 10000 | AO54: {=SUMPRODUCT((D$8:AN$8="Margin")*D54:AN54)} -> 4000 | AP54: SOW approved. Project will be delivered Dec 15, 2025 | AQ54: 100% | AR54: IDBS | AS54: DS10_Secured
A55: IDBS Website Audit, Recommendations and Templates | B55: Neeraj | C55: Project | D55: 0 | G55: 0 | J55: 0 | M55: 0 | P55: 0 | S55: 0 | V55: 0 | Y55: 0 | AB55: 0 | AE55: 0 | AH55: 0 | AK55: 13000 | AM55: =AK55*0.4 -> 5200 | AN55: {=SUMPRODUCT((D$8:AK$8<>"Margin")*(D$8:AK$8<>"Salary_$600")*D55:AK55)} -> 13000 | AO55: {=SUMPRODUCT((D$8:AN$8="Margin")*D55:AN55)} -> 5200 | AP55: SOW approved. Need to deliver Dec 31, 2025 | AQ55: 100% | AR55: IDBS | AS55: DS10_Secured
A56: LiveRamp Marketo & Analytics | B56: Neeraj | C56: Staff Aug | D56: 16000 | F56: 7445 | G56: 16000 | I56: 7445 | J56: 16000 | K56: 8555 | L56: 7445 | M56: 16000 | N56: 9026 | O56: 6974 | P56: 16000 | Q56: 9026 | R56: 6974 | S56: 16000 | T56: 9026 | U56: 6974 | V56: 16000 | W56: 9026 | X56: 6974 | Y56: 16000 | Z56: 9026 | AA56: 6974 | AB56: 16000 | AC56: 9026 | AD56: 6974 | AE56: 16000 | AF56: 9026 | AG56: 6974 | AH56: 16000 | AI56: 9026 | AJ56: 6974 | AK56: 16000 | AL56: 9026 | AM56: 6974 | AN56: {=SUMPRODUCT((D$8:AK$8<>"Margin")*(D$8:AK$8<>"Salary_$600")*D56:AK56)} -> 192000 | AO56: {=SUMPRODUCT((D$8:AN$8="Margin")*D56:AN56)} -> 85101 | AP56: SOW valid until Dec 31, 2025 | AQ56: 100% | AR56: LiveRamp | AS56: DS10_Secured
A57: Molecular Devices | B57: Neeraj | C57: Staff Aug | D57: 15500 | F57: 5040 | G57: 15500 | I57: 5040 | J57: 15500 | K57: 10460 | L57: 5040 | M57: 15500 | N57: 12007 | O57: 3493 | P57: 15500 | Q57: 9964 | R57: 5536 | S57: 15500 | T57: 9964 | U57: 5536 | V57: 15500 | W57: 9964 | X57: 5536 | Y57: 15500 | Z57: 9964 | AA57: 5536 | AB57: 15500 | AC57: 9964 | AD57: 5536 | AE57: 15500 | AF57: 9964 | AG57: 5536 | AH57: 15500 | AI57: 9964 | AJ57: 5536 | AK57: 15500 | AL57: 9964 | AM57: 5536 | AN57: {=SUMPRODUCT((D$8:AK$8<>"Margin")*(D$8:AK$8<>"Salary_$600")*D57:AK57)} -> 186000 | AO57: {=SUMPRODUCT((D$8:AN$8="Margin")*D57:AN57)} -> 62901 | AP57: SOW valid until Dec 31, 2025 | AQ57: 100% | AR57: Molecular Devices | AS57: DS10_Secured
A58: Molecular Devices (Ceros Designer) | B58: Neeraj | C58: Staff Aug | AB58: 1800 | AC58: 1300 | AD58: =AB58-AC58 -> 500 | AE58: 1800 | AF58: 1300 | AG58: =AE58-AF58 -> 500 | AH58: 1800 | AI58: 1300 | AJ58: =AH58-AI58 -> 500 | AK58: 1800 | AL58: 1300 | AM58: =AK58-AL58 -> 500 | AN58: {=SUMPRODUCT((D$8:AK$8<>"Margin")*(D$8:AK$8<>"Salary_$600")*D58:AK58)} -> 7200 | AO58: {=SUMPRODUCT((D$8:AN$8="Margin")*D58:AN58)} -> 2000 | AP58: New 4-month SOW signed with partial resource. Client has started with a part time resource to access ROI. In December we will come to know if client wants to extend this SOW | AQ58: 100% | AR58: Molecular Devices | AS58: DS10_Secured
A59: RingCentral Web Development | B59: Neeraj | C59: Staff Aug | D59: 41975 | F59: 22721 | G59: 42003 | I59: 22721 | J59: 41975 | K59: 19254 | L59: 22721 | M59: =41975+24 -> 41999 | N59: 20361 | O59: 21614 | P59: 41975 | Q59: 20361 | R59: 21614 | S59: 41975 | T59: 20361 | U59: 21614 | V59: 41975 | W59: 20361 | X59: 21614 | Y59: 41975 | Z59: 20361 | AA59: 21614 | AB59: 41975 | AC59: 20361 | AD59: 21614 | AE59: 41975 | AF59: 20361 | AG59: 21614 | AH59: 41975 | AI59: 20361 | AJ59: 21614 | AK59: 41975 | AL59: 20361 | AM59: 21614 | AN59: {=SUMPRODUCT((D$8:AK$8<>"Margin")*(D$8:AK$8<>"Salary_$600")*D59:AK59)} -> 503752 | AO59: {=SUMPRODUCT((D$8:AN$8="Margin")*D59:AN59)} -> 262689 | AP59: SOW for the period Oct 1, 2025 – Dec 31, 2025 has been approved. | AQ59: 100% | AR59: RingCentral | AS59: DS10_Secured
A60: SEMI - PM - Developer - Designer | B60: Neeraj | C60: Staff Aug | D60: 12500 | F60: 1536 | G60: 12500 | I60: 1536 | J60: 12500 | K60: 10964 | L60: 1536 | M60: 12500 | N60: 11852 | O60: 648 | P60: 12500 | Q60: 11852 | R60: 648 | S60: 12500 | T60: 11852 | U60: 648 | V60: 12500 | W60: 11852 | X60: 648 | Y60: 12500 | Z60: 11852 | AA60: 648 | AN60: {=SUMPRODUCT((D$8:AK$8<>"Margin")*(D$8:AK$8<>"Salary_$600")*D60:AK60)} -> 100000 | AO60: {=SUMPRODUCT((D$8:AN$8="Margin")*D60:AN60)} -> 7848 | AP60: Merged into the master SEMI SOW | AR60: SEMI | AS60: DS10_Secured
A61: SEMI - Shopify Full Stack Developer | B61: Neeraj | C61: Staff Aug | D61: 4166 | F61: -1348 | G61: 4166 | I61: -1348 | J61: 4166 | K61: 5514 | L61: -1348 | M61: 4166 | N61: 3398 | O61: =M61-N61 -> 768 | P61: 4166 | Q61: 3398 | R61: =P61-Q61 -> 768 | S61: 4166 | T61: 3398 | U61: =S61-T61 -> 768 | V61: 4166 | W61: 3398 | X61: =V61-W61 -> 768 | Y61: 4166 | Z61: 3398 | AA61: =Y61-Z61 -> 768 | AN61: {=SUMPRODUCT((D$8:AK$8<>"Margin")*(D$8:AK$8<>"Salary_$600")*D61:AK61)} -> 33328 | AO61: {=SUMPRODUCT((D$8:AN$8="Margin")*D61:AN61)} -> -204 | AP61: Merged into the master SEMI SOW | AR61: SEMI | AS61: DS10_Secured
A62: SEMI - PM, Drupal Developer, Designer & Shopify Full Stack Developer | B62: Neeraj | C62: Staff Aug | AB62: 16666 | AC62: 14464 | AD62: =AB62-AC62 -> 2202 | AE62: 16666 | AF62: 14464 | AG62: =AE62-AF62 -> 2202 | AH62: 16666 | AI62: 14464 | AJ62: =AH62-AI62 -> 2202 | AK62: 16666 | AL62: 14464 | AM62: =AK62-AL62 -> 2202 | AN62: {=SUMPRODUCT((D$8:AK$8<>"Margin")*(D$8:AK$8<>"Salary_$600")*D62:AK62)} -> 66664 | AO62: {=SUMPRODUCT((D$8:AN$8="Margin")*D62:AN62)} -> 8808 | AP62: SOW valid for duration Aug16, 2025 to Aug 15, 2026 | AQ62: 100% | AR62: SEMI | AS62: DS10_Secured
A63: UiPath Web Development | B63: Neeraj | C63: Staff Aug | D63: 36400 | F63: 17996 | G63: 45600 | I63: 17996 | J63: 45600 | K63: 27604 | L63: 17996 | M63: 45600 | N63: 29244 | O63: 16356 | P63: 45600 | Q63: 29244 | R63: 16356 | S63: 45600 | T63: 29244 | U63: 16356 | V63: 45600 | W63: 29244 | X63: 16356 | Y63: 45600 | Z63: 29244 | AA63: 16356 | AB63: 45600 | AC63: 29244 | AD63: 16356 | AE63: 45600 | AF63: 29244 | AG63: 16356 | AH63: =45600-4600 -> 41000 | AI63: 29244 | AJ63: 16356 | AK63: =45600-4600 -> 41000 | AL63: 29244 | AM63: 16356 | AN63: {=SUMPRODUCT((D$8:AK$8<>"Margin")*(D$8:AK$8<>"Salary_$600")*D63:AK63)} -> 528800 | AO63: {=SUMPRODUCT((D$8:AN$8="Margin")*D63:AN63)} -> 201192 | AP63: SOW valid until 30 Apr, 2026 | AQ63: 100% | AR63: UiPath | AS63: DS10_Secured
A64: UiPath Forum | B64: Neeraj | C64: Staff Aug | D64: 4600 | F64: 0 | G64: 0 | I64: 0 | J64: 0 | K64: 0 | L64: 0 | M64: 0 | P64: 0 | S64: 0 | V64: 0 | Y64: 0 | AB64: 0 | AC64: 0 | AD64: 0 | AE64: 0 | AF64: 0 | AG64: 0 | AH64: 0 | AI64: 0 | AJ64: 0 | AK64: 0 | AL64: 0 | AM64: 0 | AN64: {=SUMPRODUCT((D$8:AK$8<>"Margin")*(D$8:AK$8<>"Salary_$600")*D64:AK64)} -> 4600 | AO64: {=SUMPRODUCT((D$8:AN$8="Margin")*D64:AN64)} -> 0 | AP64: Merged into the master UiPath SOW effective Feb 1, 2025. | AR64: UiPath | AS64: DS10_Secured
A65: YetiMyFriend App | B65: Neeraj | C65: Staff Aug | D65: 5820 | F65: 1523 | G65: 5080 | I65: 1523 | J65: 4940 | K65: 3417 | L65: =J65-K65 -> 1523 | M65: 4980 | N65: 3698 | O65: =M65-N65 -> 1282 | P65: 4800 | Q65: 3698 | R65: 1102 | S65: 4820 | T65: 3698 | U65: 1102 | V65: 4800 | W65: 3698 | X65: 1102 | Y65: 4800 | Z65: 3698 | AA65: 1102 | AB65: 4800 | AC65: 3698 | AD65: =AB65-AC65 -> 1102 | AE65: 4640 | AF65: 3698 | AG65: =AE65-AF65 -> 942 | AH65: 4500 | AI65: 3698 | AJ65: =AH65-AI65 -> 802 | AK65: 4781 | AL65: 3698 | AM65: =AK65-AL65 -> 1083 | AN65: {=SUMPRODUCT((D$8:AK$8<>"Margin")*(D$8:AK$8<>"Salary_$600")*D65:AK65)} -> 58761 | AO65: {=SUMPRODUCT((D$8:AN$8="Margin")*D65:AN65)} -> 14188 | AP65: Open-ended SOW. On client request a $300 discount in monthly billing has been agreed. Client is fine with the newly monthly rate for the next 6 months. | AQ65: 100% | AR65: YetiMyFriend | AS65: DS10_Secured
A66: Solutions and Staff Augmentation (Projects) - Track 2
A69: TOTAL Secured | D69: =SUM(D11:D68) -> 420557 | F69: =SUM(F11:F68) -> 212638.04 | G69: =SUM(G11:G68) -> 501227 | I69: =SUM(I11:I68) -> 204562.04 | J69: =SUM(J11:J68) -> 658373 | L69: =SUM(L11:L68) -> 183066.04 | M69: =SUM(M11:M68) -> 520730 | O69: =SUM(O11:O68) -> 152059 | P69: =SUM(P11:P68) -> 464099 | R69: =SUM(R11:R68) -> 207980 | S69: =SUM(S11:S68) -> 478239 | U69: =SUM(U11:U68) -> 203640 | V69: =SUM(V11:V68) -> 515679 | X69: =SUM(X11:X68) -> 210516 | Y69: =SUM(Y11:Y68) -> 454163 | AA69: =SUM(AA11:AA68) -> 219326 | AB69: =SUM(AB11:AB68) -> 589509 | AD69: =SUM(AD11:AD68) -> 212915.5 | AE69: =SUM(AE11:AE68) -> 635118.8 | AG69: =SUM(AG11:AG68) -> 206321 | AH69: =SUM(AH11:AH68) -> 475627.33 | AJ69: =SUM(AJ11:AJ68) -> 195650.33 | AK69: =SUM(AK11:AK68) -> 637840 | AM69: =SUM(AM11:AM68) -> 181849 | AN69: =SUM(AN14:AN68) -> 6351162.1 | AO69: =SUM(AO14:AO68) -> 2619603
A70: Track 1
A71: Aldevron - Digital Web Marketing Support | B71: Neeraj | C71: Staff Aug | D71: 0 | G71: 0 | J71: 0 | M71: 0 | P71: 0 | S71: 0 | V71: 0 | Y71: 0 | AB71: 0 | AH71: 0 | AK71: 5000 | AN71: {=SUMPRODUCT((D$8:AK$8<>"Margin")*(D$8:AK$8<>"Salary_$600")*D71:AK71)} -> 5000 | AO71: {=SUMPRODUCT((D$8:AN$8="Margin")*D71:AN71)} -> 0 | AP71: Client has shared 2 tasks. Need to estimate and share SOW | AQ71: 100% | AR71: Aldevron | AS71: DS30_Projection
A72: Molecular Devices - Global SEO and GEO Optimization Support | B72: Neeraj | C72: Staff Aug | D72: 0 | G72: 0 | J72: 0 | M72: 0 | P72: 0 | S72: 0 | V72: 0 | Y72: 0 | AB72: 0 | AE72: 0 | AH72: 0 | AM72: =AK72*0.4 -> 0 | AN72: {=SUMPRODUCT((D$8:AK$8<>"Margin")*(D$8:AK$8<>"Salary_$600")*D72:AK72)} -> 0 | AO72: {=SUMPRODUCT((D$8:AN$8="Margin")*D72:AN72)} -> 0 | AP72: Not getting approved in 2025 | AQ72: 0 | AR72: Molecular Devices | AS72: DS30_Projection
A73: Molecular Devices - Performance Analytics & Reporting | B73: Neeraj | C73: Staff Aug | D73: 0 | G73: 0 | J73: 0 | M73: 0 | P73: 0 | S73: 0 | V73: 0 | Y73: 0 | AB73: 0 | AE73: 0 | AH73: 0 | AK73: 0 | AM73: =AK73*0.4 -> 0 | AN73: {=SUMPRODUCT((D$8:AK$8<>"Margin")*(D$8:AK$8<>"Salary_$600")*D73:AK73)} -> 0 | AO73: {=SUMPRODUCT((D$8:AN$8="Margin")*D73:AN73)} -> 0 | AP73: Not getting approved in 2025 | AQ73: 0 | AR73: Molecular Devices | AS73: DS30_Projection
A74: North West Distribution - Replacement for AMS | B74: Neeraj | C74: Staff Aug | D74: 0 | G74: 0 | J74: 0 | M74: 0 | P74: 0 | S74: 0 | V74: 0 | Y74: 0 | AB74: 0 | AE74: 0 | AH74: 0 | AM74: =AK74*0.4 -> 0 | AN74: {=SUMPRODUCT((D$8:AK$8<>"Margin")*(D$8:AK$8<>"Salary_$600")*D74:AK74)} -> 0 | AO74: {=SUMPRODUCT((D$8:AN$8="Margin")*D74:AN74)} -> 0 | AP74: Prospect moved it to Jan 2026 | AQ74: 0 | AR74: North West Distribution | AS74: DS30_Projection
A75: Hitachi Industrial Equipment Systems - SEO for https://www.hitachi-ies.co.jp/ (Japanese) | B75: Neeraj | C75: Project | D75: 0 | G75: 0 | J75: 0 | M75: 0 | P75: 0 | S75: 0 | V75: 0 | Y75: 0 | AB75: 0 | AE75: 0 | AH75: 0 | AK75: 0 | AM75: =AK75*0.4 -> 0 | AN75: {=SUMPRODUCT((D$8:AK$8<>"Margin")*(D$8:AK$8<>"Salary_$600")*D75:AK75)} -> 0 | AO75: {=SUMPRODUCT((D$8:AN$8="Margin")*D75:AN75)} -> 0 | AP75: Did not win this project | AQ75: 0 | AR75: HIES | AS75: DS30_Projection
A76: Hitachi Industrial Equipment Systems - SEO strategy and implementation - https://www.hitachi-ies.com/ (English) | B76: Neeraj | C76: Project | D76: 0 | G76: 0 | J76: 0 | M76: 0 | P76: 0 | S76: 0 | V76: 0 | Y76: 0 | AB76: 0 | AE76: 0 | AH76: 0 | AK76: 0 | AM76: =AK76*0.4 -> 0 | AN76: {=SUMPRODUCT((D$8:AK$8<>"Margin")*(D$8:AK$8<>"Salary_$600")*D76:AK76)} -> 0 | AO76: {=SUMPRODUCT((D$8:AN$8="Margin")*D76:AN76)} -> 0 | AP76: Did not win this project | AQ76: 0 | AR76: HIES | AS76: DS30_Projection
A77: HAL: Event ROI Framework and Executive Dashboards | B77: Neeraj | C77: Project | D77: 0 | G77: 0 | J77: 0 | M77: 0 | P77: 0 | S77: 0 | V77: 0 | Y77: 0 | AB77: 0 | AE77: 0 | AH77: 0 | AK77: 0 | AR77: HAL | AS77: DS30_Projection
A79: Track 2
A80: ADNOC - Mobile Application, CRM and Web Development | B80: Neeraj | D80: 0 | G80: 0 | J80: 0 | M80: 0 | P80: 0 | S80: 0 | V80: 0 | Y80: 0 | AB80: 0 | AE80: 0 | AH80: 0 | AK80: 0 | AN80: {=SUMPRODUCT((D$8:AK$8<>"Margin")*(D$8:AK$8<>"Salary_$600")*D80:AK80)} -> 0 | AO80: {=SUMPRODUCT((D$8:AN$8="Margin")*D80:AN80)} -> 0 | AQ80: 5% | AR80: ADNOC | AS80: DS50_Projection
A81: Fannie Mae - RFP for Digital Marketing | B81: Neeraj | C81: Staff Aug | D81: 0 | G81: 0 | J81: 0 | M81: 0 | P81: 0 | S81: 0 | V81: 0 | Y81: 0 | AB81: 0 | AE81: 0 | AH81: 0 | AK81: 0 | AN81: {=SUMPRODUCT((D$8:AK$8<>"Margin")*(D$8:AK$8<>"Salary_$600")*D81:AK81)} -> 0 | AO81: {=SUMPRODUCT((D$8:AN$8="Margin")*D81:AN81)} -> 0 | AP81: RFP on hold for now | AQ81: 5% | AR81: Fannie Mae | AS81: DS50_Projection
A82: Miller Knoll - Social Media Management Platform Provider | B82: Neeraj | C82: Project | D82: 0 | G82: 0 | J82: 0 | M82: 0 | P82: 0 | S82: 0 | V82: 0 | Y82: 0 | AB82: 0 | AE82: 0 | AH82: 0 | AK82: 0 | AN82: {=SUMPRODUCT((D$8:AK$8<>"Margin")*(D$8:AK$8<>"Salary_$600")*D82:AK82)} -> 0 | AO82: {=SUMPRODUCT((D$8:AN$8="Margin")*D82:AN82)} -> 0 | AP82: No POC being done. Client will provide new requirements | AQ82: 5% | AR82: Miller Knoll | AS82: DS50_Projection
A83: GIZ - Nigeria Energy Support Programme | B83: Neeraj | C83: Project | D83: 0 | G83: 0 | J83: 0 | M83: 0 | P83: 0 | S83: 0 | V83: 0 | Y83: 0 | AB83: 0 | AE83: 0 | AH83: 0 | AN83: {=SUMPRODUCT((D$8:AK$8<>"Margin")*(D$8:AK$8<>"Salary_$600")*D83:AK83)} -> 0 | AO83: {=SUMPRODUCT((D$8:AN$8="Margin")*D83:AN83)} -> 0 | AP83: RFP response submitted, confidence to win for delivery in 2026 | AQ83: 25% | AR83: GIZ | AS83: DS50_Projection
A84: Inatech - Web Marketing support | B84: Neeraj | D84: 0 | G84: 0 | J84: 0 | M84: 0 | P84: 0 | S84: 0 | V84: 0 | Y84: 0 | AB84: 0 | AE84: 0 | AH84: 0 | AK84: 0 | AN84: {=SUMPRODUCT((D$8:AK$8<>"Margin")*(D$8:AK$8<>"Salary_$600")*D84:AK84)} -> 0 | AO84: {=SUMPRODUCT((D$8:AN$8="Margin")*D84:AN84)} -> 0 | AP84: Top-of-funnel activities. Working with Ram | AQ84: 5% | AR84: Inatech | AS84: DS50_Projection
A85: IHG - Web Marketing support | B85: Neeraj | C85: Project | D85: 0 | G85: 0 | J85: 0 | M85: 0 | P85: 0 | S85: 0 | V85: 0 | Y85: 0 | AB85: 0 | AE85: 0 | AH85: 0 | AK85: 0 | AN85: {=SUMPRODUCT((D$8:AK$8<>"Margin")*(D$8:AK$8<>"Salary_$600")*D85:AK85)} -> 0 | AO85: {=SUMPRODUCT((D$8:AN$8="Margin")*D85:AN85)} -> 0 | AP85: Request sent to Raj Verma to follow up with Vivien. Also had a meeting with Ankur's contact: Ketan | AQ85: 5% | AR85: IHG | AS85: DS50_Projection
AS86: DS50_Projection
AS87: DS50_Projection
AS88: DS50_Projection
A90: TOTAL Projection | D90: =SUM(D71:D89) -> 0 | E90: =SUM(E71:E89) -> 0 | F90: =SUM(F71:F89) -> 0 | G90: =SUM(G71:G89) -> 0 | H90: =SUM(H71:H89) -> 0 | I90: =SUM(I71:I89) -> 0 | J90: =SUM(J71:J89) -> 0 | K90: =SUM(K71:K89) -> 0 | ... AK90: =SUM(AK71:AK89) -> 5000 | AL90: =SUM(AL72:AL89) -> 0 | AM90: =SUM(AM72:AM89) -> 0 | AN90: =SUM(AN71:AN89) -> 5000 | AO90: =SUM(AO71:AO89) -> 0
A92: NetApp - Staff Augmentation | B92: Neeraj | C92: Staff Aug | M92: 0 | AP92: Top-of-funnel activities. | AQ92: 25% | AR92: NetApp | AS92: DS55_Projection
A93: Moveworks - Web Marketing Support | B93: Neeraj | C93: Project | J93: 0 | K93: 0 | M93: 0 | AP93: Top-of-funnel activities. | AQ93: 25% | AR93: Moveworks | AS93: DS55_Projection
A95: TOTAL Prospecting
A96: Secured | D96: =D69 -> 420557 | G96: =G69 -> 501227 | J96: =J69 -> 658373 | K96: 0 | L96: 0 | M96: =M69 -> 520730 | N96: 0 | O96: 0 | P96: =P69 -> 464099 | Q96: 0 | R96: 0 | S96: =S69 -> 478239 | V96: =V69 -> 515679 | Y96: =Y69 -> 454163 | AB96: =AB69 -> 589509 | AE96: =AE69 -> 635118.8 | AH96: =AH69 -> 475627.33 | AK96: =AK69 -> 637840 | AN96: =AN69 -> 6351162.1
A97: Projection | D97: =D90 -> 0 | G97: =G90 -> 0 | J97: =J90 -> 0 | K97: 0 | L97: 0 | M97: =M90 -> 0 | N97: 0 | O97: 0 | P97: =P90 -> 0 | Q97: 0 | R97: 0 | S97: =S90 -> 0 | V97: =V90 -> 0 | Y97: =Y90 -> 0 | AB97: =AB90 -> 0 | AE97: =AE90 -> 0 | AH97: =AH90 -> 0 | AK97: =AK90 -> 5000 | AN97: =AN90 -> 5000
A98: Prospecting | D98: =SUM(D92:D93) -> 0 | G98: =SUM(G92:G93) -> 0 | J98: =SUM(J92:J93) -> 0 | K98: 0 | L98: 0 | M98: =SUM(M92:M93) -> 0 | N98: 0 | O98: 0 | P98: =SUM(P92:P93) -> 0 | Q98: 0 | R98: 0 | S98: =SUM(S92:S93) -> 0 | V98: =SUM(V92:V93) -> 0 | Y98: =SUM(Y92:Y93) -> 0 | AB98: =SUM(AB92:AB93) -> 0 | AE98: =SUM(AE92:AE93) -> 0 | AH98: =SUM(AH92:AH93) -> 0 | AK98: =SUM(AK92:AK93) -> 0 | AN98: =SUM(D98:AK98) -> 0
A99: Solutions and Staff Augmentation Total | D99: =D96+D97+D98 -> 420557 | G99: =G96+G97+G98 -> 501227 | J99: =J96+J97+J98 -> 658373 | K99: 0 | L99: 0 | M99: =M96+M97+M98 -> 520730 | N99: 0 | O99: 0 | P99: =P96+P97+P98 -> 464099 | Q99: 0 | R99: 0 | S99: =S96+S97+S98 -> 478239 | V99: =V96+V97+V98 -> 515679 | Y99: =Y96+Y97+Y98 -> 454163 | AB99: =AB96+AB97+AB98 -> 589509 | AE99: =AE96+AE97+AE98 -> 635118.8 | AH99: =AH96+AH97+AH98 -> 475627.33 | AK99: =AK96+AK97+AK98 -> 642840 | AN99: =SUM(D99:AK99) -> 6356162.1
A101: Staffing
A102: HPE Ami Noss | B102: Neeraj/Sunil | C102: Staffing | D102: 32856 | F102: 2496.56 | G102: 31312 | I102: 2381.84 | J102: 34608 | K102: 27410.88 | L102: 2632.56 | M102: 35152 | N102: 27756.16 | O102: 2661.92 | P102: 35056 | Q102: 27754.88 | R102: 2669.92 | S102: 34752 | T102: 27481.6 | U102: 2656.64 | V102: 36256 | W102: 29404.16 | X102: 2883.28 | Y102: 33264 | AA102: 2520.48 | AB102: 33262 | AD102: 2520.48 | AE102: 35144 | AG102: 2756 | AH102: 19728 | AJ102: 1392.48 | AK102: 18308 | AM102: 1295.12 | AN102: {=SUMPRODUCT((D$8:AK$8<>"Margin")*(D$8:AK$8<>"Salary_$600")*D102:AK102)} -> 379698 | AO102: {=SUMPRODUCT((D$8:AN$8="Margin")*D102:AN102)} -> 28867.28 | AP102: SOW for renewal has been submitted | AQ102: 100% | AR102: HPE | AS102: DS70_Secured | AT102: Jennifer, Lesley, Heather
A103: HPE Rebecca Wissinger | B103: Neeraj/Sunil | C103: Staffing | D103: 21752 | F103: 1816 | G103: 19720 | I103: 1648 | J103: 21336 | K103: 17052 | L103: 1764 | M103: 19024 | N103: 14952 | O103: 1432 | P103: 12600 | Q103: 9408 | R103: 672 | S103: 14175 | T103: 10584 | U103: 756 | V103: 13200 | W103: 10584 | X103: 756 | Y103: 12600 | AA103: 672 | AB103: 12825 | AD103: 684 | AE103: 14250 | AG103: 760 | AH103: 10200 | AJ103: 544 | AK103: 9900 | AM103: 528 | AN103: {=SUMPRODUCT((D$8:AK$8<>"Margin")*(D$8:AK$8<>"Salary_$600")*D103:AK103)} -> 181582 | AO103: {=SUMPRODUCT((D$8:AN$8="Margin")*D103:AN103)} -> 12032 | AP103: SOW valid until Oct 31, 2026 | AQ103: 100% | AR103: HPE | AS103: DS70_Secured | AT103: Judy
A104: HPE Budget Mgmt | B104: Neeraj/Sunil | C104: Staffing | D104: 14400 | F104: 1400 | G104: 10080 | I104: 980 | J104: 12096 | L104: 1176 | M104: 12672 | O104: 1232 | P104: 5904 | R104: 574 | S104: 11520 | U104: 1120 | V104: 9936 | X104: 966 | Y104: 12096 | AA104: 1176 | AB104: 12096 | AD104: 1176 | AE104: 15264 | AG104: 1484 | AH104: 10656 | AJ104: 1036 | AK104: 10368 | AM104: 1008 | AN104: {=SUMPRODUCT((D$8:AK$8<>"Margin")*(D$8:AK$8<>"Salary_$600")*D104:AK104)} -> 137088 | AO104: {=SUMPRODUCT((D$8:AN$8="Margin")*D104:AN104)} -> 13328 | AP104: SOW valid until Apr 30, 2026 | AQ104: 100% | AR104: HPE | AS104: DS70_Secured | AT104: Ben
A105: HPE Tech Compliance | B105: Neeraj/Sunil | C105: Staffing | D105: 10590.44 | F105: 638.74 | G105: 9716 | I105: 586 | J105: 10298.96 | L105: 621.16 | M105: 10590.44 | O105: 638.74 | P105: 10687.6 | R105: 644.6 | S105: 10298.96 | U105: 621.16 | V105: 11464.88 | X105: 691.48 | Y105: 9813 | AA105: 591.86 | AB105: 10590.44 | AD105: 638.74 | AE105: 11153 | AG105: 673.9 | AH105: 11200.28 | AJ105: 533.26 | AK105: 11939 | AM105: 568.42 | AN105: {=SUMPRODUCT((D$8:AK$8<>"Margin")*(D$8:AK$8<>"Salary_$600")*D105:AK105)} -> 128343 | AO105: {=SUMPRODUCT((D$8:AN$8="Margin")*D105:AN105)} -> 7448.06 | AP105: SOW valid until Jan 31, 2026 | AQ105: 100% | AR105: HPE | AS105: DS70_Secured | AT105: Jim
A106: HPE Data Foundations Shashidhar Iddamsetty | B106: Neeraj/Sunil | C106: Staffing | D106: 49560 | F106: 3948 | G106: 44840 | I106: 3572 | J106: 49560 | L106: 3948 | M106: 51920 | O106: 4136 | P106: 50472 | R106: 4020 | S106: 43780 | U106: 3598 | V106: 51920 | X106: 4136 | Y106: 54720 | AA106: 4548 | AB106: 50920 | AD106: 4368 | AE106: 60730 | AG106: 5074 | AH106: 28424 | AJ106: 1836 | AK106: 27588 | AM106: 1782 | AN106: {=SUMPRODUCT((D$8:AK$8<>"Margin")*(D$8:AK$8<>"Salary_$600")*D106:AK106)} -> 564434 | AO106: {=SUMPRODUCT((D$8:AN$8="Margin")*D106:AN106)} -> 44966 | AP106: SOW for renewal has been submitted | AQ106: 100% | AR106: HPE | AS106: DS70_Secured | AT106: Jon, Ramesh, Vani
A107: HPE Marketing Automation- Christian Voigt | B107: Neeraj/Sunil | C107: Staffing | D107: 15960 | F107: 1680 | G107: 15105 | I107: 1590 | J107: 15960 | L107: 1680 | M107: 16720 | O107: 1760 | P107: 13680 | R107: 1440 | S107: 14440 | U107: 1520 | V107: 16720 | X107: 1760 | Y107: 12160 | AA107: 1280 | AB107: 15960 | AD107: 1680 | AE107: 17480 | AG107: 1840 | AH107: 9880 | AJ107: 1040 | AK107: 13300 | AM107: 1400 | AN107: {=SUMPRODUCT((D$8:AK$8<>"Margin")*(D$8:AK$8<>"Salary_$600")*D107:AK107)} -> 177365 | AO107: {=SUMPRODUCT((D$8:AN$8="Margin")*D107:AN107)} -> 18670 | AP107: SOW valid until Jan 31, 2026 | AQ107: 100% | AR107: HPE | AS107: DS70_Secured | AT107: Stephen
A108: TCS India Staffing | B108: Neeraj/Sunil | C108: Staffing | D108: 0 | E108: 0 | F108: 0 | G108: 0 | H108: 0 | I108: 0 | J108: 0 | K108: 0 | L108: 0 | M108: 0 | N108: 0 | O108: 0 | P108: 0 | Q108: 0 | R108: 0 | S108: 0 | T108: 0 | U108: 0 | V108: 0 | W108: 0 | X108: 0 | Y108: 0 | Z108: 0 | AA108: 0 | AB108: 0 | AC108: 0 | AD108: 0 | AE108: 0 | AG108: 0 | AH108: 0 | AJ108: 0 | AK108: 0 | AM108: 0 | AN108: {=SUMPRODUCT((D$8:AK$8<>"Margin")*(D$8:AK$8<>"Salary_$600")*D108:AK108)} -> 0 | AO108: {=SUMPRODUCT((D$8:AN$8="Margin")*D108:AN108)} -> 0 | AP108: There are no opportunities identified at this stage | AR108: TCS | AS108: DS80_Secured
...

Sheet Working Days 2026
A1: Month | B1: Days | C1: Hours
A2: Jan | B2: 21 | C2: =B2*8 -> 168 | D2: =C2*35 -> 5880
A3: Feb | B3: 20 | C3: =B3*8 -> 160 | D3: =C3*35 -> 5600
A4: Mar | B4: 21 | C4: =B4*8 -> 168 | D4: =C4*35 -> 5880
A5: Apr | B5: 22 | C5: =B5*8 -> 176 | D5: =C5*35 -> 6160
A6: May | B6: 21 | C6: =B6*8 -> 168 | D6: =C6*35 -> 5880
A7: Jun | B7: 22 | C7: =B7*8 -> 176 | D7: =C7*35 -> 6160
A8: Jul | B8: 23 | C8: =B8*8 -> 184 | D8: =C8*35 -> 6440 | F8: =(184-120)*35 -> 2240
A9: Aug | B9: 20 | C9: =B9*8 -> 160 | D9: =C9*35 -> 5600
A10: Sep | B10: 22 | C10: =B10*8 -> 176 | D10: =C10*35 -> 6160
A11: Oct | B11: 21 | C11: =B11*8 -> 168 | D11: =C11*35 -> 5880
A12: Nov | B12: 18 | C12: =B12*8 -> 144 | D12: =C12*35 -> 5040
A13: Dec | B13: 14 | C13: =B13*8 -> 112 | D13: =C13*35 -> 3920

Sheet Working Days
A1: Month | B1: Days | C1: Hours
A2: Jan | B2: 22 | C2: =B2*8 -> 176
A3: Feb | B3: 19 | C3: =B3*8 -> 152
A4: Mar | B4: 20 | C4: =B4*8 -> 160
A5: Apr | B5: 22 | C5: =B5*8 -> 176
A6: May | B6: 22 | C6: =B6*8 -> 176
A7: Jun | B7: 21 | C7: =B7*8 -> 168
A8: Jul | B8: 23 | C8: =B8*8 -> 184
A9: Aug | B9: 20 | C9: =B9*8 -> 160
A10: Sep | B10: 22 | C10: =B10*8 -> 176
A11: Oct | B11: 20 | C11: =B11*8 -> 160
A12: Nov | B12: 19 | C12: =B12*8 -> 152
A13: Dec | B13: 17 | C13: =B13*8 -> 136

Sheet Archived
A4: Name | B4: POC | C4: Service | D4: 45658 | E4: 45658 | F4: 45658 | G4: 45689 | H4: 45689 | I4: 45689 | J4: 45717 | K4: 45741 | L4: 45741 | M4: 45748 | N4: 45772 | O4: 45772 | P4: 45778 | Q4: 45778 | R4: 45802 | S4: 45809 | T4: 45809 | U4: 45809 | V4: 45839 | W4: 45839 | X4: 45839 | Y4: 45870 | Z4: 45870 | AA4: 45870 | AB4: 45901 | AC4: 45901 | AD4: 45901 | AE4: 45931 | AF4: 45931 | AG4: 45931 | AH4: 45962 | AI4: 45962 | AJ4: 45962 | AK4: 45992 | AL4: 45992 | AM4: 45992 | AN4: Total (Revenue) | AO4: Total Margin | AP4: Comments | AQ4: Renewal Confidence
A5: Please note: All data entered below this line was discarded as of July 29, 2025.
A9: Conde Group, Inc. | B9: Wendy | C9: Staffing | D9: 5988.5 | G9: 5264 | J9: 5684 | K9: 0 | L9: 5684 | M9: 20092.8 | N9: 0 | O9: 20093 | P9: 0 | Q9: 0 | R9: 0 | S9: 0 | T9: 0 | U9: 0 | V9: 0 | W9: 0 | Y9: 0 | AB9: 0 | AE9: 0 | AH9: 0 | AK9: 0 | AN9: {=SUMPRODUCT(('Sales by Customer- 2025'!D$8:AK$8<>"Margin")*('Sales by Customer- 2025'!D$8:AK$8<>"Salary_$600")*D9:AK9)} -> 37029.3
A10: Maxonic Inc. | B10: Wendy | C10: Staffing | D10: 70392 | G10: 65072 | J10: 55272 | K10: 50736 | L10: 4536 | M10: 57664 | N10: 52984 | O10: 4680 | P10: 59466 | Q10: 54056 | R10: 5410 | S10: 68026 | T10: 60689 | U10: 7337 | V10: 69352 | W10: 64593 | X10: 7496 | Y10: 65738 | AA10: 7620 | AB10: 69140 | AD10: 7620 | AE10: 69140 | AG10: 7620 | AH10: 69140 | AJ10: 7620 | AK10: 69140 | AM10: 7620 | AN10: {=SUMPRODUCT(('Sales by Customer- 2025'!D$8:AK$8<>"Margin")*('Sales by Customer- 2025'!D$8:AK$8<>"Salary_$600")*D10:AK10)} -> 787542
A11: Mindsource | B11: Wendy | C11: Staffing | D11: 0 | G11: 0 | J11: 0 | K11: 0 | L11: 0 | M11: 0 | N11: 0 | O11: 0 | P11: 0 | S11: 0 | V11: 0 | W11: 0 | X11: 0 | Y11: 0 | AB11: 0 | AE11: 0 | AH11: 0 | AK11: 0 | AN11: {=SUMPRODUCT(('Sales by Customer- 2025'!D$8:AK$8<>"Margin")*('Sales by Customer- 2025'!D$8:AK$8<>"Salary_$600")*D11:AK11)} -> 0
A12: Match Point (WWT) | B12: Wendy | C12: Staffing | D12: 14280 | G12: 12920 | J12: 5475 | K12: 4745 | L12: 730 | M12: 13200 | N12: 11440 | O12: 1760 | P12: 13200 | Q12: 11440 | R12: 1760 | S12: 12600 | T12: 10920 | U12: 1680 | V12: 13200 | W12: 11440 | X12: 1760 | Y12: 12600 | AA12: 1600 | AB12: 12000 | AD12: 1600 | AE12: 12000 | AG12: 1600 | AH12: 12000 | AJ12: 1600 | AK12: 12000 | AM12: 1600 | AN12: {=SUMPRODUCT(('Sales by Customer- 2025'!D$8:AK$8<>"Margin")*('Sales by Customer- 2025'!D$8:AK$8<>"Salary_$600")*D12:AK12)} -> 145475
A13: Johnson Service Group Inc. | B13: Wendy | C13: Staffing | D13: 4436 | G13: 4955 | J13: 5917 | K13: 0 | L13: 5917 | M13: 10262 | N13: 0 | O13: 10262 | P13: 7212 | Q13: 0 | R13: 7212 | S13: 8308 | T13: 0 | U13: 8308 | V13: 12291 | W13: 0 | X13: 12291 | Y13: 6733 | AA13: 6240 | AB13: 6240 | AD13: 6240 | AE13: 6240 | AG13: 6240 | AH13: 6240 | AJ13: 6240 | AK13: 6240 | AM13: 6240 | AN13: {=SUMPRODUCT(('Sales by Customer- 2025'!D$8:AK$8<>"Margin")*('Sales by Customer- 2025'!D$8:AK$8<>"Salary_$600")*D13:AK13)} -> 85074
A14: Trans American Information Systems, Inc. | B14: Wendy | C14: Staffing | D14: 36696 | G14: 34400 | J14: 36120 | K14: 31248 | L14: 4872 | M14: 35968 | N14: 31098 | O14: 4870 | P14: 36696 | Q14: 31752 | R14: 4944 | S14: 32680 | T14: 28272 | U14: 4408 | V14: 35544 | W14: 30744 | X14: 4800 | Y14: 34400 | AA14: 4640 | AB14: 34400 | AD14: 4640 | AE14: 34400 | AG14: 4640 | AH14: 34400 | AJ14: 4640 | AK14: 34400 | AM14: 4640 | AN14: {=SUMPRODUCT(('Sales by Customer- 2025'!D$8:AK$8<>"Margin")*('Sales by Customer- 2025'!D$8:AK$8<>"Salary_$600")*D14:AK14)} -> 420104
A15: VanderHouwen | B15: Wendy | C15: Staffing | D15: 54790 | G15: 31485 | J15: 32955 | K15: 32370 | L15: 585 | M15: 30420 | N15: 29880 | O15: 540 | P15: 28730 | Q15: 28220 | R15: 510 | S15: 27040 | T15: 26560 | U15: 480 | V15: 13520 | W15: 13280 | X15: 240 | Y15: 27040 | AA15: 480 | AB15: 27040 | AD15: 480 | AE15: 27040 | AG15: 480 | AH15: 27040 | AJ15: 480 | AK15: 27040 | AM15: 480 | AN15: {=SUMPRODUCT(('Sales by Customer- 2025'!D$8:AK$8<>"Margin")*('Sales by Customer- 2025'!D$8:AK$8<>"Salary_$600")*D15:AK15)} -> 354140
A16: VDart Inc | B16: Wendy | C16: Staffing | D16: 10080 | G16: 9120 | J16: 10080 | K16: 9744 | L16: 184.8 | M16: 10560 | N16: 10208 | O16: 193.6 | P16: 10080 | Q16: 9744 | R16: 184.8 | S16: 10080 | T16: 9744 | U16: 184.8 | V16: 10560 | W16: 10208 | X16: 193.6 | Y16: 10800 | AA16: 176 | AB16: 9600 | AD16: 176 | AE16: 9600 | AG16: 176 | AH16: 9600 | AJ16: 176 | AK16: 9600 | AM16: 176 | AN16: {=SUMPRODUCT(('Sales by Customer- 2025'!D$8:AK$8<>"Margin")*('Sales by Customer- 2025'!D$8:AK$8<>"Salary_$600")*D16:AK16)} -> 119760
A17: Azu Solutions | B17: Neeraj | C17: Staffing | S17: 0 | T17: 0 | U17: 0 | V17: 0 | W17: 0 | X17: 0 | Y17: 22000 | AA17: 2080 | AB17: 31200 | AD17: 3120 | AE17: 49600 | AG17: 4160 | AH17: 49600 | AJ17: 4160 | AK17: 49600 | AM17: 4160 | AN17: {=SUMPRODUCT(('Sales by Customer- 2025'!D$8:AK$8<>"Margin")*('Sales by Customer- 2025'!D$8:AK$8<>"Salary_$600")*D17:AK17)} -> 202000
A18: Technology Partners | C18: Staffing | S18: 840 | T18: 0 | U18: 840 | V18: 880 | W18: 0 | X18: 880 | Y18: 0 | Z18: 0 | AA18: 0 | AB18: 0 | AC18: 0 | AD18: 0 | AE18: 0 | AF18: 0 | AG18: 0 | AH18: 0 | AI18: 0 | AJ18: 0 | AK18: 0 | AL18: 0 | AM18: 0 | AN18: 0
A20: Red Oak Technologies | B20: Wendy | C20: Staffing | D20: 0 | G20: 0 | J20: 0 | K20: 0 | L20: 0 | M20: 0 | P20: 0 | S20: 0 | V20: 0 | Y20: 0 | AB20: 0 | AE20: 0 | AH20: 0 | AK20: 0 | AN20: {=SUMPRODUCT(('Sales by Customer- 2025'!D$8:AK$8<>"Margin")*('Sales by Customer- 2025'!D$8:AK$8<>"Salary_$600")*D20:AK20)} -> 0
A21: The Mice Groups Inc | B21: Wendy | C21: Staffing | D21: 0 | G21: 0 | J21: 0 | K21: 0 | L21: 0 | M21: 0 | P21: 0 | S21: 0 | V21: 0 | Y21: 0 | AB21: 0 | AE21: 0 | AH21: 0 | AK21: 0 | AN21: {=SUMPRODUCT(('Sales by Customer- 2025'!D$8:AK$8<>"Margin")*('Sales by Customer- 2025'!D$8:AK$8<>"Salary_$600")*D21:AK21)} -> 0
A22: Evolutionary System Corp. | B22: Wendy | C22: Staffing | D22: 0 | G22: 0 | J22: 0 | K22: 0 | L22: 0 | M22: 0 | P22: 0 | S22: 0 | V22: 0 | Y22: 0 | AB22: 0 | AE22: 0 | AH22: 0 | AK22: 0 | AN22: {=SUMPRODUCT(('Sales by Customer- 2025'!D$8:AK$8<>"Margin")*('Sales by Customer- 2025'!D$8:AK$8<>"Salary_$600")*D22:AK22)} -> 0
A23: Infostretch Corporation | B23: Wendy | C23: Staffing | D23: 0 | G23: 0 | J23: 0 | K23: 0 | L23: 0 | M23: 0 | P23: 0 | S23: 0 | V23: 0 | Y23: 0 | AB23: 0 | AE23: 0 | AH23: 0 | AK23: 0 | AN23: {=SUMPRODUCT(('Sales by Customer- 2025'!D$8:AK$8<>"Margin")*('Sales by Customer- 2025'!D$8:AK$8<>"Salary_$600")*D23:AK23)} -> 0
A24: _New Business SS | B24: Wendy | C24: Staffing | D24: 0 | G24: 0 | J24: 0 | K24: 0 | L24: 0 | M24: 0 | P24: 0 | S24: 0 | V24: 0 | Y24: 0 | AB24: 0 | AE24: 0 | AH24: 0 | AK24: 0 | AN24: {=SUMPRODUCT(('Sales by Customer- 2025'!D$8:AK$8<>"Margin")*('Sales by Customer- 2025'!D$8:AK$8<>"Salary_$600")*D24:AK24)} -> 0
A25: _New Business PG | B25: Wendy | C25: Staffing | D25: 0 | G25: 17398 | J25: 28308 | K25: 22260 | L25: 6048 | M25: 40388 | O25: 3385.6 | P25: 61975 | R25: 5501.55 | S25: 67392 | U25: 6488.4 | V25: 86241 | X25: 9477.4 | Y25: 49360 | AA25: 4096 | AB25: 49360 | AD25: 4096 | AE25: 49360 | AG25: 4096 | AH25: 49360 | AJ25: 4096 | AK25: 49360 | AM25: 4096 | AN25: {=SUMPRODUCT(('Sales by Customer- 2025'!D$8:AK$8<>"Margin")*('Sales by Customer- 2025'!D$8:AK$8<>"Salary_$600")*D25:AK25)} -> 548502
A26: _New Business BS | B26: Wendy | C26: Staffing | D26: 0 | G26: 2400 | J26: 5040 | K26: 1680 | L26: 3360 | M26: 13440 | O26: 5405.04 | P26: 14232 | R26: 5365.6 | S26: 23600 | U26: 11912.87 | V26: 34886 | X26: 17153.58 | Y26: 22080 | AA26: 5803.2 | AB26: 22080 | AD26: 5803.2 | AE26: 22080 | AG26: 5803.2 | AH26: 22080 | AJ26: 5803.2 | AK26: 22080 | AM26: 5803.2 | AN26: {=SUMPRODUCT(('Sales by Customer- 2025'!D$8:AK$8<>"Margin")*('Sales by Customer- 2025'!D$8:AK$8<>"Salary_$600")*D26:AK26)} -> 203998

Sheet Salary Projections 2026
A1: Projects | B1: Jan - Mar | C1: Apr - Sep | D1: Oct - Dec
A2: Automation Anywhere Web Dev | B2: 26522 | C2: 26522 | D2: 26522
A3: CheckPoint Desktop publishing of translated assets | B3: 849 | C3: 849 | D3: 849
A4: Church's Chicken & IT Support | B4: 201 | C4: 201 | D4: 201
A5: Databricks Martech Platform Operations Administrator | B5: 7419 | C5: 7511 | D5: 7511
A6: Databricks Ongoing Support | B6: =5656+32832 -> 38488 | C6: =5656+32832 -> 38488 | D6: =5656+32832 -> 38488
A7: Databricks Planning Project | B7: 3517 | C7: 3517 | D7: 3517
A8: Databricks Program Manager and Marketo | B8: 55460 | C8: 53358 | D8: =53358+15000*0.8 -> 65358
A9: Databricks SEO Project Management | B9: 3568 | C9: 3568 | D9: 3568
A10: EGIA Development Support | B10: 17108 | C10: 17108 | D10: 17108
A11: HAL Creative Support | B11: 2698 | C11: 2698 | D11: 2698
A12: HAL Digital Web Marketing | B12: 4478 | C12: 4478 | D12: 4478
A13: HAL Marketo Support | B13: 2543 | C13: 2543 | D13: 2543
A14: Hitachi Asia | B14: =12535+61000/6 -> 22701.667 | C14: =12535+61000/6 -> 22701.667 | D14: =12535+61000/6 -> 22701.667
A15: Hitachi Stem - Development Support | B15: 3015 | C15: 3015 | D15: 3015
A16: HPE- Documents Rebranding Landmark | B16: 3369 | C16: 3369 | D16: 3369
A17: HPE Marketing Strategy & Operations for the APJ Region | B17: 4802 | C17: 4802 | D17: 4802
A18: HPE Data & Analytics Zainab Jamal | B18: 5268 | C18: =1800+1927 -> 3727 | D18: =1800+1927 -> 3727
A19: HPE Data Foundations Shashidhar Iddamsetty | B19: 6597 | C19: =4333 -> 4333 | D19: =4333 -> 4333
A20: HPE Marketing Automation- Christian Voigt | B20: 7591 | C20: 7591 | D20: 7591
A21: HPE SEO PM HPE Store Hament Dudeja | B21: 748 | C21: 748 | D21: 748
A22: HPE SEO PM HPE Store Srihari Gopinath | B22: 2245 | C22: 2245 | D22: 2245
A23: HPE SEO Strategy Towa Ghosh (Projects) | B23: =6941-2245 -> 4696 | C23: =6941-2245 -> 4696 | D23: =6941-2245 -> 4696
A24: Icertis Web dev and Creative | B24: 4979 | C24: 4979 | D24: 4979
A25: LiveRamp Marketo & Analytics | B25: 9270 | C25: 9270 | D25: 9270
A26: Molecular Devices Web development, SEO, Ceros Designer | B26: 11884 | C26: 11884 | D26: 11884
A27: RingCentral Web Development | B27: =13973-900 -> 13073 | C27: 13973 | D27: 13973
A28: SEMI - PM, Drupal Developer, Designer & Shopify Full Stack Developer | B28: 14938 | C28: 14938 | D28: 14938
A29: SEMI - UI/UX Designer | B29: 2086 | C29: 2086 | D29: 2086
A30: UiPath Web Development | B30: =-2640+25641-3000 -> 20001 | C30: =-2640+25641-3000 -> 20001 | D30: =-2640+25641-3000 -> 20001
A31: YetiMyFriend App | B31: 3698 | C31: 3698 | D31: 3698

Sheet Salary Projections 2026 (copy)
A1: Projects | B1: Jan - Mar | C1: Apr - Sep | D1: Oct - Dec
A2: Automation Anywhere Web Dev | B2: 26522 | C2: 27762 | D2: 28634
A3: CheckPoint Desktop publishing of translated assets | B3: 849 | C3: 904 | D3: 904
A4: Church's Chicken & IT Support | B4: 201 | C4: 215 | D4: 215
A5: Databricks Martech Platform Operations Administrator | B5: 7693 | C5: 8283 | D5: 8283
A6: Databricks Ongoing Support | B6: =5656+32832 -> 38488 | C6: =5656*1.1+33882 -> 40103.6 | D6: =5656*1.1+34920 -> 41141.6
A7: Databricks Planning Project | B7: 3631 | C7: 3772 | D7: 3874
A8: Databricks Program Manager and Marketo | B8: 56520 | C8: 57811 | D8: 58791
A9: Databricks SEO Project Management | B9: 3713 | C9: 3713 | D9: 4024
A10: EGIA Development Support | B10: 17108 | C10: 18284 | D10: 18459
A11: HAL Creative Support | B11: 2698 | C11: 2698 | D11: 2908
A12: HAL Digital Web Marketing | B12: 4478 | C12: 4866 | D12: 4866
A13: HAL Marketo Support | B13: 2543 | C13: 2737 | D13: 2737
A14: Hitachi Asia | B14: 12535 | C14: 13001 | D14: 13245
A15: Hitachi Stem - Development Support | B15: 3015 | C15: 3256 | D15: 3256
A16: HPE- Documents Rebranding Landmark | B16: 3369 | C16: 3646 | D16: 3646
A17: HPE Marketing Strategy & Operations for the APJ Region | B17: 4802 | C17: 4802 | D17: 5222
A18: HPE Data & Analytics Zainab Jamal | B18: 5268 | C18: 5675 | D18: 5675
A19: HPE Data Foundations Shashidhar Iddamsetty | B19: 6597 | C19: =4333*1.1 -> 4766.3 | D19: =4333*1.1 -> 4766.3
A20: HPE Marketing Automation- Christian Voigt | B20: 7591 | C20: 7591 | D20: 7958
A21: HPE SEO PM HPE Store Hament Dudeja | B21: 748 | C21: 808 | D21: 808
A22: HPE SEO PM HPE Store Srihari Gopinath | B22: 2245 | C22: 2424 | D22: 2424
A23: HPE SEO Strategy Towa Ghosh (Projects) | B23: =6941-2245 -> 4696 | C23: =7293-C22 -> 4869 | D23: =7440-D22 -> 5016
A24: Icertis Web dev and Creative | B24: 4979 | C24: 5140 | D24: 5357
A25: LiveRamp Marketo & Analytics | B25: 9270 | C25: 9631 | D25: 9957
A26: Molecular Devices Web development, SEO, Ceros Designer | B26: 11884 | C26: 12660 | D26: 12742
A27: RingCentral Web Development | B27: 20901 | C27: 21771 | D27: 22331
A28: SEMI - PM, Drupal Developer, Designer & Shopify Full Stack Developer | B28: 14938 | C28: 16175 | D28: 16175
A29: SEMI - UI/UX Designer | B29: 2086 | C29: 2086 | D29: 2234.6
A30: UiPath Web Development | B30: =-2640+25641-3000 -> 20001 | C30: =-2640+27302-3000 -> 21662 | D30: =-2640+27665-3000 -> 22025
A31: YetiMyFriend App | B31: 3698 | C31: 4008 | D31: 4008

Sheet Action Items - 2026
B2: Line Item | C2: Recommended Action Items for Sustaining and Growth
B3: 1 | C3: Enhance both NVISH and MTI web properties to effectively showcase our capabilities, success stories, and portfolio.
B4: 2 | C4: Execute brand-building initiatives and targeted campaigns to highlight our expertise and achievements.
B5: 3 | C5: Generate lead introductions through our executives and sales associates.
B6: 4 | C6: Strengthen the process of assisting professionals from our network who are exploring new job opportunities.
B7: 5 | C7: Hire a sales hunter to proactively identify and close new business opportunities.
B8: 6 | C8: Pursue introductions with S-curve companies for strategic growth engagements.
B9: 7 | C9: Establish solution partnerships with platforms such as SEMRush, HubSpot, Marketo, UiPath etc., and leverage visibility on their partner portals.
B10: 8 | C10: Develop proofs of concept (POCs) to demonstrate our technical strengths and innovation.
B11: 9 | C11: Drive training and certification of our teams on emerging technologies, especially AI tools.
B12: 10 | C12: Monitor and analyze the careers sections and LinkedIn of our target companies (especially those where we have connections or MSAs) to understand hiring trends and plan proactive outreach.

Sheet HPE SOW Staffing
C2: Hewlett Packard Enterprise Company(SOW- Ami Noss)
B4: 1 | C4: Heather Smith
B5: 2 | C5: Jennifer Milhausen
B6: 3 | C6: Lesley Krone
C9: Hewlett Packard Enterprise Company(SOW- Rebecca Wissinger)
B11: 1 | C11: Judy-Anne K Goldman
C13: Hewlett Packard Enterprise Company (Rest of SOW minus above 2 SOWs)
B15: 1 | C15: Benjamin Nalezny
B16: 2 | C16: Jim Walsh
B17: 3 | C17: Jonathan Williams
B18: 4 | C18: Ramesh Babu
B19: 5 | C19: Stephen Usher
B20: 6 | C20: Vani Pindiproli

Sheet Sales by Customer- 2024
B1: Green: Legacy account, Little Growth, Blue: Legacy Account with Growth, Yellow: New Logo with jobs, Orange: Pipeline
B2: NVISH Solutions Inc.
B3: Sales by Customer Summary
E5: Actual | F5: Actual | G5: Actual | H5: Actual | I5: Actual | J5: Actual | K5: Actual | L5: Actual | M5: Actual | N5: Actual | O5: Actual | P5: Actual
A6: Status | C6: POC | D6: Service | E6: Jan 2024 | F6: Feb 2024 | G6: Mar 2024 | H6: Apr 2024 | I6: May 2024 | J6: Jun 2024 | K6: Jul 2024 | L6: 45505 | M6: 45559 | N6: 45589 | O6: 45597 | P6: 45627 | Q6: Total | R6: Comments
B7: Solutions and Staff Augmentation
A8: Confirmed | B8: AuditBoard, Inc. | C8: Neeraj | D8: Staff Aug | H8: =4000 -> 4000 | I8: =4000 -> 4000 | J8: =4000 -> 4000 | K8: 4000 | L8: 4000 | M8: 4000 | N8: 4000 | O8: 4000 | P8: 4000 | Q8: =SUM(E8:P8) -> 36000
A9: Confirmed | B9: Automation Anywhere, Inc | C9: Neeraj | D9: Staff Aug | E9: =86475 -> 86475 | F9: =45880 -> 45880 | G9: =45880 -> 45880 | H9: =45880 -> 45880 | I9: =40080 -> 40080 | J9: =40080 -> 40080 | K9: =40080 -> 40080 | L9: 40430 | M9: 40430 | N9: 40430 | O9: =(36580+3850) -> 40430 | P9: 40809 | Q9: =SUM(E9:P9) -> 546884
A10: Closed | B10: Blaze Technology, Inc. | C10: Neeraj | D10: Project | I10: =4500 -> 4500 | J10: =4748 -> 4748 | K10: 2800 | L10: 3640 | N10: 3395 | Q10: =SUM(E10:P10) -> 19083
A11: Confirmed | B11: Check Point Software Technologies Ltd. | C11: Neeraj | D11: Staff Aug | E11: =5000 -> 5000 | G11: =10200 -> 10200 | J11: =4995 -> 4995 | L11: 5000 | N11: 4995
A12: Confirmed | B12: Chooch.com | C12: Neeraj | D12: Staff Aug | E12: =9950 -> 9950 | F12: =3500 -> 3500 | G12: =3500 -> 3500 | H12: =3500 -> 3500 | J12: =3500 -> 3500 | K12: =7000 -> 7000 | L12: 3500 | M12: 3500 | N12: 3500 | O12: 4025 | P12: 3500 | Q12: =SUM(E12:P12) -> 48975
A13: Confirmed | B13: Church's Chicken | C13: Neeraj | D13: Project | E13: =7500 -> 7500 | Q13: =SUM(E13:P13) -> 7500
A14: Confirmed | B14: Databricks Ongoing Support | C14: Neeraj | D14: Staff Aug | E14: 51450 | F14: 51450 | G14: 51450 | H14: 51450 | I14: 51450 | J14: 51450 | K14: 51450 | L14: 51450 | M14: 51450 | N14: 114990 | O14: =51450+4950+3875+3875 -> 64150 | P14: 64175 | Q14: =SUM(E14:P14) -> 706365
A15: Confirmed | B15: Databricks Planning Project | C15: Neeraj | D15: Staff Aug | I15: 5000 | J15: 5000 | K15: 5000 | L15: 5000 | M15: 5000 | N15: 5000 | O15: 5000 | P15: 5000 | Q15: =SUM(E15:P15) -> 40000
A16: Confirmed | B16: Databricks Program Manager and Marketo | C16: Neeraj | D16: Staff Aug | I16: 13950 | J16: 23125 | K16: 23950 | L16: 30086 | M16: 34236 | N16: 40189 | O16: 58993 | P16: 77282 | Q16: =SUM(E16:P16) -> 301811
A17: Confirmed | B17: Databricks SEO Project Management | C17: Neeraj | D17: Staff Aug | I17: 4500 | J17: 4500 | K17: 4500 | L17: 4500 | M17: 4500 | N17: 4500 | O17: 4500 | P17: 4500 | Q17: =SUM(E17:P17) -> 36000
A18: Confirmed | B18: Databricks Web Accessibility | C18: Neeraj | D18: Staff Aug | J18: 3875 | K18: 3875 | L18: 3875 | M18: 3875 | Q18: =SUM(E18:P18) -> 15500 | R18: Getting merged in October with Ongoing Support SOW
A19: Confirmed | B19: EGIA | C19: Neeraj | D19: Staff Aug | E19: =73000 -> 73000 | F19: =73000 -> 73000 | G19: =73000 -> 73000 | H19: =73000 -> 73000 | J19: =39000 -> 39000 | K19: =39000 -> 39000 | L19: 39000 | M19: 39000 | N19: 39000 | O19: 39000 | P19: 39000 | Q19: =SUM(E19:P19) -> 565000
A20: Confirmed | B20: Hitachi America, Ltd. | C20: Neeraj | D20: Staff Aug | E20: =5000 -> 5000 | F20: =94135 -> 94135 | G20: =59525 -> 59525 | H20: =44000 -> 44000 | J20: =3096.38 -> 3096.38 | K20: =36000 -> 36000 | L20: 42625 | M20: 45010 | N20: 55000 | O20: 39625 | Q20: =SUM(E20:P20) -> 424016.38
A21: Confirmed | B21: Hitachi Asia Ltd. | C21: Neeraj | D21: Project | E21: =36135 -> 36135 | M21: 147928 | N21: 0 | Q21: =SUM(E21:P21) -> 184063
A22: Confirmed | B22: Hitachi Elevator Asia Pte Ltd. | C22: Neeraj | D22: Project | F22: =243 -> 243 | L22: 4270 | Q22: =SUM(E22:P22) -> 4513
A23: Confirmed | B23: Hitachi High Technologies America, Inc. | C23: Neeraj | D23: Staff Aug | E23: =4000 -> 4000 | F23: =4000 -> 4000 | G23: =4000 -> 4000 | H23: =5250 -> 5250 | J23: =5250 -> 5250 | K23: =8000 -> 8000 | L23: 4000 | M23: 4000 | N23: 4000 | O23: 4000 | P23: 4000 | Q23: =SUM(E23:P23) -> 50500
A24: Confirmed | B24: Hitachi Industrial Equipment & Solutions America, LLC | C24: Neeraj | D24: Project | E24: =10000 -> 10000 | H24: =6150 -> 6150 | J24: =15400 -> 15400 | K24: =15400 -> 15400 | L24: 30800 | Q24: =SUM(E24:P24) -> 77750
A25: Confirmed | B25: Hitachi Vantara LLC | C25: Neeraj | D25: Project | H25: =9000 -> 9000 | J25: =8000 -> 8000 | K25: =8000 -> 8000 | Q25: =SUM(E25:P25) -> 25000
A26: Confirmed | B26: Hewlett Packard Enterprise Company (India Staff Augmentation) | C26: Neeraj | E26: 45836 | F26: 50736 | G26: 42966 | H26: 50946 | I26: 51366 | J26: 60536 | K26: 70826 | L26: 65646 | M26: 64668 | N26: 72688 | O26: 74506 | P26: 66386 | Q26: =SUM(E26:P26) -> 717106
A27: Confirmed | B27: Icertis Inc. | C27: Neeraj | D27: Staff Aug | G27: 10800 | H27: 9464 | I27: 0 | J27: 9464 | K27: 10050 | L27: 18300 | M27: 6872 | N27: 7528 | O27: 7050 | P27: 7050 | Q27: =SUM(E27:P27) -> 86578
A28: Closed | B28: LeapPoint, LLC | C28: Neeraj | D28: Project | G28: =2800 -> 2800 | H28: =2100 -> 2100 | Q28: =SUM(E28:P28) -> 4900
A29: Confirmed | B29: LiveRamp, Inc. | C29: Neeraj | D29: Staff Aug | E29: =16000 -> 16000 | F29: =16000 -> 16000 | G29: =16000 -> 16000 | H29: =16000 -> 16000 | I29: =16000 -> 16000 | J29: =16000 -> 16000 | K29: =16000 -> 16000 | L29: 16000 | M29: 16000 | N29: 16000 | O29: 16000 | P29: 16000 | Q29: =SUM(E29:P29) -> 192000
A30: Closed | B30: Lob.com | C30: Neeraj | D30: Project | Q30: =SUM(E30:P30) -> 0
A31: Confirmed | B31: Molecular Devices Inc. | C31: Neeraj | D31: Staff Aug | E31: =14000 -> 14000 | F31: =15500 -> 15500 | G31: =16574 -> 16574 | H31: =15500 -> 15500 | I31: =17420 -> 17420 | J31: =15500 -> 15500 | K31: =15500 -> 15500 | L31: 15500 | M31: 15500 | N31: 15500 | O31: 15500 | P31: 16460 | Q31: =SUM(E31:P31) -> 188454
A32: Confirmed | B32: Marvell | C32: Neeraj/Sunil | D32: Staffing | E32: 13138 | F32: 16794 | G32: 9904 | H32: 12612 | I32: 14049 | J32: 19240 | K32: 25230 | L32: 26821 | M32: 27923 | N32: 27443 | O32: 23137.84 | P32: 27938.42 | Q32: =SUM(E32:P32) -> 244230.26
A33: Confirmed | B33: RingCentral, Inc. | C33: Neeraj | D33: Staff Aug | E33: =41975 -> 41975 | F33: =41975 -> 41975 | G33: =41975 -> 41975 | H33: =41975 -> 41975 | I33: =41975 -> 41975 | J33: =41975 -> 41975 | K33: =41975 -> 41975 | L33: 41975 | M33: 54445 | N33: 54445 | O33: 54445 | P33: 51975 | Q33: =SUM(E33:P33) -> 551110
A34: Confirmed | B34: SEMI | C34: Neeraj | D34: Staff Aug | E34: 16666 | F34: 16666 | G34: 16666 | H34: 16666 | I34: 16666 | J34: 16666 | K34: 17666 | L34: 16666 | M34: 16666 | N34: 16666 | O34: 16666 | P34: 16666 | Q34: =SUM(E34:P34) -> 200992
A35: Confirmed | B35: UiPath Inc. | C35: Neeraj | D35: Staff Aug | E35: 36400 | F35: 36400 | G35: 36400 | H35: 36400 | I35: 36400 | J35: 41000 | K35: 45600 | L35: 45600 | M35: 45600 | N35: 45600 | O35: 39686 | P35: 41000 | Q35: =SUM(E35:P35) -> 486086
A36: Paused | B36: VMware LLC | C36: Neeraj | D36: Staff Aug | E36: =4000 -> 4000 | F36: =4000 -> 4000 | G36: =4000 -> 4000 | H36: =4000 -> 4000 | J36: =4000 -> 4000 | Q36: =SUM(E36:P36) -> 20000
A37: Paused | B37: WekaIO, Inc. | C37: Neeraj | D37: Staff Aug | E37: =14906 -> 14906 | F37: =14907 -> 14907 | G37: =14906 -> 14906 | H37: =14906 -> 14906 | J37: =14907 -> 14907 | Q37: =SUM(E37:P37) -> 74532
A40: Growth | B40: Databricks Martech Platform Operations | C40: Neeraj | D40: Staff Aug | Q40: =SUM(E40:P40) -> 0 | R40: Candidate shortlisted by client. SOW start date Jan 2
A41: Growth | B41: Databricks Web Producers for Event Management (3 Swoogo developers) | C41: Neeraj | D41: Staff Aug | Q41: =SUM(E41:P41) -> 0 | R41: Start Date Feb. Team of 3 Web Producers for Event Management
A42: Growth | B42: Databricks Analyst for Insights (5 months) | C42: Neeraj | D42: Staff Aug | Q42: =SUM(E42:P42) -> 0
A43: LOST | B43: Polis Educational Solutions, Inc. | C43: Neeraj | D43: Project | Q43: =SUM(E43:P43) -> 0 | R43: Client's expecation was to spend too little and get the product developed. Not beneficial for NVISH to take it on..
A44: LOST | B44: Kubota Tractors | C44: Neeraj | D44: Staff Aug | Q44: =SUM(E44:P44) -> 0 | R44: Part time Consultant Architect with python, Azure, postgres background
A45: Growth | B45: Databricks Nintex Developer | C45: Neeraj | D45: Staff Aug | Q45: =SUM(E45:P45) -> 0 | R45: We are looking for Nintex developers for client round
A46: Growth | B46: UNDP | C46: Neeraj | D46: Project | Q46: =SUM(E46:P46) -> 0 | R46: Submitted SOW for fixed cost
A47: Growth | B47: RingCentral SEM landing pages creation | C47: Neeraj | D47: Project | Q47: =SUM(E47:P47) -> 0 | R47: SOW submitted for approval
A48: Growth | B48: UiPath Community and Forum maintenance | C48: Neeraj | D48: Staff Aug | Q48: =SUM(E48:P48) -> 0 | R48: One developer with expertise in Discourse and Front End
A49: SubTotal Confirmed + Growth | E49: =SUM(E8:E48) -> 491431 | F49: =SUM(F8:F48) -> 485186 | G49: =SUM(G8:G48) -> 460546 | H49: =SUM(H8:H48) -> 462799 | I49: =SUM(I8:I48) -> 317356 | J49: =SUM(J8:J48) -> 455307.38 | K49: =SUM(K8:K48) -> 491902 | L49: =SUM(L8:L48) -> 518684 | ... Q49: =SUM(Q8:Q48) -> 5854948.6
A51: Projection | B51: Inscopix
A52: Projection | B52: Neuron 7
A53: Projection | B53: Outsourcing4work GmBH
A54: Projection | B54: Serene Sleep
A55: Projection | B55: UNICEF
A56: Projection | B56: Vast Data
A57: SubTotal Projection | E57: =SUM(E51:E56) -> 0 | F57: =SUM(F51:F56) -> 0 | G57: =SUM(G51:G56) -> 0 | H57: =SUM(H51:H56) -> 0 | I57: =SUM(I51:I56) -> 0 | J57: =SUM(J51:J56) -> 0 | K57: =SUM(K51:K56) -> 0 | L57: =SUM(L51:L56) -> 0 | ... Q57: =SUM(Q51:Q56) -> 0
A59: Prospecting | B59: The Mom Project | C59: Raghu | Q59: =SUM(E59:P59) -> 0
A60: Prospecting | B60: Icon Parking | C60: Raghu | Q60: =SUM(E60:P60) -> 0
A61: Prospecting | B61: GalaxESystems | C61: Ram | Q61: =SUM(E61:P61) -> 0
A62: Prospecting | B62: Plume | C62: Neeraj | D62: Staff Aug
A63: Prospecting | B63: Extreme Networks | C63: Neeraj | D63: Project
A64: Prospecting | B64: 8x8 | C64: Neeraj | D64: Project
A65: Confirmed | B65: IDBS | C65: Neeraj | D65: Project | N65: 6000 | O65: 6000 | P65: 6000 | Q65: =SUM(E65:P65) -> 18000
A66: Confirmed | B66: YETI MY FRIEND | C66: Neeraj | D66: Staff Aug | L66: 3927 | M66: 6260 | N66: 5260 | O66: 6470 | P66: 7930 | Q66: =SUM(E66:P66) -> 29847
A67: Prospecting | B67: Moveworks | C67: Neeraj | D67: Project
A68: SubTotal Prospecting | E68: =SUM(E59:E67) -> 0 | F68: =SUM(F59:F67) -> 0 | G68: =SUM(G59:G67) -> 0 | H68: =SUM(H59:H67) -> 0 | I68: =SUM(I59:I67) -> 0 | J68: =SUM(J59:J67) -> 0 | K68: =SUM(K59:K67) -> 0 | L68: =SUM(L59:L67) -> 3927 | ... Q68: =SUM(Q59:Q67) -> 47847
B70: Secured | E70: =+E49 -> 491431 | F70: =+F49 -> 485186 | G70: =+G49 -> 460546 | H70: =+H49 -> 462799 | I70: =+I49 -> 317356 | J70: =+J49 -> 455307.38 | K70: =+K49 -> 491902 | L70: =+L49 -> 518684 | ... Q70: =+Q49 -> 5854948.6
B71: Projection | E71: =+E57 -> 0 | F71: =+F57 -> 0 | G71: =+G57 -> 0 | H71: =+H57 -> 0 | I71: =+I57 -> 0 | J71: =+J57 -> 0 | K71: =+K57 -> 0 | L71: =+L57 -> 0 | ... Q71: =+Q57 -> 0
B72: Prospecting | E72: =+E68 -> 0 | F72: =+F68 -> 0 | G72: =+G68 -> 0 | H72: =+H68 -> 0 | I72: =+I68 -> 0 | J72: =+J68 -> 0 | K72: =+K68 -> 0 | L72: =+L68 -> 3927 | ... Q72: =+Q68 -> 47847
B73: Solutions and Staff Augmentation Total | E73: =SUM(E70:E72) -> 491431 | F73: =SUM(F70:F72) -> 485186 | G73: =SUM(G70:G72) -> 460546 | H73: =SUM(H70:H72) -> 462799 | I73: =SUM(I70:I72) -> 317356 | J73: =SUM(J70:J72) -> 455307.38 | K73: =SUM(K70:K72) -> 491902 | L73: =SUM(L70:L72) -> 522611 | ... Q73: =SUM(Q70:Q72) -> 5902795.6
B75: Staffing
A76: Secured | B76: Conde Group, Inc. | C76: Wendy | D76: Staffing | E76: =10215.5 -> 10215.5 | F76: =10576 -> 10576 | G76: =10654 -> 10654 | H76: =11498 -> 11498 | I76: =10600 -> 10600 | J76: =9502 -> 9502 | K76: 10960 | L76: 10572 | M76: 8776 | N76: 9734 | O76: 7156 | P76: 7261 | Q76: =SUM(E76:P76) -> 117504.5
A77: Secured | B77: Evolutionary System Corp. | C77: Wendy | D77: Staffing | E77: =20930 -> 20930 | F77: =20778.4 -> 20778.4 | G77: =19320 -> 19320 | H77: =24323.5 -> 24323.5 | I77: =21712 -> 21712 | J77: =21119.89 -> 21119.89 | K77: 21712 | L77: 0 | M77: 0 | N77: 0 | O77: 0 | P77: 0 | Q77: =SUM(E77:P77) -> 149895.79
A78: Secured | B78: Hewlett Packard Enterprise Company | C78: Neeraj/Sunil | D78: Staffing | E78: 165961.36 | F78: 159336.44 | G78: 159341.96 | H78: 172073.44 | I78: 170155.6 | J78: 143954.96 | K78: 165136.79 | L78: 152318.4 | M78: 145485.8 | N78: 159707.08 | O78: 121577.96 | P78: 106520.69 | Q78: =SUM(E78:P78) -> 1821570.5
A79: Secured | B79: IDC Technologies Inc. | C79: Wendy | D79: Staffing | E79: =20071.08 -> 20071.08 | F79: =5227.32 -> 5227.32 | G79: 0 | H79: 0 | I79: 0 | J79: 0 | K79: 0 | L79: 0 | M79: 0 | N79: 0 | O79: 0 | Q79: =SUM(E79:P79) -> 25298.4
A80: Secured | B80: Infostretch Corporation | C80: Wendy | D80: Staffing | E80: =9600 -> 9600 | F80: =9600 -> 9600 | G80: =9900 -> 9900 | H80: =10740 -> 10740 | I80: =10560 -> 10560 | J80: =9600 -> 9600 | K80: 9600 | L80: 10560 | M80: 4320 | N80: 0 | O80: 0 | P80: 0 | Q80: =SUM(E80:P80) -> 84480
A81: Secured | B81: Johnson Service Group Inc. | C81: Wendy | D81: Staffing | E81: 8676 | F81: 8252 | G81: 10758 | H81: 8021 | I81: 7438.5 | J81: 7736 | K81: 12692 | L81: 10937 | M81: 8561 | N81: 6042 | O81: 5120 | P81: 4887 | Q81: =SUM(E81:P81) -> 99120.5
A82: Secured | B82: Match Point (WWT) | C82: Wendy | D82: Staffing | E82: 0 | F82: 0 | G82: 0 | H82: 0 | I82: 0 | J82: 0 | K82: 0 | L82: 0 | M82: 0 | N82: 14535 | O82: 10800 | P82: 14280 | Q82: 14960
A83: Secured | B83: Maxonic Inc. | C83: Wendy | D83: Staffing | E83: =127788 -> 127788 | F83: =125532 -> 125532 | G83: =62544 -> 62544 | H83: =39232 -> 39232 | I83: =30688 -> 30688 | J83: =27664 -> 27664 | K83: 40640 | L83: 47008 | M83: 54368 | N83: 69968 | O83: 52816 | P83: 55352 | Q83: =SUM(E83:P83) -> 733600
A84: Secured | B84: Red Oak Technologies | C84: Wendy | D84: Staffing | E84: =360 -> 360 | F84: =400 -> 400 | G84: =600 -> 600 | H84: =400 -> 400 | I84: =380 -> 380 | J84: 0 | K84: 0 | L84: 0 | M84: 0 | N84: 0 | O84: 0 | Q84: =SUM(E84:P84) -> 2140
A85: Secured | B85: The Mice Groups Inc | C85: Wendy | D85: Staffing | E85: 0 | F85: 0 | G85: =285 -> 285 | H85: =32.5 -> 32.5 | I85: 0 | J85: 0 | K85: 0 | L85: 0 | M85: 0 | N85: 0 | O85: 0 | Q85: =SUM(E85:P85) -> 317.5
A86: Secured | B86: Trans American Information Systems, Inc. | C86: Wendy | D86: Staffing | E86: =48216 -> 48216 | F86: =54056 -> 54056 | G86: =58688 -> 58688 | H86: =73128 -> 73128 | I86: =67856 -> 67856 | J86: =52272 -> 52272 | K86: 55680 | L86: 44984 | M86: 44984 | N86: 45104 | O86: 30936 | P86: 31536 | Q86: =SUM(E86:P86) -> 607440
A87: Secured | B87: VanderHouwen | C87: Wendy | D87: Staffing | E87: =60420 -> 60420 | F87: =34025.8 -> 34025.8 | G87: =53619.33 -> 53619.33 | H87: =55060 -> 55060 | I87: =56180 -> 56180 | J87: =51540 -> 51540 | K87: 50240 | L87: 54210 | M87: 52950 | N87: 63864.99 | O87: 49300 | P87: 49180 | Q87: =SUM(E87:P87) -> 630590.12
A88: Secured | B88: VDart Inc | C88: Wendy | D88: Staffing | E88: =8160 -> 8160 | F88: =9600 -> 9600 | G88: =10080 -> 10080 | H88: =10560 -> 10560 | I88: =10560 -> 10560 | J88: =8640 -> 8640 | K88: 9600 | L88: 8160 | M88: 7680 | N88: 11040 | O88: 9120 | P88: 10080 | Q88: =SUM(E88:P88) -> 113280
B89: Staffing Total | E89: =SUM(E76:E88) -> 480397.94 | F89: =SUM(F76:F88) -> 437383.96 | G89: =SUM(G76:G88) -> 395790.29 | H89: =SUM(H76:H88) -> 405068.44 | I89: =SUM(I76:I88) -> 386130.1 | J89: =SUM(J76:J88) -> 332028.85 | K89: =SUM(K76:K88) -> 376260.79 | L89: =SUM(L76:L88) -> 338749.4 | ... Q89: =SUM(Q76:Q88) -> 4400197.3
B91: Solutions, Staff Augmentation and Staffing Total | E91: =+E89+E73 -> 971828.94 | F91: =+F89+F73 -> 922569.96 | G91: =+G89+G73 -> 856336.29 | H91: =+H89+H73 -> 867867.44 | I91: =+I89+I73 -> 703486.1 | J91: =+J89+J73 -> 787336.23 | K91: =+K89+K73 -> 868162.79 | L91: =+L89+L73 -> 861360.4 | ... Q91: =+Q89+Q73 -> 10302993

Sheet Customer Meeting Prep
A1: Client Name | B1: Status | C1: Meeting time | D1: Current Deliverables | E1: Oppurtunites/Risks
A2: Aldevron | B2: Manjeet will be able to meet if he is in town | C2: Dec 8th meet at 3 PM
A3: Databricks | B3: Becca will be able to meet if she is in town and her work schedule permits. | C3: TBD | D3: 1. Website Support a. Web Production b. Accessibility, c. Management d. SEO, GEO​ 2. Marketing Operations a. Campaign Planning Support b. Campaign creation & Launch c. Workflow automation, Scripting c. Backend Management | E3: 1. We are currently supporting Web Production where as Web Development is owned by another team under Databricks. This is a growth oppurtunity 2. Analytics is another area where we can explore
A4: EGIA | B4: Eddie will be able to meet if he is not traveling. | C4: Dec 10th lunch at 1:15 PM at https://tadichgrillsf.com/ | D4: 1. Support for existing and new EGIA application change requests. 2. Design and manage scalable, optimized databases end-to-end. 3. Modernize applications with AI integration, tech stack upgrades, and improved UI/UX. 4. Enable secure data movement across systems via REST APIs and data pipelines. 5. Provide production support for all live applications and backend processes. | E4: The workload has increased significantly, so this is a good time to propose an expansion of the team. This will also ensure we maintain an appropriate resource backup and continuity plan.
A5: JSJ | B5: James is available to meet on 12/11 evening | C5: Dec 11th meet at 4 PM
A6: Molecular Devices | B6: Gianni is busy in December and has asked to schedule a video call sometime in January. | C6: Teams meeting in January
A7: Ring Central | B7: Yansu will be able to meet if she is in town and her work schedule permits. | C7: Yansu can only do Teams meeting on 12/10 from 9 AM to 9:30 AM
A8: UiPath | B8: Siva will be able to meet if he is not traveling | C8: TBD | D8: 1. Website Development a. Component cration b. Templates creation c. Page Authoring d. QA Automation 2. Website Analytics and Audit Reports 3. Translation | E8: 1. Creative Services 2. Marketing Operations a. Campaign Planning Support b. Campaign creation & Launch c. Workflow automation, Scripting c. Backend Management 3. SEO/GEO
A9: HAL
A10: HPE
A11: AAI

Sheet Sheet1

Sheet Sheet2
A1: Projects | B1: Resources | C1: Salary_$600 | D1: Monthly Revenue | E1: Margin | F1: Margin after appraisal
A2: Automation Anywhere Web Dev | B2: 10 | C2: 28150 | D2: 32922 | E2: 4772 | F2: 1394
A3: Bench | B3: 10 | C3: 19211 | D3: 0 | E3: 0 | F3: 0
A4: CBTS | B4: 1 | C4: 2057 | D4: 4800 | E4: 2743 | F4: 2496
A5: CheckPoint Desktop publishing of translated assets | B5: 1 | C5: 1555 | D5: 1999 | E5: 444 | F5: 258
A6: Chooch | B6: 1 | C6: 1818 | D6: 2100 | E6: 282 | F6: 64
A7: Church's Chicken & IT Support | B7: 1 | C7: 1882 | D7: 625 | E7: -1257 | F7: -1483
A8: Databricks - Martech Platform Operations Administrator | B8: 1 | C8: 2834 | D8: 4500 | E8: 1666 | F8: 1326
A9: Databricks Ongoing Support | B9: 17 | C9: 33160 | D9: 64150 | E9: 30990 | F9: 27011
A10: Databricks Planning Project | B10: 2 | C10: 3366 | D10: 5000 | E10: 1634 | F10: 1230
A11: Databricks Program Manager and Marketo | B11: 15 | C11: 55219 | D11: 84850 | E11: 29631 | F11: 23005
A12: Databricks SEO Project Management | B12: 2 | C12: 4240 | D12: 4500 | E12: 260 | F12: -249
A13: DevOps | B13: 1 | C13: 1843 | D13: 0 | E13: 0 | F13: 0
... A47: Grand Total | B47: 178 | C47: 409460 | D47: 482885 | E47: 73425 | F47: 24290

Sheet BD - MS
A1: Client | B1: Growth Oppurtunities | C1: Neeraj Comments | D1: Column1
A2: Automation Anywhere
A3: Databricks
A4: Hewlett Packard Enterprise
A5: UiPath | B5: No known growth opportunity
A6: RingCentral
A7: EGIA | B7: We are currently working for Rebate Administration and Processing business of EGIA and other mentioned areas are not with us. Rebate Administration & Processing AI base solutions to cut down the Application Processing time by processors. This reduces the Operational Cost and increase margin. Strategic team expansion to support sustained business growth and rising operational demands. Digital marketing EGIA blog Social media Marketing Email Marketing Website Development : Corporate Website: Egia.org socalwatersmar.com Learning Management System Contractor University: Online Courses & Resources for Business Coaching, Sales & Marketing Training & Technical Training. HVAC Distributor University: Online Courses & Resources for Business Coaching, Sales & Marketing Training & Technical Training for Distributor Contractor Network. Marketplace Contractor Only Marketplace: Discounted Products & Services to Run a Successful Contracting Business, listed by Companies looking for Increased Exposure and brand visibility. Please Note: In the management call with Edie, ChatBot was discussed, and subsequently Edie assigned this ChatBot integration task to the Nvish team, and the same has been delivered. | C7: They have a resource in USA who does their website, social, and web marketing? Or now they have engaged some other vendor?
A8: Hitachi America, Ltd. | B8: 1. Now that the migration of most of the important websites is being migrated to AEM, work with https://www.linkedin.com/in/masaki-tanaka-784941258/ and https://www.linkedin.com/in/sjcrouch/ to get a maintenance contract. 2. While migration SEO was not part of the scope. We need to work again with Hitachi Japan to see if AEO/GEO work can be granted 3. Hitachi is hiring a couple of employees in the Growth team led by https://www.linkedin.com/in/barirani/. Because of this, they are not going to use Campaign and designer from Nvish. Build a relationship with Arya so that he can look at Nvish as a partner. 4. Two websites still need to be migrated to AEM. Work with Simon and see if these too can be assigned to Nvish a. HIESA b. Hitachi marking and coding Hitachi US, Canada, Mexico , India , Singapore and Australia for Digital marketing or SEO | C8: Need to showcase our SEO/AEO/GEO skills either with some client implementation or implementation on our web properties. Did you check with Abhishek regarding HIESA and Hitachi Marking and coding migrations?
A9: LiveRamp
A10: SEMI
A11: Molecular Devices
A12: Icertis
B14: As a regular practice review the careers sections of each of our existing and ex-client to get insights and requirements so that we can define strategy to pitch to them.

Sheet BD - RM
B1: Activities | C1: Owner | D1: Status
B2: Support To Sales Team
B3: Provide narrative / positioning / thinking / context to be developed along with the requirement | C3: Sales Team
B4: Designing Marketing Collaterals & Marketing Material | C4: Marketing Team | D4: Ongoing
B5: Do Research, Site & Competitive Analysis to provide talking points to Sales Teams | C5: Marketing Team | D5: Ongoing
B6: Digital Marketing Campaigns on Metasys | C6: Marketing Team | D6: Ongoing
B8: Website | C8: Marketing Team
B9: Received the Figma Design for the Home and About Us page and we have shared our Feedback | D9: Done
B10: New content for Home page and About us page, also working on the content for other pages as well | D10: Ongoing
B11: Update the Website Banner | D11: Ongoing
B12: Add Newark, CA office address (39899 Balentine Dr, Newark, CA) to NVISH Contact Us page | D12: Done
B13: Home Page: Ensure the top-of-the-fold page talks about key skills and the offerings that are in discussion with potential customers. | D13: WIP
B14: Service Pages: Ensure that all key service pages have meaningul content and case studies. | D14: WIP
B15: Testimonials/Reviews: Upload Testimonials received on website after successful launch | D15: WIP
B17: Search Engine Optimization/GEO | C17: Marketing Team
B18: Working on the new pages i.e. AI, GEO, partnerships etc. | D18: WIP
B19: Competitor keyword gap analysis | D19: WIP
B20: AI competitive Research and Optimize the website for AI-driven search algorithms. | D20: WIP
B21: Breadcrumb structure with structured data | D21: WIP
